Workbook

Sheet Presupuestos
B3: PRESUPUESTO 2023 | H3: GASTADO EN PUBLICACIONES
H4: Año 1- 2023 | I4: =C8 -> 21306291
B5: PRESUPUESTO 2023 | C5: 21306291 | H5: Año 2- 2024 | I5: =C18 -> 20363281
B6: 17 pub. Inf. Avance 1-2023 | H6: Año 3- 2025 | I6: =I46 -> 38576153 | J6: al 15 de octubre 2025
B7: 11 financiadas | C7: 21306291
B8: Total gastado | C8: 21306291
B9: POR GASTAR | C9: =C5-C8 -> 0 | H9: TOTAL | I9: =SUM(I4:I6) -> 80245725
B12: al 15 de mayo 2025
B13: PRESUPUESTO 2024
B15: PRESUPUESTO UC-Inicial | C15: 36000000 | D15: PRESUPUESTO UCH | E15: 0
B16: PRESUPUESTO UC- Final | C16: 40385822
B17: 31 pub. Inf Avance 02-2024
B18: 10 financiadas (100%) 3 financiadas (50%) | C18: 20363281
B19: 8 pub. Inf Avance 03-2025
B20: 8 financiadas (100%) 1 financiadas (50%) | C20: 20022541
B21: Total gastado | C21: =C18+C20 -> 40385822 | E21: =E14-E17 -> 0
B22: POR GASTAR | C22: =C16-C21 -> 0 | E22: =E15-E18 -> 0
B25: al 15 de octubre 2025
B26: PRESUPUESTO 2025
B28: PRESUPUESTO UC-Inicial | C28: 30000000 | D28: PRESUPUESTO UCH | E28: 0
B29: PRESUPUESTO UC- Final | C29: 22000000 | F29: 8 publicaciones fueron financiadas con fondos 2024
B30: 48 pub. Inf Avance 03-2025
B31: 6 financiadas (100%) 1 financiadas (50%) | C31: =' Publicaciones año 3'!Z91 -> 18553612
B33: xx financiadas (100%) xx financiadas (50%)
B34: Total gastado | C34: =C31+C33 -> 18553612 | D34: POR GASTAR | E34: =E27-E30 -> 0
B35: POR GASTAR | C35: =C29-C34 -> 3446388 | E35: =E28-E31 -> 0
H37: Actualización : 15 octubre 2025
H39: PUBLICACIONES FINANCIADAS 2025
H41: 48 publicaciones informadas en Inf Avance 03-2025
H42: PRESUPUESTO UC | J42: PRESUPUESTO UCH
I43: Monto pagado
H44: 8 publicaciones financiadas (Fdos. 2024) | I44: =C20 -> 20022541 | K44: 0
H45: 6 publicaciones financiadas (Fdos. 2025) | I45: =C31 -> 18553612
H46: Total gastado | I46: =SUM(I44:I45) -> 38576153
H48: Presupuesto asignado 2025 | I48: 20000000
H49: 6 publicaciones financiadas (Fdos.2025) | I49: =C31 -> 18553612
H50: SALDO POR GASTAR | I50: =I48-I49 -> 1446388
H52: Solicitudes
H53: Susana Mondschein (sale de su ppto WP4)

Sheet Resumen publicaciones
B4: PUBLICACIONES CIENTIFICAS
B6: PUBLICACIONES | D6: Q1 | E6: % Q1 | F6: Promedio JIF | G6: Top 10% | H6: Instituciones Internacionales | I6: Instituciones Nacionales
B7: 2023 | C7: 17 publicaciones | D7: =COUNTIFS(' Publicaciones año 1'!$F$8:$F$25,"Q1") -> 9 | E7: =D7/17 -> 0.52941176 | F7: 4.3 | G7: 6 | H7: =' Publicaciones año 1'!Q25 -> 9 | I7: =' Publicaciones año 1'!S25 -> 13
B8: 2024 | C8: 31 publicaciones | D8: =COUNTIFS(' Publicaciones año 2'!$F$7:$F$38,"Q1") -> 17 | E8: =D8/31 -> 0.5483871 | F8: 4.8 | G8: 11 | H8: =' Publicaciones año 2'!O38 -> 16 | I8: =' Publicaciones año 2'!Q38 -> 19
B9: 2025 | C9: 65 publicaciones | D9: =COUNTIFS(' Publicaciones año 3'!$G$8:$G$182,"Q1") -> 27 | E9: =D9/48 -> 0.5625 | F9: =' Publicaciones año 3'!H89 -> 4.8359375 | G9: =' Publicaciones año 3'!I89 -> 13 | H9: =' Publicaciones año 3'!L90 -> 38 | I9: =' Publicaciones año 3'!N90 -> 44 | J9: al 07 de noviembre 2025

Sheet Resumen publ por WP
B1: AÑO 1 - 2023
I2: PUBLICACIONES ASOCIATIVAS
B3: PUBLICACIONES ASOCIATIVAS | I3: AÑO 1 - 2023 | J3: AÑO 2 -2024 | K3: AÑO 3 -2025
C4: AÑO 1 - 2023 | H4: Total publicaciones | I4: 17 | J4: 31 | K4: 48 | L4: hasta el 17 de octubre
B5: Total publicaciones | C5: 17 | H5: Pub. Asociativas | I5: =F16 -> 3 | J5: =F49 -> 8 | K5: =F78 -> 13
B6: Pub. Asociativas | C6: =' Publicaciones año 1'!E25 -> 3 | H6: % Asociatividad | I6: =I5/I4 -> 0.17647059 | J6: =J5/J4 -> 0.25806452 | K6: =K5/K4 -> 0.27083333
B7: % Asociatividad | C7: =C6/C5 -> 0.17647059
B10: PUBLICACIONES NO ASOCIATIVAS | E10: PUBLICACIONES ASOCIATIVAS
B12: WP | C12: AÑO 1 - 2023 | E12: WP | F12: AÑO 1 - 2023
B13: WP-1 | C13: =COUNTIFS(' Publicaciones año 1'!$D$8:$D$24,"1") -> 0 | E13: WP 1-2 | F13: 1
B14: WP-2 | C14: =COUNTIFS(' Publicaciones año 1'!$D$8:$D$24,"2") -> 4 | E14: WP 2-3 | F14: 1
B15: WP-3 | C15: =COUNTIFS(' Publicaciones año 1'!$D$8:$D$24,"3") -> 5 | E15: WP 2-4 | F15: 1
B16: WP-4 | C16: =COUNTIFS(' Publicaciones año 1'!$D$8:$D$24,"4") -> 2 | E16: TOTAL | F16: =SUM(F13:F15) -> 3
B17: WP-5 | C17: =COUNTIFS(' Publicaciones año 1'!$D$8:$D$24,"5") -> 3
B18: TOTAL | C18: =SUM(C13:C17) -> 14
B21: Presupuesto Año 1 - 2023
B22: WP | C22: Ppto WP- 2023
B23: WP-1 | C23: 64000000
B24: WP-2 | C24: 150000000
B25: WP-3 | C25: =80000000+150000000 -> 230000000 | E25: * incluye M$150.000
B26: WP-4 | C26: 90000000
B27: WP-5 | C27: 80000000
B28: TOTAL | C28: =SUM(C23:C27) -> 614000000
B32: AÑO 2 - 2024
B34: PUBLICACIONES ASOCIATIVAS
C35: AÑO 2 - 2024
B36: Total publicaciones | C36: 31
B37: Pub. Asociativas | C37: =' Publicaciones año 2'!E38 -> 8
B38: % Asociatividad | C38: =C37/C36 -> 0.25806452
B41: PUBLICACIONES NO ASOCIATIVAS | E41: PUBLICACIONES ASOCIATIVAS
B43: WP | C43: AÑO 2 -2024 | E43: WP | F43: AÑO 2 -2024
B44: WP-1 | C44: =COUNTIFS(' Publicaciones año 2'!$D$7:$D$37,"1") -> 2 | E44: WP 2-3 | F44: 3
B45: WP-2 | C45: =COUNTIFS(' Publicaciones año 2'!$D$7:$D$37,"2") -> 8 | E45: WP 2-4 | F45: 1
B46: WP-3 | C46: =COUNTIFS(' Publicaciones año 2'!$D$7:$D$37,"3") -> 7 | E46: WP 2-5 | F46: 1
B47: WP-4 | C47: =COUNTIFS(' Publicaciones año 2'!$D$7:$D$37,"4") -> 5 | E47: WP 4-5 | F47: 1
B48: WP-5 | C48: =COUNTIFS(' Publicaciones año 2'!$D$7:$D$37,"5") -> 1 | E48: WP 2-4-5 | F48: 2
B49: TOTAL | C49: =SUM(C44:C48) -> 23 | E49: TOTAL | F49: =SUM(F44:F48) -> 8
B52: Presupuesto Año 2 - 2024
B53: WP | C53: Ppto WP- 2024
B54: WP-1 | C54: 97219824
B55: WP-2 | C55: 133000000
B56: WP-3 | C56: 70000000
B57: WP-4 | C57: 78800000
B58: WP-5 | C58: 120000000
B59: TOTAL | C59: =SUM(C54:C58) -> 499019824
B62: AÑO 3 - 2025
B64: PUBLICACIONES ASOCIATIVAS
C65: AÑO 3 - 2025
B66: Total publicaciones | C66: =C79+F78 -> 65
B67: Pub. Asociativas | C67: =' Publicaciones año 3'!F89 -> 13
B68: % Asociatividad | C68: =C67/C66 -> 0.2
B71: PUBLICACIONES NO ASOCIATIVAS | E71: PUBLICACIONES ASOCIATIVAS
B73: WP | C73: AÑO 3 -2025 | E73: WP | F73: AÑO 3 -2025
B74: WP-1 | C74: =COUNTIFS(' Publicaciones año 3'!$E$8:$E$93,"1") -> 5 | E74: WP 1-3 | F74: 1
B75: WP-2 | C75: =COUNTIFS(' Publicaciones año 3'!$E$8:$E$93,"2") -> 27 | E75: WP 2-3 | F75: 10
B76: WP-3 | C76: =COUNTIFS(' Publicaciones año 3'!$E$8:$E$93,"3") -> 13 | E76: WP 2-4 | F76: 1
B77: WP-4 | C77: =COUNTIFS(' Publicaciones año 3'!$E$8:$E$93,"4") -> 6 | E77: WP 2-5 | F77: 1
B78: WP-5 | C78: =COUNTIFS(' Publicaciones año 3'!$E$8:$E$93,"5") -> 1 | E78: TOTAL | F78: =SUM(F74:F77) -> 13
B79: TOTAL | C79: =SUM(C74:C78) -> 52
B82: Presupuesto Año 3 - 2025
B83: WP | C83: Ppto WP- 2025
B84: WP-1 | C84: 80090000
B85: WP-2 | C85: 141500000
B86: WP-3 | C86: 93000000
B87: WP-4 | C87: 93000000
B88: WP-5 | C88: 100000000
B89: TOTAL | C89: =SUM(C84:C88) -> 507590000

Sheet Publicaciones año 4-2026
J2: REGISTRO DE PUBLICACIONES
J4: INFORMADO A ANID - INFORME DE AVANCE NR. 4
J5: 2026
B7: Nr. | C7: Año Publicación | D7: WP | E7: WP consignado | F7: Nt pub con otros WP | G7: WOS Q1-Q4 (2024) | H7: Factor de impacto (2024) | I7: Top 10% | J7: Nombre publicación | K7: Autores | L7: Nro. Inst. Internacionales | M7: Publicación con Institución Internacional | N7: Nro. Inst. Nacionales | O7: Publicación con Institución Nacional | P7: Objetivo Directo/ Asociado CECAN (Identifíquelo Ej: WP-1 proyecto 1) | Q7: Funding % | R7: Estado de la Publicación | S7: Fecha estimada de publicación (En preparación/enviada) | T7: Invoice Nr. | U7: Fecha Invoice | V7: Revista | W7: Financiamiento CECAN | X7: Solicitud de apoyo solicitado por | Y7: Nr. Solicitud de apoyo | Z7: Valor Publicación revista | AA7: Valor $ pagado por UC | AB7: Valor $ pagado por UCH | AC7: 20000000 | AD7: 0 | AE7: Fecha de publicación | AF7: Volúmen. Pág. Inicio y final | AG7: DOI | AH7: ISSN | AI7: Nr. Productividad | AJ7: Link paper | AK7: Informado en Informe de Avance
B8: 50 | C8: 2025 | D8: 5-2 | E8: 10 | F8: 1 | G8: Q2 | H8: 4.4 | J8: Potential Impact of Compound Bayesian Inference in Medicine: Application to Colonoscopy Prioritization | K8: Pierre Collet 1,2,3,*, Felipe Quezada-Diaz 2,3 and Carla Taramasco 1,2,3 | L8: 0 | N8: 1 | O8: ITISB, Facultad de Ingeniería, Universidad Andres Bello, Viña del Mar, Chile 2520000, Chile; pierre.collet@ unab.cl, c1arla.taramasco@unab.cl 2 Unidad de Coloproctología. Servicio de Cirugía. Complejo Asistencial Doctor Sotero del Rio. Santiago 8550000, Chile; ffquezad@gmail.com 3 Centro para la Prevención y Control del Cáncer (CECAN) | T8: 3906851 | U8: 45964 | V8: Cancers | X8: Carla Taramasco | Y8: 14-2025 | Z8: USD 3255,52 | AA8: 3076890
B9: 49 | C9: 2025 | D9: 2 | E9: 2 | J9: Impact of a curriculum reform in graduate students self-reported palliative care competencies | K9: Mónica Grez A. MD (1) ; Alfredo Rodríguez-Nunez MD (1) ; Armando Maldonado-Morgado MD (1) ; Felipe Castro MD (2) ; Nicolás Orozco MD (2) ; Luciana Crispino MD (1) ; Francisca Villouta MD (1) ; Carolina Jaña MD(1) ; Ofelia Leiva-Vásquez MD (1) ; Pedro E. Pérez-Cruz MD MPH | L9: 0 | N9: 0 | O9: (1) Section of Palliative Medicine, School of Medicine, Pontificia Universidad Católica de Chile (UC|Chile), Santiago, Chile. (2) Students, School of Medicine, UC|Chile, Santiago, Chile. (3) Center for Cancer Prevention and Control (CECAN). | V9: Journal of Pain and Sumptom Management

Sheet  Publicaciones año 3
J2: REGISTRO DE PUBLICACIONES | AD2: ENVIAR PDF DE LA PUBLICACION A ccabrerav@uc.cl con copia a cgoicb@uc.cl y a cecan@uc.cl
J4: INFORMADO A ANID - INFORME DE AVANCE NR. 3
J5: 2025 | AD5: Los casilleros de este color deben ser llenados cuando la publicacion se haya relizado
D6: Completar para solicitud de financiamiento | AB6: Saldo UC | AC6: Saldo UCH | AD6: COMPLETAR CUANDO EL PAPER HA SIDO PUBLICADO
B7: Nr. | C7: Año Publicación | D7: WP | E7: WP consignado | F7: Nt pub con otros WP | G7: WOS Q1-Q4 (2024) | H7: Factor de impacto (2024) | I7: Top 10% | J7: Nombre publicación | K7: Autores | L7: Nro. Inst. Internacionales | M7: Publicación con Institución Internacional | N7: Nro. Inst. Nacionales | O7: Publicación con Institución Nacional | P7: Funding % | Q7: Estado de la Publicación | R7: Fecha estimada de publicación (En preparación/enviada) | S7: Invoice Nr. | T7: Fecha Invoice | U7: Revista | V7: Financiamiento CECAN | W7: Solicitud de apoyo solicitado por | X7: Nr. Solicitud de apoyo | Y7: Valor Publicación revista | Z7: Valor $ pagado por UC | AA7: Valor $ pagado por UCH | AB7: 20000000 | AC7: 0 | AD7: Fecha de publicación | AE7: Volúmen. Pág. Inicio y final | AF7: DOI | AG7: ISSN | AH7: Nr. Productividad | AI7: Link paper | AJ7: Informado en Informe de Avance
B8: 1 | C8: 2024 | D8: 3 | E8: 3 | G8: Q3 | H8: 1.5 | J8: Alpha-Lipoic Acid-Mediated Inhibition of LTB4 Synthesis Suppresses Epithelial-Mesenchymal Transition, Modulating Functional and Tumorigenic Capacities in Non-Small Cell Lung Cancer A549 Cells | K8: María José Torres, PhD, Juan Carlos Ríos, PhD ,Alexandra Valle, MSc , Sebastián Indo, PhD , Kevin Brockway GV, MSc, Fernanda López-Moncada, Mario Faúndez, PhD, Enrique A. Castellón, PhD, Héctor R. Contreras | L8: 0 | N8: 1 | O8: 1 Laboratorio de Farmacología y Toxicología Molecular. Escuela de Química y Farmacia. Facultad de Química y de Farmacia. Pontificia Universidad Católica de Chile, Santiago, Chile. 2 Programa de Farmacología y Toxicología. Facultad de Medicina. Pontificia Universidad Católica de Chile, Santiago, Chile. 3 Laboratorio de Oncología Celular y Molecular. Departamento de Oncología Básico-Clínica. Facultad de Medicina. Universidad de Chile, Santiago, Chile. 4 Departamento de Tecnología Médica. Facultad de Medicina. Universidad de Chile, Santiago, Chile. 5 Escuela de Tecnología Médica. Universidad Austral de Chile, Puerto Montt, Chile. 6 Centro para la Prevención y el Control del Cáncer (CECAN), Santiago, Chile. 7 Departamento de Laboratorios Clínicos. Facultad de Medicina. Pontificia Universidad Católica de Chile, Santiago, Chile. | P8: 100 | Q8: Publicado | S8: OAD0000507291 | T8: 45624 | U8: Current Therapeutic Research | V8: 1 | W8: Enrique Castellón | X8: 15-2024 | Y8: USD 2460 | Z8: =2460*972.43 -> 2392177.8 | AB8: Pagado con fondos 2024 | AD8: 45625 | AE8: Vol.102 | AF8: https://doi.org/10.1016/j.curtheres.2024.100765
B9: 2 | C9: 2024 | D9: 2-3 | E9: 10 | F9: 1 | G9: Q1 | H9: 4.6 | I9: 0 | J9: A snapshot of cancer in Chile II: an update on research, strategies and analytical frameworks for equity, innovation and national development | K9: Cristóbal Vacarezza, Julieta Araneda, Pamela Gonzalez, Oscar Arteaga, Katherine Marcelain, Enrique A Castellon, Ana Periera, Maroun Khoury, Bettina Müller, Juan Alberto Lecaros, Sofia P Salas, Arnoldo Riquelme, Alejandro H Corvalan, Jorge Jiménez de la Jara, Catterina Ferreccio, Carolina Goic, Bruno Nervi, Juan Carlos Roa, Gareth I Owen | L9: 0 | N9: 1 | O9: 1- Servicio de Salud del Reloncavi, Esmeralda 269, Puerto Montt, 2-Faculty of Health and Odontology, Universidad Diego Portales, Santiago, 3- Millennium Institute on Immunology and Immunotherapy, Santiago; 4-Institute of Nutrition and Food Technology (INTA), University of Chile, 5-Laboratory of Nano‑Regenerative Medicine, Faculty of Medicine, Universidad de Los Andes, Santiago; 6- IMPACT‑ Center of Interventional Medicine for Precision and Advanced Cellular Therapy, Universidad de Los Andes, Santiago, 7- Center for Bioethics,Faculty of Medicine, Clinica Alemana, Universidad del Desarrollo Santiago, 8- Chilean Cooperative Group for Oncological Research (GOCCHI), Santiago, 9- National Cancer Institute, Santiago, 10- Bioethics and Law Observatory, 11-Institute of Sciences and Innovation in Medicine, Universidad del Desarrollo, Santiago, 12- Advanced Center for Chronic Diseases (FONDAP‑ACCDiS), 13- National Cancer Commission, Santiago | P9: 100 | Q9: Publicado | S9: 1452808303 | T9: 45577 | U9: Biological Research | V9: 1 | W9: Gareth Owen | X9: 16-2024 | Y9: USD 2307 | Z9: =2307*975.67 -> 2250870.7 | AB9: Pagado con fondos 2024 | AD9: 45644 | AF9: https://doi.org/10.1186/s40659-024-00574-2
B10: 3 | C10: 2024 | D10: 2-3 | E10: 10 | F10: 1 | G10: Q2 | H10: 4.4 | J10: Inbreeding and Gallbladder Cancer Risk: Homozygosity Associations Adjusted for Indigenous American Ancestry, BMI, and Genetic Risk of Gallstone Disease | K10: Francisco Ceballos 1,2,* , Felix Boekstegers 1 Katherine Marcelain 3 , Dominique Scherer 1 , Carol Barahona Ponce 1 , Valentina Gárate-Calderón 1,3, Melanie Waldenberger 4 , , Erik Morales 5,6, Armando Rojas 6 , César Munoz 5,6, Javier Retamales 7 Olga Barajas 3,10, María Teresa Rivera 11 , Gonzalo de Toro 8,9 , Allan Vera Kortmann 8 , , Analía Cortés 11, Denisse Loader 12, Javiera Saavedra 12, Lorena Gutiérrez 13, Alejandro Ortega 14, Maria Enriqueta Bertrán 15, Leonardo Bartolotti 16, Fernando Gabler 17, Mónica Campos 17, Juan Alvarado 18, Fabricio Moisán 18, Loreto Spencer 18, Bruno Nervi 19 , Daniel Carvajal-Hausdorf 20, Héctor Losada 21 Pamela Salinas 25 , Mauricio Almau 22, Plinio Fernández 22, Jordi Olloquequi 23,24 andJustoLorenzoBermejo 1,26, | L10: 1 | M10: 1 Statistical Genetics Research Group, Institute of Medical Biometry, Heidelberg University, Im Neuenheimer Feld 130.3, 69120 Heidelberg, Germany; boekstegers@imbi.uni-heidelberg.de (F.B.); scherer@imbi.uni-heidelberg.de (D.S.); barahona@imbi.uni-heidelberg.de (C.B.P.); garate@imbi.uni-heidelberg.de (V.G.-C.) 2 Health Institute Carlos III (ISCIII), 28029 Madrid, Spain 3 Department of Basic and Clinical Oncology, Center for Cancer Prevention and Control (CECAN), Medical Faculty, University of Chile, Santiago 380000, Chile; kmarcelain@uchile.cl (K.M.); obarajas@hcuch.cl (O.B.) 4 Research Unit of Molecular Epidemiology and Institute of Epidemiology, Helmholtz Zentrum München, German Research Center for Environmental Health, 85764 Neuherberg, Germany; waldenberger@helmholtz-muenchen.de 5 Hospital Regional de Talca, Talca 3460000, Chile; emoralesm@hospitaldetalca.cl (E.M.); cmunozc@hospitaldetalca.cl (C.M.) 6 Facultad de Medicina, Universidad Católica del Maule, Talca 3460000, Chile; arojasr@ucm.cl 7 Instituto Nacional del Cáncer, Santiago 7500650, Chile; jretamales@gocchi.org 8 Hospital de Puerto Montt, Puerto Montt 5480000, Chile; gonzalo.detoro@uach.cl (G.d.T.); allan.vera@araucanianorte.cl (A.V.K.) 9 Escuela de Tecnología Médica, Universidad Austral de Chile sede Puerto Montt, Puerto Montt 5480000, Chile 10 Hospital Clínico Universidad de Chile, Santiago 8380456, Chile 11 Hospital del Salvador, Santiago 7500922, Chile; mrivera@hsalvador.cl (M.T.R.); acortes@hsalvador.cl (A.C.) 12 Hospital Padre Hurtado, Santiago 8880456, Chile; dloader@hurtadohosp.cl (D.L.); javiera.saavedra@hurtadohosp.cl (J.S.) 13 Hospital San Juan de Dios, Santiago 8320000, Chile; lorenaf.gutierrez@redsalud.gob.cl 14 Hospital Regional, Arica 1000000, Chile; alejandro.ortega@hjnc.cl 15 Unidad Registro Hospitalario de Cáncer, Hospital Base de Valdivia, Valdivia 5090146, Chile; enriqueta.bertran@redsalud.gov.cl 16 Hospital Base de Valdivia, Valdivia 5090146, Chile; leonardo.bartolotti@redsalud.gob.cl 17 Hospital San Borja Arriarán, Santiago 8320000, Chile; gablerf@uchile.cl (F.G.); monicam.camposm@redsalud.gob.cl (M.C.) 18 Hospital Regional Guillermo Grant Benavente, Concepción 4070386, Chile; jualvarado@udec.cl (J.A.); fabriziomoisan@udec.cl (F.M.); mspencer@udec.cl (L.S.) 19 Department of Hematology and Oncology, Center for Cancer Prevention and Control (CECAN), School of Medicine, Pontificia Universidad Católica de Chile, Santiago 8330077, Chile; bnervi@uc.cl 20 Facultad de Medicina, Clínica Alemana Universidad del Desarrollo, Santiago 7650568, Chile; carvajalh.daniel@gmail.com 21 Departamento de Cirugía, Universidad de La Frontera, Temuco 4780000, Chile; hector.losada@ufrontera.cl 22 Hospital de Rancagua, Rancagua 2820000, Chile; halmau@clinicaisamedica.cl (M.A.); pfernandez@clinicaisamedica.cl (P.F.) 23 Department of Biochemistry and Physiology, Faculty of Pharmacy and Food Sciences, University of Barcelona, 08007 Barcelona, Spain; jordiolloquequi@ub.edu 24 Facultad de Ciencias de la Salud, Universidad Autónoma de Chile, Talca 3460000, Chile 25 Instituto de Alta Investigación, Tarapacá University, Arica 1000000, Chile; psalinas@gestion.uta.cl 26 Laboratory of Biostatistics for Precision Oncology, Institut de Cancérologie Strasbourg Europe, 67200 Strasbourg, France | N10: 1 | O10: 1 Statistical Genetics Research Group, Institute of Medical Biometry, Heidelberg University, Im Neuenheimer Feld 130.3, 69120 Heidelberg, Germany; boekstegers@imbi.uni-heidelberg.de (F.B.); scherer@imbi.uni-heidelberg.de (D.S.); barahona@imbi.uni-heidelberg.de (C.B.P.); garate@imbi.uni-heidelberg.de (V.G.-C.) 2 Health Institute Carlos III (ISCIII), 28029 Madrid, Spain 3 Department of Basic and Clinical Oncology, Center for Cancer Prevention and Control (CECAN), Medical Faculty, University of Chile, Santiago 380000, Chile; kmarcelain@uchile.cl (K.M.); obarajas@hcuch.cl (O.B.) 4 Research Unit of Molecular Epidemiology and Institute of Epidemiology, Helmholtz Zentrum München, German Research Center for Environmental Health, 85764 Neuherberg, Germany; waldenberger@helmholtz-muenchen.de 5 Hospital Regional de Talca, Talca 3460000, Chile; emoralesm@hospitaldetalca.cl (E.M.); cmunozc@hospitaldetalca.cl (C.M.) 6 Facultad de Medicina, Universidad Católica del Maule, Talca 3460000, Chile; arojasr@ucm.cl 7 Instituto Nacional del Cáncer, Santiago 7500650, Chile; jretamales@gocchi.org 8 Hospital de Puerto Montt, Puerto Montt 5480000, Chile; gonzalo.detoro@uach.cl (G.d.T.); allan.vera@araucanianorte.cl (A.V.K.) 9 Escuela de Tecnología Médica, Universidad Austral de Chile sede Puerto Montt, Puerto Montt 5480000, Chile 10 Hospital Clínico Universidad de Chile, Santiago 8380456, Chile 11 Hospital del Salvador, Santiago 7500922, Chile; mrivera@hsalvador.cl (M.T.R.); acortes@hsalvador.cl (A.C.) 12 Hospital Padre Hurtado, Santiago 8880456, Chile; dloader@hurtadohosp.cl (D.L.); javiera.saavedra@hurtadohosp.cl (J.S.) 13 Hospital San Juan de Dios, Santiago 8320000, Chile; lorenaf.gutierrez@redsalud.gob.cl 14 Hospital Regional, Arica 1000000, Chile; alejandro.ortega@hjnc.cl 15 Unidad Registro Hospitalario de Cáncer, Hospital Base de Valdivia, Valdivia 5090146, Chile; enriqueta.bertran@redsalud.gov.cl 16 Hospital Base de Valdivia, Valdivia 5090146, Chile; leonardo.bartolotti@redsalud.gob.cl 17 Hospital San Borja Arriarán, Santiago 8320000, Chile; gablerf@uchile.cl (F.G.); monicam.camposm@redsalud.gob.cl (M.C.) 18 Hospital Regional Guillermo Grant Benavente, Concepción 4070386, Chile; jualvarado@udec.cl (J.A.); fabriziomoisan@udec.cl (F.M.); mspencer@udec.cl (L.S.) 19 Department of Hematology and Oncology, Center for Cancer Prevention and Control (CECAN), School of Medicine, Pontificia Universidad Católica de Chile, Santiago 8330077, Chile; bnervi@uc.cl 20 Facultad de Medicina, Clínica Alemana Universidad del Desarrollo, Santiago 7650568, Chile; carvajalh.daniel@gmail.com 21 Departamento de Cirugía, Universidad de La Frontera, Temuco 4780000, Chile; hector.losada@ufrontera.cl 22 Hospital de Rancagua, Rancagua 2820000, Chile; halmau@clinicaisamedica.cl (M.A.); pfernandez@clinicaisamedica.cl (P.F.) 23 Department of Biochemistry and Physiology, Faculty of Pharmacy and Food Sciences, University of Barcelona, 08007 Barcelona, Spain; jordiolloquequi@ub.edu 24 Facultad de Ciencias de la Salud, Universidad Autónoma de Chile, Talca 3460000, Chile 25 Instituto de Alta Investigación, Tarapacá University, Arica 1000000, Chile; psalinas@gestion.uta.cl 26 Laboratory of Biostatistics for Precision Oncology, Institut de Cancérologie Strasbourg Europe, 67200 Strasbourg, France | Q10: Publicado | U10: Cancers | V10: 0 | W10: No | AD10: 45643 | AF10: https://doi.org/10.3390/cancers16244195
B11: 4 | C11: 2025 | D11: 4 | E11: 4 | G11: Q1 | H11: 3.6 | I11: 1 | J11: Perceived barriers to reaching equity in effective access to diagnosis and treatment for women with breast cancer in Chile | K11: Campaña, C, Cabieses, B, Obach, A, Vezzani, F | L11: 0 | N11: 0 | P11: 100 | Q11: Publicado | S11: 1452824357 | T11: 45717 | U11: Humanities and Social Sciences Communications | V11: 1 | W11: Báltica Cabieses | X11: 17-2024 | Y11: USD 1765 | Z11: =1765*1007.51 -> 1778255.1 | AB11: Pagado con fondos 2024 | AD11: 45693 | AF11: https://doi.org/10.1057/s41599-024-04259-9
B12: 5 | C12: 2025 | D12: 2-3 | E12: 10 | F12: 1 | G12: Q1 | H12: 5.1 | I12: 0 | J12: Comprehensive histopathological analysis of gastric cancer in European and Latin America populations reveals differences in PDL1, HER2, p53 and MUC6 expression | K12: Carolina Martínez‑Ciarpaglini1 · Rita Barros2,3,4,5 · Carmelo Caballero6 · Hugo Boggino6 · Lorena Alarcón‑Molero1,7 · Bárbara Peleteiro8,9,10,11 · Erika Ruiz‑García12,13 · Edith Fernandez‑Figueroa14 · Roberto Herrera‑Goepfert15 · Consuelo Díaz‑Romero16 · Rui Ferreira2,17 · Tessa S. Groen‑van Schooten18,19,20 · Cinthia Gauna21 · Rita Pereira21 · Daniel Cantero22 · Horacio Lezcano23 · Federico Esteso24 · Juan O´Connor24 · Arnoldo Riquelme25 · Gareth I. Owen26 · Marcelo Garrido27 · Juan Carlos Roa28 · Fiorella Ruiz‑Pace29 · Ana Vivancos30 · Marc Diez‑García31 · Maria Alsina31,32 · Judit Matito30 · Agatha Martin30 · Marina Gómez30 · Ester Castillo30 · Maria Vila30 · João Santos‑Antunes33 · Andreia Costa34 · Florian Lordick35 · Judith Farrés36 · Brenda Palomar‑De Lucas37 · Manuel Cabeza‑Segura37 · Rosanna Villagrasa38 · Elena Jimenez‑Martí37 · Ana Miralles‑Marco37 · Rodrigo Dienstmann29 · Sarah Derks18,19,20 · Ceu Figueiredo2,3,4 · Andrés Cervantes37,38,39 · Fátima Carneiro2,3,4,5 · Tania Fleitas‑Kanonnikoff37 | L12: 1 | M12: 1 Department of Pathology, Hospital Clinico Universitario, INCLIVA, Biomedical Research Institute, University of Valencia, Valencia, Spain 2 Ipatimup, Institute of Molecular Pathology and Immunology of the University of Porto, Rua Júlio Amaral de Carvalho 45, 4200 ‑135 Porto, Portugal 3 i3S‑Instituto de Investigação e Inovação em Saúde, Universidade Do Porto, Porto, Portugal 4 Faculty of Medicine of the University of Porto, Porto, Portugal 5 Department of Pathology, Unidade Local de Saúde São João, Porto, Portugal 6 Department of Pathology, GENPAT, Asunción, Paraguay 7 Department of Pathology, Hospital General de Valdepeñas, Valdepeñas, Spain 8 Hospital Epidemiology Center, University Hospital Center of São João, Porto, Portugal 9 Department of Public Health and Forensic Sciences, and Medical Education, Faculty of Medicine, University of Porto, Porto, Portugal 10 EPIUnit‑Institute of Public Health, University of Porto, Porto, Portugal 11 Laboratory for Integrative and Translational Research in Population Health (ITR), University of Porto, Porto, Portugal 12 Departamento de Tumores de Tubo Digestivo, Instituto Nacional de Cancerología, Mexico City, México 13 Laboratorio de Medicina Traslacional, Instituto Nacional de Cancerología, Mexico City, México 14 Núcleo B de Innovación en Medicina de Precisión, Instituto Nacional de Medicina Genómica, Mexico City, México 15 Departamento de Patología Quirúrgica, Instituto Nacional de Cancerología, Mexico City, México 16 Departamento de Oncología Médica, Instituto Nacional de Cancerología, Mexico City, México 17 Microbes & Cancer. i3S, Instituto de Investigação e Inovação em Saúde, , Rua Alfredo Allen, 208, 4200‑135 Porto, Portugal 18 Department of Medical Oncology, Amsterdam University Medical Center (UMC) Location Vrije Universiteit Amsterdam, Amsterdam, Netherlands 19 Cancer Biology and Immunology, Cancer Center Amsterdam, Amsterdam, Netherlands 20 Oncode Institute, Amsterdam, The Netherlands 21 Medical Oncology Department, Instituto de Previsión Social, Asunción, Paraguay 22 Department of Gastroenterology, Instituto de Previsión, Social, Asunción, Paraguay 23 Pathology Department, Instituto de Previsión Social, Asunción, Paraguay 24Oncology Data Science, Valld`Hebron Institute of Oncology, Barcelona, Spain 30 Cancer Genomics Lab, Valld`Hebron Institute of Oncology, Barcelona, Spain 31 Medical Oncology Department, Valld`Hebron Institute of Oncology, Barcelona, Spain 32 Hospital Universitario de Navarra, Navarrabiomed-IdiSNA, Pamplona, Spain 33 Department of Gastroenterology, Unidade Local de Saúde São João, Porto, Portugal 34 Department of Oncology, Unidade Local de Saúde São João, Porto, Portugal 35 Department of Medicine (Oncology, Gastroenterology, Hepatology, and Pulmonology), Comprehensive Cancer Center Central Germany (CCCG), University of Leipzig Medical Center, Leipzig, Germany 36 Anaxomics Biotech, S.L. Barcelona, Barcelona, Spain 37 Department of Medical Oncology, Hospital Clinico Universitario, INCLIVA, Biomedical Research Institute, University of Valencia, Avenida Menendez Pelayo nro 4 accesorio, Valencia, Spain 38 Department of Gastroenterology, Hospital Clínico Universitario de Valencia, Valencia, Spain 39 CiberOnc. Carlos III Institute, Madrid, Spain Medical Oncology Department, Instituto Alexander Fleming, Buenos Aires, Argentina | N12: 1 | O12: Centro de Oncología de Precisión, Universidad Mayor, Santiago, Chile | Q12: Publicado | S12: 0 | U12: Gastric Cancer | V12: 0 | W12: No | Y12: 0 | AD12: 45662 | AF12: https://doi.org/10.1007/s10120-024-01578-3
B13: 6 | C13: 2025 | D13: 3 | E13: 3 | G13: Q1 | H13: 4.9 | I13: 0 | J13: Understanding microRNA-mediated chemoresistance in colorectal cancer treatment | K13: Guillermo Valenzuela; Héctor R. Contreras; Katherine Marcelain; Mauricio Burotto; Jaime González-Montero | L13: 0 | N13: 1 | O13: Bradford Hill Clinical Research Center | P13: 100 | Q13: Publicado | S13: 3432801 | T13: 45684 | U13: Int.J.Molecular Sciences | V13: 1 | W13: Jaime González | X13: 1-2025 | Y13: USD 2557,46 | Z13: 2369538 | AB13: Pagado con fondos 2024 | AD13: 29-02-2025 | AF13: https://doi.org/10.3390/ijms26031168
B14: 7 | C14: 2025 | D14: 1 | E14: 1 | G14: Q1 | H14: 3.4 | I14: 0 | J14: Exposure to pesticides in Chile and its relationship with carcinogenic potential: a review | K14: María Teresa Muñoz Quezada, Veronica Iglesias, Liliana Zúñiga, Floria Pancetti, Claudia Foerster, Natalia Landeros, Boris Lucero, Daniel Schwantes, Sandra Cortés | L14: 0 | N14: 1 | O14: Laboratorio de Neurotoxicología Ambiental, Departamento de Ciencias Biomédicas, Facultad de Medicina, Universidad Católica del Norte, Coquimbo, Chile, 6 Centro de Investigación y Desarrollo Tecnológico en Algas y otros Recursos Biológicos (CIDTA), Universidad Católica del Norte, Coquimbo, Chile, 7 Institute of Agri-food, Animal and Environmental Sciences (ICA3), Universidad de O' Higgins, San Fernando, Chile, 8 Unidad de Innovación en Prevención y Oncología de Precisión, Centro Oncológico, Facultad de Medicina, Universidad Católica del Maule, Talca, Chile, 9 In Vivo Tumor Biology Research Facility, Centro Oncológico, Facultad de Medicina, Universidad Católica del Maule, Talca, Chile, 10 The Neuropsychology and Cognitive Neurosciences Research Center CINPSI Neurocog, Faculty of Health Sciences, Universidad Católica del Maule, Talca, Advanced Center for Chronic Diseases (ACCDiS), Centro de Desarrollo Urbano Sustentable (CEDEUS), Santiago | P14: 50 | Q14: Publicado | U14: Frontiers in Public Health | V14: 0.5 | W14: M. Teresa Muñoz | X14: 2-2025 | Y14: USD 3495/2 | Z14: 1619094 | AB14: Pagado con fondos 2024 | AD14: 45748 | AF14: https://doi: 10.3389/fpubh.2025.1531751
B15: 8 | C15: 2025 | D15: 3 | E15: 3 | G15: Q2 | H15: 4.4 | J15: Patient-Derived Organoid Models for NKT Cell-Based Cancer Immunotherapy | K15: Pablo A. Palacios 1,† , Iván Flores 2,†, Lucas Cereceda 1 , Francisco F. Otero 1, Marioly Müller 3, Priscilla Brebi 4,5 , Héctor R. Contreras 2,6,* and Leandro J. Carreño 1,5,* | L15: 0 | N15: 1 | O15: Millennium Institute on Immunology and Immunotherapy, Laboratory of Integrative Biology (LIBi), Centro de Excelencia en Medicina Traslacional (CEMT), Scientific and Technological Bioresource Nucleus (BIOREN), Universidad de La Frontera, Temuco 4811230, Chile, Biomedical Research Consortium (BMRC), Santiago | P15: 30 | Q15: Publicado | U15: Cancers | V15: 0 | W15: No | AD15: 45683 | AF15: https://doi.org/10.3390/ cancers17030406
B16: 9 | C16: 2025 | D16: 4 | E16: 4 | G16: Q3 | H16: 2 | J16: Sociodemographic, political, and policy contexts of cancer care: A comparative analysis of countries with the highest survival rates | K16: Alejandra Fuentes-García, Carla Flores-Figueroa, Alondra Castillo-Delgado | L16: 0 | N16: 1 | O16: School of Nursing, Faculty of Health, Universidad Santo Tom´as, Chile d School of Speech Therapy, Faculty of Medicine, Universidad de Valparaíso, | P16: 100 | Q16: Publicado | U16: Journal of Cancer Policy | V16: 0 | W16: No | AD16: 45688 | AF16: https://doi.org/10.1016/j.jcpo.2025.100559
B17: 10 | C17: 2025 | D17: 2 | E17: 2 | G17: Q1 | H17: 8.1 | I17: 1 | J17: ACG Clinical Guideline: Diagnosis and Management of Gastric Premalignant Conditions | K17: Douglas R. Morgan, MD, MPH, FACG1, Juan E. Corral, MD,MPH2, Dan Li,MD3,4, Elizabeth A. Montgomery,MD5, Arnoldo Riquelme,MD6, John J. Kim, MD, FACG7, Bryan Sauer, MD, MSc, FACG8 and Shailja C. Shah, MD, MPH9,10 | L17: 1 | M17: 1Division of Gastroenterology, The University of Alabama at Birmingham, Birmingham, Alabama, USA; 2Division of Gastroenterology, Prisma Health, Greenville, South Carolina, USA; 3Department of Gastroenterology, Kaiser Permanente Medical Center, Santa Clara, California, USA; 4Kaiser Permanente Northern California Division of Research, Oakland, California, USA; 5Department of Pathology, University of Miami Miller School of Medicine, Miami, Florida, USA, 7Division of Gastroenterology, Los Angeles General Medical Center, Los Angeles, California, USA; 8Division of Gastroenterology, University of Virginia, Charlottesville, Virginia, USA; 9Division of Gastroenterology, University of California, San Diego, La Jolla, California, USA; 10Gastroenterology Section, Jennifer Moreno Veterans Affairs Medical Center, La Jolla, California, USA. | N17: 0 | P17: 50 | Q17: Publicado | U17: Amer J. of Gastroenterology | V17: 0 | W17: No | AD17: 45728 | AF17: http://links.lww.com/AJG/D558, http://links.lww.com/AJG/D559
B18: 11 | C18: 2025 | D18: 2 | E18: 2 | G18: Q3 | H18: 2.1 | J18: Accurate prognostic awareness is associated with increased emotional distress in Latino patients with advanced cancer | K18: Pedro E. Pérez-Cruz, M.D., M.P.H.1,2 , María Jesús San Martín, M.PSYCH.3, Josefa Palacios, M.SC., PH.D.4 , Laura Tupper-Satt, M.D.5, Marcela González-Otaíza, M.D.5 and Paula Repetto, PH.D.2,6 | L18: 0 | N18: 1 | O18: 3Escuela de Psicología, Facultad de Educación, Psicología y Familia, Universidad Finis Terrae, 5Unidad de Cuidados Paliativos, Complejo Asistencial Dr. Sótero del Río, Servicio de Salud Metropolitano Sur Oriente, Puente Alto, | Q18: Publicado | U18: Palliative and Supportive Care | V18: 0 | W18: No | AD18: 45769 | AF18: https://doi.org/ 10.1017/S1478951525000252
B19: 12 | C19: 2025 | D19: 5-2 | E19: 10 | F19: 1 | G19: Q2 | H19: 3 | J19: Education and Symptom Reporting in an mHealth App for Patients With Cancer: Mixed Methods Development and Validation Study | K19: Carolina Muñoz Olivar1,2*, MSc; Miguel Pineiro2,3*, PhD; Juan Sebastián Gómez Quintero4*, PhD; Carlos Javier Avendaño-Vásquez5,6*, PhD; Pablo Ormeño-Arriagada7*, PhD; Silvia Palma Rivadeneira2,8,9*, MSc; Carla Taramasco Toro2,3*, PhD | L19: 1 | M19: Faculty of Medicine, Antonio Nariño University, Bogotá, Colombia; 6School of Nursing, Industrial University of Santander, Bucaramanga, Colombia | N19: 1 | O19: 7Faculty of Engineering, Business, and Agro-Environmental Sciences, Department of Computer Civil Engineering, Universidad Viña del Mar, Viña del Mar, Chile; 9UC-CHRISTUS Health Network, Santiago, Chile | P19: 100 | Q19: Publicado | U19: JMIR Human Factors | V19: 1 | W19: Carla Taramasco | X19: 3-2025 | Y19: USD 2123,95 | Z19: 1967882 | AB19: Pagado con fondos 2024 | AD19: 45775 | AF19: doi:10.2196/60169
B20: 13 | C20: 2025 | D20: 5 | E20: 5 | G20: Q2 | H20: 1.3 | J20: Using implementation science to develop and deploy an oncology electronic health record | K20: Carla Taramasco, René Noel, Gastón Márquez, Diego Robles | L20: 0 | N20: 1 | O20: Escuela de Ingeniería Informática, Universidad de Valparaíso, Departamento de Ciencias de la Computación y Tecnologías de la Información, Universidad del Bío-Bío, Chillán; Escuela de Kinesiología. Facultad de Odontología y Salud, Universidad Diego Portales, Santiago | P20: 100 | Q20: Publicado | U20: Informatics in Medicine | V20: 0 | W20: Carla Taramasco | X20: 4-2025 | Y20: 0 | AD20: 45698 | AF20: https://doi.org/10.1016/j.imu.2025.101625
B21: 14 | C21: 2025 | D21: 2 | E21: 2 | G21: Q2 | H21: 2.3 | J21: Spiritual care for prevention of psychological disorders in critically ill patients: study protocol of a feasibility randomised controlled pilot trial | K21: Paula Repetto1,2, Carolina Ruiz3,4, Verónica Rojas5, Patricia Olivares6,7, Jan Bakker8, Leyla Alegria3,9 | L21: 1 | M21: 8Department of Intensive Care Adults, Erasmus MC University Medical Center, Rotterdam, The Netherlands | N21: 1 | O21: 4Unidad de Paciente Critico, Complejo Asistencial Dr Sotero del Río, Santiago, Servicio de Medicina Interna, Complejo Asistencial Dr Sotero del Río, Santiago, Chile; | Q21: Publicado | U21: BMJ Open | V21: 0 | W21: Paula Repetto | X21: 5-2025 | AD21: 45750 | AF21: https://doi.org/10.1136/bmjopen-2024-084914
B22: 15 | C22: 2025 | D22: 1 | E22: 1 | G22: Q2 | H22: 2.7 | J22: Assessing the alignment of Chilean Food-Based Dietary Guidelines on cancer prevention: a content analysis | K22: Alejandra Ortega Guzmán, Solange Parra-Soto, María Jesús Vega-Salas, Lorena Rodríguez-Osiac, Sandra López-Arana | L22: 0 | N22: 1 | O22: Centro para la Transversalización de Género en I+D+i+e, Vicerrectoría de Investigación y Doctorados, Universidad Autónoma de Chile, Santiago, 2 Department of Nutrition and Public Health, Faculty of Health and Food Science, Universidad del Bío-Bío, Chillan, Escuela de Nutrición y Dietética, Facultad de Medicina, Universidad Finis Terrae, Providencia | P22: 100 | Q22: Publicado | U22: Healthcare | V22: 1 | W22: Lorena Rodriguez | X22: 6-2025 | Y22: USD 3304,47 | Z22: 3176058 | AB22: Pagado con fondos 2024 | AD22: 45790 | AF22: https://doi.org/10.3390/healthcare13101133
B23: 16 | C23: 2025 | D23: 4 | E23: 4 | G23: Q2 | H23: 3 | J23: Barriers to accessing formal cancer care from the perspective of informal caregivers: a qualitative study | K23: Carla Campaña1,2 · Báltica Cabieses1,2 · Alexandra Obach1,2 · Francisca Vezzani1,2 · Angela Estay3 · Diego Carrillo4 | L23: 0 | N23: 1 | O23: Centro Oncológico del Norte, Antofagasta, Chile | P23: 100 | Q23: Publicado | U23: Supportive Care in Cancer | V23: 1 | W23: Carla Campaña | X23: 7-2025 | Y23: USD 4765 | Z23: 4468665 | AB23: Pagado con fondos 2024 | AD23: 45768 | AF23: https://doi.org/10.1007/s00520-025-09426-5
B24: 17 | C24: 2025 | D24: 4 | E24: 4 | G24: Q2 | H24: 2.6 | J24: Exploring the Characteristics of Cancer-Centred Civil Society Organisations in Chile: A Qualitative Study | K24: Antonia Roberts1,4, Francisca Vezzani 1,4, Báltica Cabieses 1,2,4, Alexandra Obach1,4, Carla Campaña 1,4, Manuel A. Espinoza 3,4. | L24: 1 | M24: Department of Health Sciences, University of York, United Kingdom | N24: 0 | P24: 100 | Q24: Publicado | S24: PAB392735 | T24: 45771 | U24: PLOS One | V24: 1 | W24: Antonia Roberts | X24: 8-2025 | Y24: USD 2290 | Z24: 2137165 | AB24: =AB7-Z24 -> 17862835 | AD24: 45793 | AF24: https://doi.org/10.1371/journal.pone.0315589
B25: 18 | C25: 2025 | D25: 4-2 | E25: 10 | F25: 1 | G25: Q3 | H25: 1.5 | J25: Utility Values of Health Status in Gastric Cancer: A Systematic Review | K25: Cristian González, Manuel Espinoza, Matías Libuy, Francisca Crispi, ARNOLDO RIQUELME, Fernando Alarid-Escudero, Gonzalo Latorre, Margarita Pizarro, Cristóbal Cuadrado | L25: 1 | M25: Department of Health Policy, School of Medicine and Center for Health Policy, Freeman Spogli Institute, Stanford University, Stanford, CA, USA | N25: 0 | Q25: Publicado | U25: Value in Health Reg Issues | V25: 0 | W25: No | Z25: 0 | AB25: =AB24-Z25 -> 17862835 | AD25: 45686 | AF25: https://doi.org/10.1016/j.vhri.2024.101063
B26: 19 | C26: 2025 | D26: 2 | E26: 2 | G26: Q3 | H26: 1.3 | J26: Implementation of an Educational Intervention for Gastric Cancer Awareness in the General Population in CELAC and Europe: A Strategy Proposed by the LEGACy Consortium | K26: Juan Antonio Carbonell‑Asins1 · Elena Jiménez‑Martí2,3 · Sergio Romero2 · Eduardo García4 · Ana Miralles‑Marco2 · Beatriz Lopez2 · Marisol Huerta2 · Carmelo Caballero5 · Hugo Boggino5 ·Cinthia Gauna6 · Olga Beatriz Acevedo‑Funes7 · Gabriel Benitez Nuñez7 · Claudia Melina Céspedes‑Cardozo7 ·Edith A. Fernandez‑Figueroa8 · Nayeli Ortiz‑Olvera9 · Erika Ruiz‑García10,11 · Fátima Carneiro12,13,14 ·Rita Barros12,13,14 · Ceu Figueiredo4,12,13 · Rui M. Ferreira12,13 · Tessa Suzanne Groen ‑ van Schooten15,16,17 ·Demi van Santvliet15 · Sarah Derks15,16,17 · Romina Luca18 · Maria Alsina19 · Arnoldo Riquelme20,21 · Andrés Cervantes2,22 · Tania Fleitas2 | L26: 1 | M26: 1 Department of Medical Oncology, Hospital Clínico Universitario, Biostatistical Unit, INCLIVA, Biomedical Research Institute, Avenida Menendez Pelayo Nro 4 Accesorio, 46010 Valencia, Spain 2 Department of Medical Oncology Hospital Clínico Universitario, INCLIVA, Biomedical Research Institute, University of Valencia, Avenida Blasco Ibañez 17, 46010 Valencia, Spain 3 Department of Biochemistry, University of Valencia, Avenida Blasco Ibañez XX, 46010 Valencia, Spain 4 Vall d Hebron Institute of Oncology, Biostatistical Unit, Calle Nazaret 155‑177 08035, Barcelona, Spain 5 Genpat. Pathology Department, Guido Spano 1448, Asunción, Paraguay 6 Oncology Department, Instituto de Previsión Social, Av Santisimo Sacramento y Dr. Manuel Peña, Asunción, Paraguay 7 Cátedra de Biofísica, Universidad Nacional de Asunción, Campus Universitario San Lorenzo, San Lorenzo, Paraguay 8 Núcleo B de Innovación en Medicina de Precisión, Instituto Nacional de Medicina Genómica, Periferico Sur Número 4809, Colonia Arenal, Tepepán, Alcaldia Tialpan, 14610 Ciudad de México, Mexico 9 Departamento de Gastroenterología, UMAE, Hospital de Especialidades Dr. Bernardo Sepúlveda, Centro Médico Nacional Siglo XXI, IMSS, Avda Cuauhtemoc 330, Doctores, Cuauhtemoc, 06720 Ciudad de México, Mexico 10 Departamento de Tumores de Tubo Digestivo, Instituto Nacional de Cancerología, Avda San Fernando 22, Belisario Dominguez, Secc 16, Tialpán, 14080 Ciudad de México, Mexico 11 Laboratorio de Medicina Traslacional, Instituto Nacional de Cancerología, Avda San Fernando 22, Belisario Dominguez, Secc 16, Tialpán, 14080 Ciudad de México, Mexico 12 Institute of Molecular Pathology and Immunology of the University of Porto (IPATIMUP), Rua Julio Amaral de Carvalho, 45, 4200‑135 Porto, Portugal 13 i3S–Instituto de Investigação e Inovação em Saúde, Universidade Do Porto, R. Alfredo Allen 208, 4200‑135 Porto, Portugal 14 Department of Pathology, Faculty of Medicine of the University of Porto, Alameida Prof. Hernani Monteiro, 4200‑319 Porto, Portugal 15 Department of Medical Oncology, Amsterdam UMC Location University of Amsterdam, Meibergdreef 9, Amsterdam, The Netherlands 16 Cancer Center Amsterdam, Cancer Biology and Immunology, Meibergdreef 9, Amsterdam, The Netherlands 17 Oncode Institute, Jaarbeursplein 6, 3521 AL Utrecht, The Netherlands 18 Oncology Department, Instituto Alexander Flemming, Crammer 1180, C1426 Buenos Aires, Argentina 19 Oncology Department, Vall d Hebron Institute of Oncology, Calle Nazareth 115‑117, 08035 Barcelona, Spain 20 Gastroenterology Department, Pontificia Universidad Católica de Chile, Santiago, Chile 21 Centro Para La Prevención y Control del Cáncer (CECAN), Avenida Libertador Bernardo O`Higgins 340, Santiago de Chile, Chile 22 CIBERONC, Instituto de Salud Carlos III, Avenida de Monforte de Lemos 5, Fuencarral‑El Pardo, 28029 Madrid, Spain | N26: 0 | Q26: Publicado | U26: Journal of Cancer Education | V26: 0 | W26: No | Z26: 0 | AB26: =AB25-Z26 -> 17862835 | AD26: 45701 | AF26: https://doi.org/10.1007/s13187-025-02578-2
B27: 20 | C27: 2025 | D27: 2 | E27: 2 | G27: Q1 | H27: 25.9 | I27: 1 | J27: Innovation Meets Practice: A Scalable Simulation-based Methodology for Massive Paracentesis Training | K27: Úrsula Figueroa,1,* Cristián Jarry,1,* Martin Inzunza,1 Isabella Montero,1 Francisco Garrido,2 Ignacio Villagrán,3 Francisca Belmar,1 Gabriel Escalona,1 Arnoldo Riquelme,4,5 and Julián Varas | L27: 0 | N27: 1 | O27: UC Christus | Q27: Publicado | U27: Gastroenterology | V27: 0 | W27: No | Z27: 0 | AB27: =AB26-Z27 -> 17862835 | AD27: 45716 | AF27: https://doi.org/10.1053/j.gastro.2024.12.015
B28: 21 | C28: 2025 | D28: 2 | E28: 2 | G28: Q1 | H28: 4.3 | I28: 0 | J28: Helicobacter pylori and Colorectal Cancer: Meeting Sir Austin Bradford Hill's Causality Criteria | K28: Juan Sebastián Frías-Ordoñez 1 2 3 4, Arnoldo Riquelme 5 6, Hernando Marulanda-Fernandez 3 7 8, Lina Otero-Parra 3, José Augusto Urrego 1 2, Elder Otero-Ramos 3 5, José Darío Portillo-Miño 8 9, William Otero Regino 1 2 3 8 | L28: 1 | M28: 1Department of Gastroenterology and Digestive Endoscopy, Faculty of Medicine, Universidad Nacional de Colombia, Bogotá, Colombia. 2Gastroenterology Unit, Hospital Universitario Nacional de Colombia, Bogotá, Colombia. 3Gastroenterology and Digestive Endoscopy Unit, Gastroenterology Center, Bogotá, Colombia. 4Hospital Internacional de Colombia, Bucaramanga, Colombia. 5Department of Gastroenterology, Faculty of Medicine, Pontificia Universidad Católica de Chile, Santiago, Chile. 6Centro Para la Prevención y Control del Cancer (CECAN), Santiago, Chile. 7Hospital Central de la Policía, Bogotá, Colombia. 8Colombian Research Group on Helicobacter pylori, Bogotá, Colombia. 9Infectious Diseases and Cancer Research Group (GINFYCA), Centro de Investigaciones Clínicas, Fundación Hospital San Pedro, Pasto, Nariño, Colombia. | N28: 0 | Q28: Publicado | U28: Helicobacter | V28: 0 | W28: No | Z28: 0 | AB28: =AB27-Z28 -> 17862835 | AD28: 45707 | AF28: https://doi.org/10.1111/hel.70024
B29: 22 | C29: 2025 | D29: 2 | E29: 2 | G29: Q1 | H29: 3.7 | I29: 1 | J29: Randomized Trial Assessing Prospective Surveillance and Exercise for Preventing Breast Cancer-Related Lymphedema in High-Risk Patients | K29: Karol Ramırez-Parada,PT,MSc,MBA,a,b Cesar Sanchez,MD,b,c Irene Cantarero-Villanueva,PT,MSc,PhD,d,e,f_Alvaro1 Reyes,PT,MSc,PhD,gMauricio P.Pinto,PhD,hM. Loreto Bravo,PhD,hDenise Montt-Blanchard,MSc,b,i Francisco Acevedo,MD,b,c Benjamın Walbaum,MD,c,j,kMargarita Alfaro-Barra,PT,lMargarita Barra-Navarro,PT,a Scarlet Muñoz-Flores,PT,a Constanza Pinto,mSabrina Muñiz,RN,c Felipe Contreras-Briceño,PT,MSc,PhD,a,n Tomás Merino,MD,c Gina Merino,MSco | L29: 1 | M29: a Departamento de Kinesiología, Escuela Ciencias de la Salud, Facultad de Medicina, Pontificia Universidad Católica de Chile, Santiago, Chile b Centro para la prevención y el control del cáncer, CECAN, Santiago, Chile c Department of Hematology-Oncology, Faculty of Medicine, Pontificia Universidad Católica de Chile, Santiago, Chile d Department of Physical Therapy, Faculty of Health Sciences, University of Granada, Granada, Spain e Instituto de Investigación Biosanitaria (ibs.GRANADA), Granada, Spain f Sport and Health Joint University Institute (iMUDS), Granada, Spain g Exercise and Rehabilitation Sciences Laboratory, School of Physical Therapy, Faculty of Rehabilitation Sciences, Universidad Andres Bello, Santiago, Chile h Support team for Oncological Research and Medicine (STORM), Santiago, Chile i School of Design, Faculty of Architecture, Design and Urban Studies. Pontificia Universidad Católica de Chile, Santiago, Chile j Translational Genomics and Targeted Therapies in Solid Tumors Group, August Pi I Sunyer Biomedical Research Institute, Barcelona, Spain k Department of Medical Oncology, Hospital Clinic of Barcelona, Barcelona, Spain l Clínica Universidad de los Andes, Servicio de Kinesiología, Santiago, Chile m Unidad de patología mamaria, Complejo Asistencial Dr. Sótero del Río, Santiago, Chile n Laboratory of Exercise Physiology, Department of Physical Therapy, School of Health Sciences, Faculty of Medicine, Pontificia Universidad Católica de Chile, Santiago, Chile o Departamento Agencia Nacional de Prevención y Control del Cáncer, Subsecretaria de Salud Pública, Ministerio de Salud de Chile, Santiago, Chile | N29: 1 | O29: a Departamento de Kinesiología, Escuela Ciencias de la Salud, Facultad de Medicina, Pontificia Universidad Católica de Chile, Santiago, Chile b Centro para la prevención y el control del cáncer, CECAN, Santiago, Chile c Department of Hematology-Oncology, Faculty of Medicine, Pontificia Universidad Católica de Chile, Santiago, Chile d Department of Physical Therapy, Faculty of Health Sciences, University of Granada, Granada, Spain e Instituto de Investigación Biosanitaria (ibs.GRANADA), Granada, Spain f Sport and Health Joint University Institute (iMUDS), Granada, Spain g Exercise and Rehabilitation Sciences Laboratory, School of Physical Therapy, Faculty of Rehabilitation Sciences, Universidad Andres Bello, Santiago, Chile h Support team for Oncological Research and Medicine (STORM), Santiago, Chile i School of Design, Faculty of Architecture, Design and Urban Studies. Pontificia Universidad Católica de Chile, Santiago, Chile j Translational Genomics and Targeted Therapies in Solid Tumors Group, August Pi I Sunyer Biomedical Research Institute, Barcelona, Spain k Department of Medical Oncology, Hospital Clinic of Barcelona, Barcelona, Spain l Clínica Universidad de los Andes, Servicio de Kinesiología, Santiago, Chile m Unidad de patología mamaria, Complejo Asistencial Dr. Sótero del Río, Santiago, Chile n Laboratory of Exercise Physiology, Department of Physical Therapy, School of Health Sciences, Faculty of Medicine, Pontificia Universidad Católica de Chile, Santiago, Chile o Departamento Agencia Nacional de Prevención y Control del Cáncer, Subsecretaria de Salud Pública, Ministerio de Salud de Chile, Santiago, Chile | Q29: Publicado | U29: Archives of Physical Medicine and Rehabilitation | V29: 0 | W29: No | Z29: 0 | AB29: =AB28-Z29 -> 17862835 | AD29: 45727 | AF29: https://doi.org/10.1016/j.apmr.2025.03.002
B30: 23 | C30: 2025 | D30: 2 | E30: 2 | G30: Q3 | H30: 1.2 | J30: Feasibility of Solution-focused Brief Therapy for individuals with alcohol use in primary health care | K30: Karla González-Suitta,b, Rodolfo Barríac, and Vanessa Iturrietaa | L30: 0 | N30: 1 | O30: cDepartamento de Matemática y Ciencia de la Computación, Universidad de Santiago de Chile, Santiago, Chile | Q30: Publicado | U30: Journal of Ethnic & Cultural Diversity in Social Work | V30: 0 | Z30: 0 | AB30: =AB29-Z30 -> 17862835 | AD30: 45807 | AF30: https://doi.org/10.1080/15313204.2025.2510210
B31: 24 | C31: 2025 | D31: 3 | E31: 3 | G31: Q3 | H31: 3 | J31: Towards Personalized Precision Oncology: A Feasibility Study of NGS-Based Variant Analysis of FFPE CRC Samples in a Chilean Public Health System Laboratory | K31: Eduardo Durán Jara 1 Iván Ponce 1 , Marcelo Rojas Herrera 1 , Jessica Toro 2, 3 , Paulo Covarrubias 1 , Evelin González 2 , Natalia T. Santis Alay 4 5 , Mario E. Soto Marchant 4 6 , Katherine Marcelain 2, 3 , Bárbara Parra 1 and Jorge Fernández 1 | L31: 0 | N31: 1 | O31: Subdepartamento de Genómica y Genética Molecular, Laboratorio Nacional Biomédico y de Referencia, Instituto de Salud Pública de Chile, y Departamento Agencia Nacional de Dispositivos Médicos, Instituto de Salud Pública de Chile. Escuela de Tecnología Médica, Facultad de Salud y Odontología, Universidad Diego Portales Santiago , Chile | Q31: Publicado | U31: Curr. Issues Mol. Biol | V31: 0 | W31: No | Z31: 0 | AB31: =AB30-Z31 -> 17862835 | AD31: 45868 | AF31: https://doi.org/10.3390/cimb47080599
B32: 25 | C32: 2025 | D32: 3 | E32: 3 | G32: Q1 | H32: 6.6 | I32: 0 | J32: Oxidative stress, parity history and remnant follicles in the aged ovary. Insights on ovarian cancer risk and protection. | K32: Ulises Urzúa , Arnaldo Andrés Marín, Enrique Castellón $ 3.224.953 (50%) | L32: 0 | N32: 0 | Q32: Publicado | S32: 3648338 | T32: 45826 | U32: Antoxidants | V32: 0.5 | W32: Enrique Castellón | X32: 9-2025 | Y32: USD 3446,42 | Z32: 3244953 | AB32: =AB31-Z32 -> 14617882 | AD32: 45833 | AF32: https://doi.org/10.3390/antiox14070759
B33: 26 | C33: 2025 | D33: 2 | E33: 2 | G33: Q1 | H33: 7.6 | I33: 1 | J33: Assessing the Impact of a Single Qualitative Fecal Immunochemical Test on Colonoscopy Prioritization and Mortality in Risk-Stratified Patients with Suspected Colorectal Cancer: A Retrospective Cohort Study | K33: Felipe F. Quezada-Diaz MD 1-3, Johanna Acevedo, MSc2-3, Maite González, MSc 2, Andrea Tello 1, Richard CastilloMD 1, Carlos Morales Mora MD1, Erik Manríquez Alegría MD 1, Valentina Duran Espinoza MD, MSc4, Felipe Mena MD1, Catherine Le- Bert 1, Manuel Cabreras MD 1, Ángelo Fulle MD1, Gonzalo Carvajal MD1, Pamela Briones MD1, Bruno Nervi MD3.4, Rodrigo Kusanovich MD 1. | L33: 0 | N33: 1 | O33: 1Servicio de Cirugía, Unidad de Coloproctología, Complejo Asistencial Doctor Sótero Del Río, Santiago, Chile. 2Centro para la Prevención y el Control del Cáncer (CECAN), Santiago, Chile. 3Instituto de Ciencias e Innovación en Medicina, Facultad de Medicina Clínica Alemana Universidad del Desarrollo, Santiago, Chile. 4Escuela de Medicina. Pontificia Universidad Católica de Chile, Santiago, Chile. 5Departamento de Hematología y Oncología, Facultad de Medicina, Pontificia Universidad Católica de Chile, Santiago, Chile. | Q33: Publicado | S33: OAD0000611643 | T33: 45860 | U33: Lancet Regional Health Americas | V33: 1 | W33: Bruno Nervi | X33: 10-2025 | Y33: USD 2465 | Z33: 2350131 | AB33: =AB32-Z33 -> 12267751 | AD33: 45880 | AF33: https://doi.org/10.1016/j.lana.2025.101201
B34: 27 | C34: 2025 | D34: 2 | E34: 2 | G34: Q2 | H34: 2.3 | J34: The challenges of cancer survivorship care in Chile: A longitudinal study comparing the quality of care and quality of life for cancer survivors in a primary care network and a Cancer Center in Chile. | K34: Puschel Klaus1,2, Arancibia Victor2, Rioseco Andrea1,2, Paz Sarah2, Soto María Gabriela1.2, Martinez Javiera2,3, Faundez Marcela1, Acevedo Francisco2, Di Biase Felipe2,3, Emery Jon2,4, León Augusto5, Are Chandrekanth6, Thompson Beti7 | L34: 1 | M34: 1Department of Family and Community Medicine, Pontificia Universidad Catolica De Chile School of Medicine, Santiago, Chile kpuschel@uc.cl. 2Center for Cancer Prevention and Control (CECAN), Santiago, Chile. 3Department of Family and Community Medicine, Pontificia Universidad Catolica De Chile School of Medicine, Santiago, Chile. 4The University of Melbourne, Medical School, Melbourne, Victoria, Australia. 5Department of Oncology, Pontificia Universidad Catolica De Chile School of Medicine, Santiago, Chile. 6Universidad de los Andes, Santiago, Chile. 7Department of Surgical Oncology, Pontificia Universidad Catolica de Chile, School of Medicine, Santiago, Chile. 8Division of Surgical Oncology, University of Nebraska Medical Center, Omaha, Nebraska, USA. 9Fred Hutchinson Cancer Research Center, Seattle, Washington, USA. | N34: 1 | O34: 1Department of Family and Community Medicine, Pontificia Universidad Catolica De Chile School of Medicine, Santiago, Chile kpuschel@uc.cl. 2Center for Cancer Prevention and Control (CECAN), Santiago, Chile. 3Department of Family and Community Medicine, Pontificia Universidad Catolica De Chile School of Medicine, Santiago, Chile. 4The University of Melbourne, Medical School, Melbourne, Victoria, Australia. 5Department of Oncology, Pontificia Universidad Catolica De Chile School of Medicine, Santiago, Chile. 6Universidad de los Andes, Santiago, Chile. 7Department of Surgical Oncology, Pontificia Universidad Catolica de Chile, School of Medicine, Santiago, Chile. 8Division of Surgical Oncology, University of Nebraska Medical Center, Omaha, Nebraska, USA. 9Fred Hutchinson Cancer Research Center, Seattle, Washington, USA. | Q34: Publicado | S34: APC600692271 | T34: 45860 | U34: BMJ Open | V34: 1 | W34: Klaus Puschel | X34: 11-2025 | Y34: USD 3125 | Z34: 2979375 | AB34: =AB33-Z34 -> 9288376 | AD34: 45879 | AF34: https://doi.org/10.1136/bmjopen-2024-097015
B35: 28 | C35: 2025 | D35: 3 | E35: 3 | G35: Q2 | H35: 3.3 | J35: Genetic variants and clinical determinants affecting the response to 5-Fluorouracilbased treatment in Chilean patients with advanced colorectal cancer | K35: Leslie C. Cerpa1,2,3, Christopher Sandoval4, Paula Escalante1, Juan P. Cayún1,2, María A. Lavanderos1,2,5, Claudio Alarcón-Concha1,6, Guillermo Kaempfe1, Diego Moreno-Tapia1, Camilo S. Quiroz1, Carolina Gutierrez-Cáceres1,7, Olga Barajas3,8, Bettina Müller3,9, Alicia Colombo3,10, Gerardo Donoso3,10, Angie Nuñez11, Nelson M. Varela1,2 and Luis A. Quiñones1,2,7* | L35: 1 | M35: 1Laboratory of Chemical Carcinogenesis and Pharmacogenetics, Department of Basic-Clinical Oncology (DOBC), Faculty of Medicine, University of Chile, Santiago, Chile, 2Latin American Network for Implementation and Validation of Clinical Pharmacogenomics Guidelines (RELIVAF), Santiago, Chile, 3Center for Cancer Prevention and Control (CECAN), Santiago, Chile, 4Clinical Laboratory, Felix Bulnes Clinical Hospital, Santiago, Chile, 5Department of Basic Sciences, Faculty of Sciences, University of Bío, Bío, Chile, 6Escuela de Medicina, Fundación Instituto Profesional Duoc UC, Santiago, Chile, 7Department of Pharmaceutical Sciences and Technology, Faculty of Chemical and Pharmaceutical Sciences, University of Chile, Santiago, Chile, 8Clinical Hospital of University of Chile, Santiago, Chile, 9National Cancer Institute, Santiago, Chile, 10Biobank of Fluids and Tissues of the University of Chile, Santiago, Chile, 11Faculty of Pharmacy, University of Costa Rica, San Jose, Costa Rica | N35: 1 | O35: 1Laboratory of Chemical Carcinogenesis and Pharmacogenetics, Department of Basic-Clinical Oncology (DOBC), Faculty of Medicine, University of Chile, Santiago, Chile, 2Latin American Network for Implementation and Validation of Clinical Pharmacogenomics Guidelines (RELIVAF), Santiago, Chile, 3Center for Cancer Prevention and Control (CECAN), Santiago, Chile, 4Clinical Laboratory, Felix Bulnes Clinical Hospital, Santiago, Chile, 5Department of Basic Sciences, Faculty of Sciences, University of Bío, Bío, Chile, 6Escuela de Medicina, Fundación Instituto Profesional Duoc UC, Santiago, Chile, 7Department of Pharmaceutical Sciences and Technology, Faculty of Chemical and Pharmaceutical Sciences, University of Chile, Santiago, Chile, 8Clinical Hospital of University of Chile, Santiago, Chile, 9National Cancer Institute, Santiago, Chile, 10Biobank of Fluids and Tissues of the University of Chile, Santiago, Chile, 11Faculty of Pharmacy, University of Costa Rica, San Jose, Costa Rica | P35: 0.5 | Q35: Publicado | U35: Frontiers in Oncology | V35: 1 | W35: Lluis Quiñones | X35: 13-2025 | Y35: USD 2172,97 | Z35: 2080966 | AB35: =AB34-Z35 -> 7207410 | AD35: 45863 | AF35: https://doi.org/10.3389/fonc.2025.1589724
B36: 29 | C36: 2025 | D36: 2-3 | E36: 10 | F36: 1 | G36: Q1 | H36: 5.9 | I36: 1 | J36: Data Resource Profile: EULAT Eradicate GBC: the European-Latin American Research Consortium towards Eradication of Preventable Gallbladder Cancer | K36: Dominique Scherer1,† , Carol Barahona Ponce1,†, Claudio Mengoa2, Paola Montenegro3, Hector Losada4, Ana Lineth Garcia5, Armando Rojas6, Erik Morales6,7, Allan Vera Kortmann8, Loreto Spencer9, Alejandro Ortega10, Karina Vargas Valdebenito10, Juan Carlos Roa11,12, Cristina Inklemona13, Alicia Colombo Flores11,14,15,16, Romy Kirsten17, Linda Zollner1, Katherine Marcelain11,16, Trine B. Rounge18,19, Hilde Langseth19, Sarah Jane Lewis20 , Gerardo Francisco Arroyo21, Ricardo Armisen22, Bruno Nervi Nattero11,23, Bettina G. Muller24, Piga Roxana Fernández Kaempffer25, Rajiv Kumar1, Pamela Salinas-Alvarez26, Rachel Sabine Kelly27 Dominique Scherer, Mazda Jenab28, Justo Lorenzo Bermejo1,29 | L36: 1 | M36: 1Statistical Genetics Research Group, Institute of Medical Biometry, Heidelberg University, Heidelberg, Germany 2Instituto Regional de Enfermedades Neopl�asicas, Arequipa, Peru 3Departamento de Medicina Oncol�ogica, Instituto Nacional de Enfermedades Neopl�asicas, Lima, Peru 4Departamento de Cirug�ıa, Universidad de la Frontera, Temuco, Chile 5Instituto de Investigaciones Biom�edicas (IIBISMED), Facultad de Medicina, Universidad Mayor de San Sim�on, Cochabamba, Bolivia 6Facultad de Medicina, Universidad Cat�olica del Maule, Talca, Chile 7Servicio de Anatomia Patologica, Hospital Regional de Talca, Talca, Chile 8Hospital de Puerto Montt, Los Lagos, Puerto Montt, Chile 9Hospital Clinico Regional Concepci�on, Concepci�on, Chile 10Hospital Juan No�e Crevani, Arica, Chile 11Center for Cancer Prevention and Control (CECAN), Chile 12Servicio de Anatomia Patologica, Pontificia Universidad Catolica de Chile, Santiago, Chile 13Hospital Pablo Soria, San Salvador de Jujuy, Argentina 14Department of Anatomy Pathology, Faculty of Medicine, Universidad de Chile, Santiago, Chile 15Pathological Anatomy Service, Clinical Hospital of the University of Chile, Santiago, Chile 16Departamento de Oncolog�ıa B�asico Cl�ınica, Facultad de Medicina, Universidad de Chile, Santiago, Chile 17University Hospital Mannheim, Medicial Faculty Mannheim, Heidelberg University, Mannheim, Germany 18Centre for Bioinformatics, Department of Pharmacy, University of Oslo, Oslo, Norway 19Department of Research, Cancer Registry of Norway, Oslo, Norway 20Department of Population Health Sciences, University of Bristol, Bristol, United Kingdom 21ILOGI (Latin-American Gastrointestinal Oncology Intergroup), San Salvador de Jujuy, Argentina 22Centro de Gen�etica y Gen�omica, Instituto de Ciencias e Innovaci�on en Medicina, Facultad de Medicina Cl�ınica Alemana Universidad del Desarrollo, Santiago, Chile 23Departamento de Hematolog�ıa y Oncolog�ıa, Pontificia Universidad Cat�olica De Chile, Santiago, Chile 24Chilean Cooperative Group for Oncological Research (GOCCHI), Santiago, Chile 25Fundaci�on GIST Chile, Santiago, Chile 26Instituto de Alta Investigaci�on, Universidad de Tarapac�a, Arica, Chile 27Channing Division of Network Medicine, Brigham and Women’s Hospital and Harvard Medical School, Boston, USA 28Nutrition and Metabolism Branch, International Agency for Research on Cancer (IARC-WHO), Lyon, France 29Laboratory of Biostatistics for Precision Oncology, Institut de canc�erologie Strasbourg Europe, Strasbourg, France | N36: 1 | O36: 1Statistical Genetics Research Group, Institute of Medical Biometry, Heidelberg University, Heidelberg, Germany 2Instituto Regional de Enfermedades Neopl�asicas, Arequipa, Peru 3Departamento de Medicina Oncol�ogica, Instituto Nacional de Enfermedades Neopl�asicas, Lima, Peru 4Departamento de Cirug�ıa, Universidad de la Frontera, Temuco, Chile 5Instituto de Investigaciones Biom�edicas (IIBISMED), Facultad de Medicina, Universidad Mayor de San Sim�on, Cochabamba, Bolivia 6Facultad de Medicina, Universidad Cat�olica del Maule, Talca, Chile 7Servicio de Anatomia Patologica, Hospital Regional de Talca, Talca, Chile 8Hospital de Puerto Montt, Los Lagos, Puerto Montt, Chile 9Hospital Clinico Regional Concepci�on, Concepci�on, Chile 10Hospital Juan No�e Crevani, Arica, Chile 11Center for Cancer Prevention and Control (CECAN), Chile 12Servicio de Anatomia Patologica, Pontificia Universidad Catolica de Chile, Santiago, Chile 13Hospital Pablo Soria, San Salvador de Jujuy, Argentina 14Department of Anatomy Pathology, Faculty of Medicine, Universidad de Chile, Santiago, Chile 15Pathological Anatomy Service, Clinical Hospital of the University of Chile, Santiago, Chile 16Departamento de Oncolog�ıa B�asico Cl�ınica, Facultad de Medicina, Universidad de Chile, Santiago, Chile 17University Hospital Mannheim, Medicial Faculty Mannheim, Heidelberg University, Mannheim, Germany 18Centre for Bioinformatics, Department of Pharmacy, University of Oslo, Oslo, Norway 19Department of Research, Cancer Registry of Norway, Oslo, Norway 20Department of Population Health Sciences, University of Bristol, Bristol, United Kingdom 21ILOGI (Latin-American Gastrointestinal Oncology Intergroup), San Salvador de Jujuy, Argentina 22Centro de Gen�etica y Gen�omica, Instituto de Ciencias e Innovaci�on en Medicina, Facultad de Medicina Cl�ınica Alemana Universidad del Desarrollo, Santiago, Chile 23Departamento de Hematolog�ıa y Oncolog�ıa, Pontificia Universidad Cat�olica De Chile, Santiago, Chile 24Chilean Cooperative Group for Oncological Research (GOCCHI), Santiago, Chile 25Fundaci�on GIST Chile, Santiago, Chile 26Instituto de Alta Investigaci�on, Universidad de Tarapac�a, Arica, Chile 27Channing Division of Network Medicine, Brigham and Women’s Hospital and Harvard Medical School, Boston, USA 28Nutrition and Metabolism Branch, International Agency for Research on Cancer (IARC-WHO), Lyon, France 29Laboratory of Biostatistics for Precision Oncology, Institut de canc�erologie Strasbourg Europe, Strasbourg, France | Q36: Publicado | U36: Int Journal of Epidemiology | V36: 0 | W36: No | AB36: =AB35-Z36 -> 7207410 | AD36: 45835 | AF36: https://doi.org/10.1093/ije/dyaf127
B37: 30 | C37: 2025 | D37: 2-3 | E37: 10 | F37: 1 | G37: Q1 | H37: 6.8 | I37: 0 | J37: Immune profiling of gastric adenocarcinomas in EU and LATAM countries identifies global differences in immune subgroups and microbiome influence | K37: Tessa S. Groen– van Schooten 1,2,3,36, Manuel Cabeza-Segura4,36, Rui M. Ferreira5,6, Carolina Martínez-Ciarpaglini7, Rita Barros5,6,8,9, João Santos-Antunes10, Andreia Costa11, Edith A. Fernández-Figueroa12, Leonardo Lino-Silva 13, Angélica Ixtaccihuatl Hernandez-Guerrero14, Erika Ruiz-García 15,16, Carmelo Caballero17, Hugo Boggino17, Cinthia Gauna18, Daniel Cantero19, Berenice Freile20, Federico Esteso20, Juan O´Connor20, Arnoldo Riquelme21, Gareth Owen22, Erick Riquelme23, Juan Carlos Roa 24, Gonzalo Latorre25, Marcelo Garrido26, Fiorella Ruiz-Pace27, Marc Diez García Florian Lordick 28, Maria Alsina28,29, 30, Judith Farrés31, Juan Antonio Carbonell-Asins32, Rossana Villagrasa33, Rita Pereira19, Roos E. Pouw34, Elena Jimenez-Martí4, Ana Miralles4, Rodrigo Dientsmann 1,2,3,37✉ and Tania Fleitas Sarah Derks 1234567890();,: © The Author(s) 2025 4,37✉ 27, Ceu Figueiredo 5,6,9, Fatima Carneiro 5,6,8,9, Andrés Cervantes 4,35, | L37: 1 | M37: 1Department of Medical Oncology, Amsterdam University Medical Center (UMC) location Vrije Universiteit Amsterdam, Amsterdam, Netherlands. 2Cancer Biology and Immunology, Cancer Center Amsterdam, Amsterdam, Netherlands. 3Oncode Institute, Amsterdam, Netherlands. 4Department of Medical Oncology, Hospital Clinico Universitario, INCLIVA, Biomedical Research Institute, University of Valencia, Valencia, Spain. 5i3S - Instituto de Investigação e Inovação em Saúde, Universidade do Porto, Porto, Portugal. 6Ipatimup - Institute of Molecular Pathology and Immunology of the University of Porto, Porto, Portugal. 7Pathology Department. Hospital Clínico Universitario de Valencia, INCLIVA, Valencia, Spain. 8Faculty of Medicine of the University of Porto, Porto, Portugal. 9Department of Pathology, Unidade Local de Saúde São João, Porto, Portugal. 10Department of Gastroenterology, Unidade Local de Saúde São João, Porto, Portugal. 11Department of Oncology, Unidade Local de Saúde São João, Porto, Portugal. 12Núcleo B de Innovación en Medicina de Precisión, Instituto Nacional de Medicina Genómica, Ciudad de, México, México. 13Head of Division. Surgical Pathology, National Cancer Institute (INCan), Mexico City, Mexico. 14Department of Gastrointestinal Endoscopy, Instituto Nacional de Cancerología, Mexico City, Mexico. 15Departamento de Tumores de Tubo Digestivo, Instituto Nacional de Cancerología, Ciudad de, México, México. 16Laboratorio de Medicina Traslacional, Instituto Nacional de Cancerología, Ciudad de México, México. 17Department of Pathology, GENPAT, Asunción, Paraguay. 18Medical Oncology Department, Instituto de Previsión Social, Asunción, Paraguay. 19Department of Gastroenterology, Instituto de Previsión Social, Asunción, Paraguay. 20Medical Oncology Department, Instituto Alexander Fleming, Buenos Aires, Argentina. 21Department of Gastroenterology, Faculty of Medicine. Pontificia Universidad Catolica de Chile. Center for Prevention and Control of Cancer (CECAN), Santiago, Chile. 22Faculty of Biological Sciences & Faculty of Medicine. Pontificia Universidad Católica de Chile, Millennium Institute for Immunology and Immunotherapy, Center for Prevention and Control of Cancer (CECAN), Advance Center for Chronic Disease (ACCDIS), Santiago, Chile. 23Department of Respiratory Diseases, Faculty of Medicine. Pontificia Universidad Católica de Chile, Santiago, Chile. 24Department of Pathology, Faculty of Medicine. Pontificia Universidad Católica de Chile, Santiago, Chile. 25Department of Gastroenterology, Faculty of Medicine. Pontificia Universidad Catolica de Chile, Santiago, Chile. 26Facultad de Ciencia de la Salud, Centro de Oncología de Precision, Universidad Mayor, Huechuraba, Chile. 27Oncology Data Science, Vall d’Hebron Institute of Oncology, Barcelona, Spain. 28Medical Oncology Department, Vall d’Hebron Institute of Oncology, Barcelona, Spain. 29Hospital Universitario de Navarra, Navarrabiomed-IdiSNA, Pamplona, Spain. 30Department of Medicine (Oncology, Gastroenterology, Hepatology, and Pulmonology), University of Leipzig Medical Center, Comprehensive Cancer Center Central Germany (CCCG), Leipzig, Germany. 31Anaxomics Biotech, S.L., Barcelona, Spain. 32Department of Bioestatistics, INCLIVA Biomedical Research Institute, Valencia, Spain. 33Department of Gastroenterology, Hospital Clínico Universitario de Valencia, Valencia, Spain. 34Gastroenterology Department. Amsterdam UMC, Amsterdam, The Netherlands. 35CiberOnc. Carlos III Institute, Madrid, Spain. | N37: 1 | O37: 1Department of Medical Oncology, Amsterdam University Medical Center (UMC) location Vrije Universiteit Amsterdam, Amsterdam, Netherlands. 2Cancer Biology and Immunology, Cancer Center Amsterdam, Amsterdam, Netherlands. 3Oncode Institute, Amsterdam, Netherlands. 4Department of Medical Oncology, Hospital Clinico Universitario, INCLIVA, Biomedical Research Institute, University of Valencia, Valencia, Spain. 5i3S - Instituto de Investigação e Inovação em Saúde, Universidade do Porto, Porto, Portugal. 6Ipatimup - Institute of Molecular Pathology and Immunology of the University of Porto, Porto, Portugal. 7Pathology Department. Hospital Clínico Universitario de Valencia, INCLIVA, Valencia, Spain. 8Faculty of Medicine of the University of Porto, Porto, Portugal. 9Department of Pathology, Unidade Local de Saúde São João, Porto, Portugal. 10Department of Gastroenterology, Unidade Local de Saúde São João, Porto, Portugal. 11Department of Oncology, Unidade Local de Saúde São João, Porto, Portugal. 12Núcleo B de Innovación en Medicina de Precisión, Instituto Nacional de Medicina Genómica, Ciudad de, México, México. 13Head of Division. Surgical Pathology, National Cancer Institute (INCan), Mexico City, Mexico. 14Department of Gastrointestinal Endoscopy, Instituto Nacional de Cancerología, Mexico City, Mexico. 15Departamento de Tumores de Tubo Digestivo, Instituto Nacional de Cancerología, Ciudad de, México, México. 16Laboratorio de Medicina Traslacional, Instituto Nacional de Cancerología, Ciudad de México, México. 17Department of Pathology, GENPAT, Asunción, Paraguay. 18Medical Oncology Department, Instituto de Previsión Social, Asunción, Paraguay. 19Department of Gastroenterology, Instituto de Previsión Social, Asunción, Paraguay. 20Medical Oncology Department, Instituto Alexander Fleming, Buenos Aires, Argentina. 21Department of Gastroenterology, Faculty of Medicine. Pontificia Universidad Catolica de Chile. Center for Prevention and Control of Cancer (CECAN), Santiago, Chile. 22Faculty of Biological Sciences & Faculty of Medicine. Pontificia Universidad Católica de Chile, Millennium Institute for Immunology and Immunotherapy, Center for Prevention and Control of Cancer (CECAN), Advance Center for Chronic Disease (ACCDIS), Santiago, Chile. 23Department of Respiratory Diseases, Faculty of Medicine. Pontificia Universidad Católica de Chile, Santiago, Chile. 24Department of Pathology, Faculty of Medicine. Pontificia Universidad Católica de Chile, Santiago, Chile. 25Department of Gastroenterology, Faculty of Medicine. Pontificia Universidad Catolica de Chile, Santiago, Chile. 26Facultad de Ciencia de la Salud, Centro de Oncología de Precision, Universidad Mayor, Huechuraba, Chile. 27Oncology Data Science, Vall d’Hebron Institute of Oncology, Barcelona, Spain. 28Medical Oncology Department, Vall d’Hebron Institute of Oncology, Barcelona, Spain. 29Hospital Universitario de Navarra, Navarrabiomed-IdiSNA, Pamplona, Spain. 30Department of Medicine (Oncology, Gastroenterology, Hepatology, and Pulmonology), University of Leipzig Medical Center, Comprehensive Cancer Center Central Germany (CCCG), Leipzig, Germany. 31Anaxomics Biotech, S.L., Barcelona, Spain. 32Department of Bioestatistics, INCLIVA Biomedical Research Institute, Valencia, Spain. 33Department of Gastroenterology, Hospital Clínico Universitario de Valencia, Valencia, Spain. 34Gastroenterology Department. Amsterdam UMC, Amsterdam, The Netherlands. 35CiberOnc. Carlos III Institute, Madrid, Spain. | Q37: Publicado | U37: British Journal of Cancer | V37: 0 | W37: No | AB37: =AB36-Z37 -> 7207410 | AD37: 45736 | AF37: https://doi.org/10.1038/s41416-025-02979-6
B38: 31 | C38: 2025 | D38: 3 | E38: 3 | G38: Q2 | H38: 3.3 | J38: Genetic Ancestry, Intrinsic Tumor Subtypes, and Breast Cancer Survival in Latin American Women | K38: Daniela Alves da Quinta1,2, Dar ío Rocha3, Cristian Ýañez4, Renata Binato5, Sheila Coelho Soares-Lima5, Xiaosong Huang6, Daiana Ganiewich1, Valentina A.Zavala7, Monica Sans8, Alejandra Lopez-Vazquez9, Jael Quintero9, Olivia Valenzuela9, Antonio Quintero-Ramos10, Alicia Del Toro-Arreola10, Mauricio Cerda11 Katherine Marcelain12, Susanne Crocamo5, Maria Aparecida Nagai13, Dirce M. Carraro14, Marcia Maria Chiquitelli Marques15, Jorge Go ́mez16, Nora Artagaveytia8, Adrian Daneri-Navarro10, Bettina G. Mu ̈ller17, Javier Retamales18, Carlos Velazquez9, Elmer A. Fern ́andez19,20,21, Osvaldo L. Podhajcer1, Eliana Abdelhay5, Ricardo A. Verdugo4,12; the LACRN Investigators22, Andrea S. Llera1, and Laura Fejerman5,23,24 | L38: 1 | M38: 1Laboratorio de Terapia Molecular y Celular, Fundaci´on Instituto Leloir-CONICET, Ciudad de Buenos Aires, Argentina. 2Universidad Argentina de la Empresa (UADE), Instituto de Tecnolog´ıa (INTEC), Buenos Aires, Argentina. 3Universidad Nacional de C´ordoba, Facultad de Ciencias Exactas, F´ısicas y Naturales, C´ordoba, Argentina. 4Programa de Gen´etica Humana, ICBM, Facultad de Medicina, Universidad de Chile, Santiago, Chile. 5Instituto Nacional de Cˆancer, Rio de Janeiro, Brazil. 6Genome Center, College of Biological Sciences, University of California Davis, Davis, California. 7Department of Public Health Sciences, University of California, Davis, Davis, California. 8Hospital de Clinicas Manuel Quintela, Universidad de la Rep´ublica, Montevideo, Uruguay. 9Universidad de Sonora, Hermosillo, Mexico. 10Universidad de Guadalajara, Guadalajara, Mexico. 11Integrative Biology Program, Instituto de Ciencias Biomedicas (ICBM), Centro de Inform´atica M´adica y Telemedicina, Facultad de Medicina, Universidad de Chile, Santiago, Chile. 12Departamento de Oncolog´ıa B´asico Cl´ınico and Centro para la Prevenci´on y el Control del C´ancer (CeCAN), Facultad de Medicina, Universidad de Chile, Santiago, Chile. 13Instituto de Cancer de São Paulo, São Paulo, Brazil. 14AC Camargo Cancer Center, São Paulo, Brazil. 15Hospital de Cancer de Barretos, Barretos, Brazil. 16Health Sciences Center, Texas A&M University, Bryan, Texas. 17Instituto Nacional del C´ancer, Santiago de Chile, Chile. 18Grupo Oncol´ogico Cooperativo Chileno de Investigaci´on, Santiago de Chile, Chile. 19Fundaci´on para el Progreso de la Medicina, ScireLab, C´ordoba, Argentina. 20CONICET, C´ordoba, Argentina. 21FCEFyN, Depto. de Computaci´on, Escuela de Ingenier´ıa Biom´edica, Universidad Nacional de C´ordoba, C´ordoba, Argentina. 22The list of LACRN Investigators with their affiliations is included at the end of the Supplementary Information. 23Department of Public Health Sciences, School of Medicine, University of California Davis, Davis, California. 24University of California Davis Comprehensive Cancer Center, School of Medicine, University of California Davis, Davis, California. | N38: 1 | O38: 1Laboratorio de Terapia Molecular y Celular, Fundaci´on Instituto Leloir-CONICET, Ciudad de Buenos Aires, Argentina. 2Universidad Argentina de la Empresa (UADE), Instituto de Tecnolog´ıa (INTEC), Buenos Aires, Argentina. 3Universidad Nacional de C´ordoba, Facultad de Ciencias Exactas, F´ısicas y Naturales, C´ordoba, Argentina. 4Programa de Gen´etica Humana, ICBM, Facultad de Medicina, Universidad de Chile, Santiago, Chile. 5Instituto Nacional de Cˆancer, Rio de Janeiro, Brazil. 6Genome Center, College of Biological Sciences, University of California Davis, Davis, California. 7Department of Public Health Sciences, University of California, Davis, Davis, California. 8Hospital de Clinicas Manuel Quintela, Universidad de la Rep´ublica, Montevideo, Uruguay. 9Universidad de Sonora, Hermosillo, Mexico. 10Universidad de Guadalajara, Guadalajara, Mexico. 11Integrative Biology Program, Instituto de Ciencias Biomedicas (ICBM), Centro de Inform´atica M´adica y Telemedicina, Facultad de Medicina, Universidad de Chile, Santiago, Chile. 12Departamento de Oncolog´ıa B´asico Cl´ınico and Centro para la Prevenci´on y el Control del C´ancer (CeCAN), Facultad de Medicina, Universidad de Chile, Santiago, Chile. 13Instituto de Cancer de São Paulo, São Paulo, Brazil. 14AC Camargo Cancer Center, São Paulo, Brazil. 15Hospital de Cancer de Barretos, Barretos, Brazil. 16Health Sciences Center, Texas A&M University, Bryan, Texas. 17Instituto Nacional del C´ancer, Santiago de Chile, Chile. 18Grupo Oncol´ogico Cooperativo Chileno de Investigaci´on, Santiago de Chile, Chile. 19Fundaci´on para el Progreso de la Medicina, ScireLab, C´ordoba, Argentina. 20CONICET, C´ordoba, Argentina. 21FCEFyN, Depto. de Computaci´on, Escuela de Ingenier´ıa Biom´edica, Universidad Nacional de C´ordoba, C´ordoba, Argentina. 22The list of LACRN Investigators with their affiliations is included at the end of the Supplementary Information. 23Department of Public Health Sciences, School of Medicine, University of California Davis, Davis, California. 24University of California Davis Comprehensive Cancer Center, School of Medicine, University of California Davis, Davis, California. | Q38: Publicado | U38: Cancer Research Communications | V38: 0 | W38: No | AB38: =AB37-Z38 -> 7207410 | AD38: 45841 | AF38: https://doi.org/10.1158/2767-9764.CRC-25-0014
B39: 32 | C39: 2025 | D39: 2-3 | E39: 10 | F39: 1 | G39: Q1 | H39: 8.3 | I39: 0 | J39: Integrated clinico-molecular analysis of gastric cancer in European and Latin American populations: LEGACY project | K39: R. Dienstmann1,2,3, E. Ruiz-García4,5, M. Alsina6,7, F. Ruiz-Pace1, T. S. Groen-van Schooten8, C. Martínez-Ciarpaglini9, E. A. Fernández-Figueroa10, R. Herrera-Goepfert11, C. Díaz-Romero12, L. Lino-Silva13, A. I. Hernandez-Guerrero14, N. M. Valdez-Reyes5, A. León-Takahashi15, J. C. Falcón-Martínez5, R. E. Pouw16, S. Romero17, R. Villagrasa18, M. Cabeza-Segura17, L. Alarcón-Molero9,19, E. Jimenez-Martí17, A. Miralles17, H. Boggino20, C. Gauna21, R. Pereira21, H. Lezcano22, D. Cantero23, A. Vivancos24, J. Matito24, A. Martin24, M. Gómez24, E. Castillo24, M. Vila24, R. M. Ferreira25,26, R. Barros25,26,27,28, J. Santos-Antunes25,26,27,29, M. Mendes-Rocha25,26,27, A. Costa30, E. Riquelme31, J. C. Roa32, G. Latorre33, B. Freile34, L. Caro35, F. Esteso34, J. O’Connor34, A. Riquelme36, G. Owen37, M. Garrido38, M. Diez-García6, C. Figueiredo25,26,27, C. Caballero20, F. Lordick39, J. Farrés40, S. Derks8, F. Carneiro25,26,27,28, A. Cervantes17,41y & T. Fleitas17,41y | L39: 1 | M39: 1Oncology Data Science, Vall d_x0001_Hebron Institute of Oncology, Barcelona, Spain; 2OC Precision Medicine, Oncoclínicas & Co, São Paulo, Brazil; 3University of VicdCentral University of Catalonia, Barcelona, Spain; 4Departamento de Tumores de Tubo Digestivo, Instituto Nacional de Cancerología, Mexico City; 5Laboratorio de Medicina Traslacional, Instituto Nacional de Cancerología, Mexico City, Mexico; 6Medical Oncology Department, Vall d`Hebron Institute of Oncology, Barcelona; 7Hospital Universitario de Navarra, Navarrabiomed-IdiSNA, Pamplona, Spain; 8Department of Medical Oncology, Amsterdam University Medical Center (UMC), location Vrije Universiteit Amsterdam, Amsterdam, The Netherlands; 9Department of Pathology, Hospital Clínico Universitario de Valencia, Valencia, Spain; 10Núcleo B de Innovación en Medicina de Precisión, Instituto Nacional de Medicina Genómica, Mexico City; Departments of 11Pathology; 12Medical Oncology, Instituto Nacional de Cancerología, Mexico City; 13Head of Division, Surgical Pathology, National Cancer Institute (INCan), Mexico City; 14Department of Gastrointestinal Endoscopy, Instituto Nacional de Cancerología, Mexico City; 15Departamento de Gastroenterología, Instituto Nacional de Cancerología, Mexico City, Mexico; 16Department of Gastroenterology and Hepatology, Amsterdam University Medical Center (UMC), location Vrije Universiteit Amsterdam, Amsterdam, The Netherlands; 17Department of Medical Oncology, Hospital Clinico Universitario, INCLIVA, Biomedical Research Institute, University of Valencia, Valencia; 18Department of Gastroenterology, Hospital Clínico Universitario de Valencia, Valencia; 19Department of Pathology, Hospital General de Valdepeñas, Valdepeñas, Spain; 20Department of Pathology, GENPAT, Asunción; Departments of 21Medical Oncology; 22Pathology; 23Gastroenterology, Instituto de Previsión Social, Asunción, Paraguay; 24Cancer Genomics Lab, Vall d`Hebron Institute of Oncology, Barcelona, Spain; 25IPATIMUPdInstitute of Molecular Pathology and Immunology of the University of Porto, Porto; 26i3SdInstituto de Investigação e Inovação em Saúde, Universidade do Porto, Porto; 27Faculty of Medicine of the University of Porto, Porto; Departments of 28Pathology; 29Gastroenterology; 30Oncology, Unidade Local de Saúde São João, Porto, Portugal; Departments of 31Respiratory Diseases; 32Pathology; 33Gastroenterology, Faculty of Medicine, Pontificia Universidad Católica de Chile, Santiago, Chile; 34Medical Oncology Department, Instituto Alexander Fleming, Buenos Aires; 35Department of Gastroenterology, Instituto Alexander Fleming, GEDYT (Gastroenterologia diagnostica y terapeutica), Buenos Aires, Argentina; 36Department of Gastroenterology, Faculty of Medicine, Pontificia Universidad Católica de Chile, Center for Prevention and Control of Cancer (CECAN), Santiago; 37Faculty of Biological Sciences & Faculty of Medicine, Pontificia Universidad Católica de Chile, Millennium Institute for Immunology and Immunotherapy, Center for Prevention and Control of Cancer (CECAN), Advance Center for Chronic Disease (ACCDIS), Santiago; 38Facultad de Medicina y Ciencia de la Salud, Centro de Oncología de Precision, Universidad Mayor, Santiago, Chile; 39Department of Oncology and University Cancer Center Leipzig, University of Leipzig Medical Center, Leipzig, Germany; 40Anaxomics Biotech S.L., Barcelona; 41Ciberonc, Instituto Carlos III, Madrid, Spain | N39: 1 | O39: 1Oncology Data Science, Vall d_x0001_Hebron Institute of Oncology, Barcelona, Spain; 2OC Precision Medicine, Oncoclínicas & Co, São Paulo, Brazil; 3University of VicdCentral University of Catalonia, Barcelona, Spain; 4Departamento de Tumores de Tubo Digestivo, Instituto Nacional de Cancerología, Mexico City; 5Laboratorio de Medicina Traslacional, Instituto Nacional de Cancerología, Mexico City, Mexico; 6Medical Oncology Department, Vall d`Hebron Institute of Oncology, Barcelona; 7Hospital Universitario de Navarra, Navarrabiomed-IdiSNA, Pamplona, Spain; 8Department of Medical Oncology, Amsterdam University Medical Center (UMC), location Vrije Universiteit Amsterdam, Amsterdam, The Netherlands; 9Department of Pathology, Hospital Clínico Universitario de Valencia, Valencia, Spain; 10Núcleo B de Innovación en Medicina de Precisión, Instituto Nacional de Medicina Genómica, Mexico City; Departments of 11Pathology; 12Medical Oncology, Instituto Nacional de Cancerología, Mexico City; 13Head of Division, Surgical Pathology, National Cancer Institute (INCan), Mexico City; 14Department of Gastrointestinal Endoscopy, Instituto Nacional de Cancerología, Mexico City; 15Departamento de Gastroenterología, Instituto Nacional de Cancerología, Mexico City, Mexico; 16Department of Gastroenterology and Hepatology, Amsterdam University Medical Center (UMC), location Vrije Universiteit Amsterdam, Amsterdam, The Netherlands; 17Department of Medical Oncology, Hospital Clinico Universitario, INCLIVA, Biomedical Research Institute, University of Valencia, Valencia; 18Department of Gastroenterology, Hospital Clínico Universitario de Valencia, Valencia; 19Department of Pathology, Hospital General de Valdepeñas, Valdepeñas, Spain; 20Department of Pathology, GENPAT, Asunción; Departments of 21Medical Oncology; 22Pathology; 23Gastroenterology, Instituto de Previsión Social, Asunción, Paraguay; 24Cancer Genomics Lab, Vall d`Hebron Institute of Oncology, Barcelona, Spain; 25IPATIMUPdInstitute of Molecular Pathology and Immunology of the University of Porto, Porto; 26i3SdInstituto de Investigação e Inovação em Saúde, Universidade do Porto, Porto; 27Faculty of Medicine of the University of Porto, Porto; Departments of 28Pathology; 29Gastroenterology; 30Oncology, Unidade Local de Saúde São João, Porto, Portugal; Departments of 31Respiratory Diseases; 32Pathology; 33Gastroenterology, Faculty of Medicine, Pontificia Universidad Católica de Chile, Santiago, Chile; 34Medical Oncology Department, Instituto Alexander Fleming, Buenos Aires; 35Department of Gastroenterology, Instituto Alexander Fleming, GEDYT (Gastroenterologia diagnostica y terapeutica), Buenos Aires, Argentina; 36Department of Gastroenterology, Faculty of Medicine, Pontificia Universidad Católica de Chile, Center for Prevention and Control of Cancer (CECAN), Santiago; 37Faculty of Biological Sciences & Faculty of Medicine, Pontificia Universidad Católica de Chile, Millennium Institute for Immunology and Immunotherapy, Center for Prevention and Control of Cancer (CECAN), Advance Center for Chronic Disease (ACCDIS), Santiago; 38Facultad de Medicina y Ciencia de la Salud, Centro de Oncología de Precision, Universidad Mayor, Santiago, Chile; 39Department of Oncology and University Cancer Center Leipzig, University of Leipzig Medical Center, Leipzig, Germany; 40Anaxomics Biotech S.L., Barcelona; 41Ciberonc, Instituto Carlos III, Madrid, Spain | Q39: Publicado | U39: ESMO Open | V39: 0 | W39: No | AB39: =AB38-Z39 -> 7207410 | AD39: 45719 | AF39: https://doi.org/10.1016/j.esmoop.2025.104482
B40: 33 | C40: 2025 | D40: 3 | E40: 3 | G40: Q1 | H40: 7.7 | I40: 0 | J40: SKI regulates rRNA transcription and pericentromeric heterochromatin to ensure centromere integrity and genome stability | K40: Víctor Pola-V´ eliza,e,f,g,h , David Carreroa, Eduardo A. Sagredoa,i , Víctor Inostrozaa , Claudio Cappellia,j , Solange Rivasa, Mirit Bitr´ ana, Evelyn Zambranoa,b , Evelin Gonzalezc , Fernanda Moralesa,b , Marcia Manterolaa,d , Martín Montecinoe,f,g,h, Ricardo Armis´ enc , Katherine Marcelaina,b,* | L40: 1 | M40: a Departamento de Oncología B´asico Clínico, Facultad de Medicina, Universidad de Chile, Santiago, Chile b Centro para la prevenci´on y el control del C´ancer (CECAN), Facultad de Medicina, Universidad de Chile, Santiago, Chile c Centro de Gen´etica y Gen´omica, Instituto de Ciencias e Innovaci´on en Medicina, Facultad de Medicina, Clínica Alemana Universidad del Desarrollo, Santiago, Chile d Center for Translational Studies in Stress and Mental Health (C-ESTRES), Universidad de Valparaíso, Valparaíso, Chile e Institute of Biomedical Sciences, Faculty of Medicine, Universidad Andr´es Bello f Millennium Nucleus of Neuroepigenetics and Plasticity g Center for Biomedical Research, Faculty of Medicine, Universidad Andr´es Bello, Santiago, Chile h FONDAP Center for Genome Regulation, Faculty of Biological Sciences, Universidad Andr´es Bello, Santiago, Chile i Current Address: Science for Life Laboratory, Department of Microbiology, Tumor and Cell Biology, Karolinska Institutet, 171 65 Solna, Sweden j Current Address: Laboratorio de Inmunoepigen´etica. Instituto de Bioquímica y Microbiología, Facultad de Ciencias, Universidad Austral de Chile, Valdivia, Chile A | N40: 1 | O40: a Departamento de Oncología B´asico Clínico, Facultad de Medicina, Universidad de Chile, Santiago, Chile b Centro para la prevenci´on y el control del C´ancer (CECAN), Facultad de Medicina, Universidad de Chile, Santiago, Chile c Centro de Gen´etica y Gen´omica, Instituto de Ciencias e Innovaci´on en Medicina, Facultad de Medicina, Clínica Alemana Universidad del Desarrollo, Santiago, Chile d Center for Translational Studies in Stress and Mental Health (C-ESTRES), Universidad de Valparaíso, Valparaíso, Chile e Institute of Biomedical Sciences, Faculty of Medicine, Universidad Andr´es Bello f Millennium Nucleus of Neuroepigenetics and Plasticity g Center for Biomedical Research, Faculty of Medicine, Universidad Andr´es Bello, Santiago, Chile h FONDAP Center for Genome Regulation, Faculty of Biological Sciences, Universidad Andr´es Bello, Santiago, Chile i Current Address: Science for Life Laboratory, Department of Microbiology, Tumor and Cell Biology, Karolinska Institutet, 171 65 Solna, Sweden j Current Address: Laboratorio de Inmunoepigen´etica. Instituto de Bioquímica y Microbiología, Facultad de Ciencias, Universidad Austral de Chile, Valdivia, Chile A | Q40: Publicado | U40: Neoplasia | V40: 0 | W40: No | X40: No | AB40: =AB39-Z40 -> 7207410 | AD40: 45840 | AF40: https://doi.org/10.1016/j.neo.2025.101204
B41: 34 | C41: 2025 | D41: 2-3 | E41: 10 | F41: 1 | G41: Q1 | H41: 12.2 | I41: 1 | J41: Gallbladder Cancer and Dysplasia in Cholecystectomy Specimens: A Large Study in High-Incidence Regions of South America | K41: Felix Boekstegers, Carol Barahona Ponce, Erik Morales, Cesar Muñoz-Castro, Cristian Lindner, Ivan Schneider Lira, Belarmino Manques, Alicia Colombo Flores, Catalina Valenzuela, Jaime Castillo, Gonzalo de Toro, Mauricio Almau, Cristina Inklemona, Carolina Ituarte, Gerardo F. Arroyo, Loreto Spencer, Hector Losada, Juan Carlos Araya, Bruno Nervi, Claudio Mengoa Quintanilla, Paola Montenegro, Ana Lineth Garcia, Sidney Rojas Orellana, Alejandro Ortega, Francisco Rothhammer and Justo Lorenzo Bermejo | L41: 1 | M41: 1Statistical Genetics Research Group, Institute of Medical Biometry, Heidelberg University, Heidelberg, Germany; 2Departamentos de Patología y Cirugía, Facultad de Medicina, Universidad Católica del Maule, Talca, Chile; 3Servicios de Anatomía Patológica y Cirugía Abdominal, Hospital Regional de Talca, Talca, Chile; 4Department of Anatomy Pathology, Faculty of Medicine, Universidad de Chile, Santiago, Chile; 5Pathological Anatomy Service, Clinical Hospital of the University of Chile, Santiago, Chile; 6Department of Basic and Clinical Oncology, Faculty of Medicine, University of Chile, Santiago, Chile; 7Center for Cancer Prevention and Control, Santiago, Chile; 8Department of Surgery, Clinical Hospital of the University of Chile, Santiago, Chile; 9Escuela de Tecnología Médica, Sede Puerto Montt, Universidad Austral de Chile, Puerto Montt, Chile; 10Departamento de Cirugía, Hospital de Rancagua, Rancagua, Chile; 11Servicio de Oncología, Hospital Pablo Soria, San Salvador de Jujuy, Argentina; 12Latin-American Gastrointestinal Oncology Intergroup, San Salvador de Jujuy, Argentina; 13Servicio de Anatomía Patológica, Hospital Clínico Regional Concepción, Concepción, Chile; 14Departamento de Cirugía, Traumatología y Anestesiología, Universidad de la Frontera, Temuco, Chile; 15Departamento de Hematología y Oncología, Escuela de Medicina, Pontificia Universidad Católica de Chile, Santiago, Chile; 16Departamento de Cirugía, Instituto Regional de Enfermedades Neoplásicas, Arequipa, Peru; 17Departamento de Oncología Médica, Instituto Nacional de Enfermedades Neoplásicas, Lima, Peru; 18Instituto de Investigaciones Biomédicas, Facultad de Medicina, Universidad Mayor de San Simón, Cochabamba, Bolivia; 19Departamento de Cirugía, Caja Nacional de Salud Hospital Obrero 2, Cochabamba, Bolivia; 20Servicio de Anatomía Patológica, Hospital Juan Noé Crevani, Arica, Chile; 21Instituto de Alta Investigación, Tarapacá University, Arica, Chile; and 22Laboratory of Biostatistics for Precision Oncology, Institut de Cancérologie Strasbourg Europe, Strasbourg, France | N41: 1 | O41: 1Statistical Genetics Research Group, Institute of Medical Biometry, Heidelberg University, Heidelberg, Germany; 2Departamentos de Patología y Cirugía, Facultad de Medicina, Universidad Católica del Maule, Talca, Chile; 3Servicios de Anatomía Patológica y Cirugía Abdominal, Hospital Regional de Talca, Talca, Chile; 4Department of Anatomy Pathology, Faculty of Medicine, Universidad de Chile, Santiago, Chile; 5Pathological Anatomy Service, Clinical Hospital of the University of Chile, Santiago, Chile; 6Department of Basic and Clinical Oncology, Faculty of Medicine, University of Chile, Santiago, Chile; 7Center for Cancer Prevention and Control, Santiago, Chile; 8Department of Surgery, Clinical Hospital of the University of Chile, Santiago, Chile; 9Escuela de Tecnología Médica, Sede Puerto Montt, Universidad Austral de Chile, Puerto Montt, Chile; 10Departamento de Cirugía, Hospital de Rancagua, Rancagua, Chile; 11Servicio de Oncología, Hospital Pablo Soria, San Salvador de Jujuy, Argentina; 12Latin-American Gastrointestinal Oncology Intergroup, San Salvador de Jujuy, Argentina; 13Servicio de Anatomía Patológica, Hospital Clínico Regional Concepción, Concepción, Chile; 14Departamento de Cirugía, Traumatología y Anestesiología, Universidad de la Frontera, Temuco, Chile; 15Departamento de Hematología y Oncología, Escuela de Medicina, Pontificia Universidad Católica de Chile, Santiago, Chile; 16Departamento de Cirugía, Instituto Regional de Enfermedades Neoplásicas, Arequipa, Peru; 17Departamento de Oncología Médica, Instituto Nacional de Enfermedades Neoplásicas, Lima, Peru; 18Instituto de Investigaciones Biomédicas, Facultad de Medicina, Universidad Mayor de San Simón, Cochabamba, Bolivia; 19Departamento de Cirugía, Caja Nacional de Salud Hospital Obrero 2, Cochabamba, Bolivia; 20Servicio de Anatomía Patológica, Hospital Juan Noé Crevani, Arica, Chile; 21Instituto de Alta Investigación, Tarapacá University, Arica, Chile; and 22Laboratory of Biostatistics for Precision Oncology, Institut de Cancérologie Strasbourg Europe, Strasbourg, France | Q41: Publicado | U41: Clinical Gastroenterology and Hepatology | V41: 0 | W41: No | AB41: =AB40-Z41 -> 7207410 | AD41: 45870 | AF41: https://doi.org/10.1016/j.cgh.2024.12.027
B42: 35 | C42: 2025 | D42: 2-3 | E42: 10 | F42: 1 | G42: Q2 | H42: 3 | J42: Arsenic in drinking water and breast cancer: a case-control study from a high exposure area in Northern Chile | K42: Estela Blanco 1 2, Johanna Acevedo 3 4, Liliana Pérez 2, Marian Herrera 2, Viviana Durán 5, Teresa Barlaro 6, Rodrigo Meza 7, Juan Carlos Roa 8, Roxana Parra 9, Hugo Benitez 9, Molly E Schwalb 10, Craig Steinmaus 11, Catterina Ferreccio 12 13 | L42: 1 | M42: 1College UC, Pontificia Universidad Católica de Chile, Santiago, Chile. 2Escuela de Salud Pública, Pontificia Universidad Católica de Chile, Santiago, Chile. 3Centro de Epidemiología y Políticas de Salud, Facultad de Medicina Clínica Alemana, Universidad del Desarrollo, Santiago, Chile. 4Centro Para La Prevención y Control del Cáncer (CECAN), Santiago, Chile. 5Department of Pathology, Hospital Juan Noé, Arica, Chile. 6Department of Pathology, Hospital Ernesto Torres Galdames de Iquique, Iquique, Chile. 7Department of Pathology, Hospital Carlos Cisternas de Calama, Calama, Chile. 8Department of Pathology, Facultad de Medicina, Pontificia Universidad Católica de Chile, Santiago, Chile. 9Department of Pathology, Hospital Leonardo Guzmán de Antofagasta, Antofagasta, Chile. 10Office of Environmental Health Hazard Assessment, California Environmental Protection Agency, Oakland, CA, USA. 11Arsenic Research Group, School of Public Health, University of California, Berkeley, CA, USA. 12Escuela de Salud Pública, Pontificia Universidad Católica de Chile, Santiago, Chile. cferreccio@ispch.cl. 13Instituto de Salud Pública de Chile, Marathón 1000, Ñuñoa Santiago, Chile. cferreccio@ispch.c | N42: 1 | O42: 1College UC, Pontificia Universidad Católica de Chile, Santiago, Chile. 2Escuela de Salud Pública, Pontificia Universidad Católica de Chile, Santiago, Chile. 3Centro de Epidemiología y Políticas de Salud, Facultad de Medicina Clínica Alemana, Universidad del Desarrollo, Santiago, Chile. 4Centro Para La Prevención y Control del Cáncer (CECAN), Santiago, Chile. 5Department of Pathology, Hospital Juan Noé, Arica, Chile. 6Department of Pathology, Hospital Ernesto Torres Galdames de Iquique, Iquique, Chile. 7Department of Pathology, Hospital Carlos Cisternas de Calama, Calama, Chile. 8Department of Pathology, Facultad de Medicina, Pontificia Universidad Católica de Chile, Santiago, Chile. 9Department of Pathology, Hospital Leonardo Guzmán de Antofagasta, Antofagasta, Chile. 10Office of Environmental Health Hazard Assessment, California Environmental Protection Agency, Oakland, CA, USA. 11Arsenic Research Group, School of Public Health, University of California, Berkeley, CA, USA. 12Escuela de Salud Pública, Pontificia Universidad Católica de Chile, Santiago, Chile. cferreccio@ispch.cl. 13Instituto de Salud Pública de Chile, Marathón 1000, Ñuñoa Santiago, Chile. cferreccio@ispch.c | Q42: Publicado | U42: Breast Cancer Res Treat | V42: 0 | W42: No | AB42: =AB41-Z42 -> 7207410 | AD42: 45846 | AF42: https://doi.org/10.1007/s10549-025-07765-9
B43: 36 | C43: 2025 | D43: 4 | E43: 4 | G43: Q3 | H43: 0.8 | J43: Caracterización de la demanda expresada y efectiva de servicios oncológicos del régimen de Garantías Explícitas de Salud en el sistema de salud público de Chile | K43: Carolina De la Fuentea, b , Paula Bedregala, b* , Paula Zamoranoa, b , Oscar Arteagab, c , Cristian Rebolledob, c , Camilo Oñatec , Pedro Zitkoa, b | L43: 0 | N43: 0 | Q43: Publicado | U43: Medwave | V43: 0 | W43: No | AB43: =AB42-Z43 -> 7207410 | AD43: 45896 | AF43: http://doi.org/10.5867/medwave.2025.07.3070
B44: 37 | C44: 2025 | D44: 3 | E44: 3 | G44: Q1 | H44: 5.9 | I44: 0 | J44: Galectin-9 and Tim-3 in gastric cancer: a checkpoint axis driving T cell exhaustion and Tregmediated immunosuppression independently of anti-PD-1 blockade | K44: Charlotte N. Hill1,2,3,4, Gabriela Maita1,2,3, Camille Cabrolier1,2,3, Constanza Aros3,4, Ana Maria Vega-Letter5, Pamela Gonzalez1,2, Alexis M. Kalergis1,2, Patricia Luz-Crawford2,3,4*and Gareth I. Owen1,2 | L44: 0 | N44: 1 | O44: 1Facultad de Ciencias Biologicas, Pontificia Universidad Catolica de Chile, Santiago de Chile, Chile, 2Millenium Institute for Immunology and Immunotherapy, Santiago de Chile, Chile, 3Laboratorio de Inmunologıa, Centro de Investigacion e Innovacion Biomedica, Facultad de Medicina, Universidad de los Andes, Santiago de Chile, Chile, 4Center of Interventional Medicine for Precision and Advanced Cellular Therapy (IMPACT), Santiago, Chile, 5Escuela de Ingenierıa Bioquımica, Pontificia Universidad Catolica de Valparaıso, Valparaıso, Chile | Q44: Publicado | U44: Frontiers in Immunology | V44: 0 | W44: No | AB44: =AB43-Z44 -> 7207410 | AD44: 45839 | AF44: http://doi.org/10.3389/fimmu.2025.1600792
B45: 38 | C45: 2025 | D45: 2 | E45: 2 | G45: Q2 | H45: 3.4 | J45: D-dimer as a predictive biomarker for cancer-associated thrombosis: A prospective cohort study | K45: E. Elsacaa,e, J. L´opezb,e, A. Valenzuelaa,e, A. Gonz´alezb,e, J. Cerdac,e, B. Nervib,d,e, A. Aizmana,e,* | L45: 0 | N45: 1 | O45: a Department of Internal Medicine, School of Medicine, Pontificia Universidad Cat´olica de Chile, Santiago, Chile b Department of Hematology and Oncology, School of Medicine, Pontificia Universidad Cat´olica de Chile, Santiago, Chile c Department of Public Health, School of Medicine, Pontificia Universidad Cat´olica de Chile, Santiago, Chile d Center for Cancer Prevention and Control (FONDAP-CECAN), Pontificia Universidad Cat´olica de Chile, Santiago, Chile e Red de Salud UC CHRISTUS, Santiago, Chile | Q45: Publicado | U45: Thrombosis Research | V45: 0 | W45: No | AB45: =AB44-Z45 -> 7207410 | AD45: 45896 | AF45: https://doi.org/10.1016/j.thromres.2025.109448
B46: 39 | C46: 2024 | D46: 1 | E46: 1 | G46: Q2 | H46: 2.6 | J46: Association between demographic, clinical characteristics and severe complications by SARS-CoV-2 infection in a community-based healthcare network in Chile. | K46: Leniz J, Hernández-Jaña S, Soto M, Arenas E, Margozzini P, Suarez F, Capurro D, Rojas MP, Bambs C*. | L46: 1 | M46: 1Escuela de Salud Pública, Facultad de Medicina, Pontificia Universidad Católica de Chile, Santiago, Chile. 2IRyS Group, Physical Education School, Pontificia Universidad Católica de Valparaíso, Valparaíso, Chile. 3Departamento de Medicina Familiar, Escuela de Medicina, Pontificia Universidad Católica de Chile, Santiago, Chile. 4Unidad de Gestión de Informática, Ancora UC, Santiago, Chile. 5Center for Cancer Prevention and Control, Fondap 152220002, Faculty of Medicine, Pontificia Universidad Católica de Chile, Santiago, Chile. 6Departamento de Estadística, Análisis y Gestión de la Información en Salud, Servicio de Salud Metropolitano Sur-Oriente, Santiago, Chile. 7School of Computing and Information Systems, University of Melbourne, Melbourne, Australia. 8Advanced Center for Chronic Diseases, Fondap 151300, Faculty of Medicine, Pontificia Universidad Católica de Chile, Santiago, Chile. | N46: 1 | O46: 1Escuela de Salud Pública, Facultad de Medicina, Pontificia Universidad Católica de Chile, Santiago, Chile. 2IRyS Group, Physical Education School, Pontificia Universidad Católica de Valparaíso, Valparaíso, Chile. 3Departamento de Medicina Familiar, Escuela de Medicina, Pontificia Universidad Católica de Chile, Santiago, Chile. 4Unidad de Gestión de Informática, Ancora UC, Santiago, Chile. 5Center for Cancer Prevention and Control, Fondap 152220002, Faculty of Medicine, Pontificia Universidad Católica de Chile, Santiago, Chile. 6Departamento de Estadística, Análisis y Gestión de la Información en Salud, Servicio de Salud Metropolitano Sur-Oriente, Santiago, Chile. 7School of Computing and Information Systems, University of Melbourne, Melbourne, Australia. 8Advanced Center for Chronic Diseases, Fondap 151300, Faculty of Medicine, Pontificia Universidad Católica de Chile, Santiago, Chile. | Q46: Publicado | U46: PLOS One | V46: 0 | W46: No | AD46: 45656 | AF46: https://doi.org/10.1371/journal.pone.0314376
B47: 40 | C47: 2024 | D47: 1 | E47: 1 | G47: Q2 | H47: 3.1 | J47: Use of GuidelineRecommended Heart Failure Drugs in High-, Middle-, and Low-Income Countries: A Systematic Review and Meta-Analysis. | K47: Satheesh G, Dhurjati R, Alston L, Tesfay F, Pant R, Bahiru E, Bambs C, Agarwal A, Peters SAE, Salam A, Johansson I | L47: 1 | Q47: Publicado | U47: Global Heart | V47: 0 | W47: No | AD47: 45547 | AF47: http://doi/10.5334/gh.1355
B48: 41 | C48: 2025 | D48: 1 | E48: 1 | G48: Q4 | H48: 0.2 | J48: Análisis Bayesiano de un ensayo controlado aleatorizado: aspectos matemáticos y clínicos | K48: Jaime Cerda1, Ricardo Castro2, Claudia Bambs1,3,4 y María Elvira Balcells5 | L48: 0 | N48: 1 | O48: 1Escuela de Salud Pública, Pontificia Universidad Católica de Chile, Santiago, Chile. 2Departamento de Medicina Intensiva. Escuela de Medicina, Pontificia Universidad Católica de Chile, Santiago, Chile. 3Centro Avanzado de Enfermedades Crónicas (ACCDiS), Fondap 1513001, Santiago, Chile. 4Centro para la Prevención y el Control del Cáncer (CECAN), Fondap 152220002, Santiago, Chile. 5Departamento de Enfermedades Infecciosas del Adulto. Escuela de Medicina, Pontificia Universidad Católica de Chile, Santiago, Chile. | Q48: Publicado | U48: Rev Chilena Infectol | V48: 0 | W48: No | AD48: 45722 | AF48: https://doi.org/10.4067/s0716-10182025000200119 | AI48: https://doi.org/10.4067/s0716-10182025000200119
B49: 42 | C49: 2025 | D49: 2 | E49: 2 | G49: Q1 | H49: 26.2 | I49: 1 | J49: Helicobacter pylori antibiotic resistance: a global challenge in search of solutions | K49: Christian Schulz ,1,2 Jyh-Ming Liou ,3 Mohamed Alboraie ,4 Jan Bornschein,5,6 Christian Campos Nunez,7 Luiz Gonzaga Coelho,8 Duc Trong Quach ,9 Carlo A Fallone,10 Yi-Chu Chen ,11 Markus Gerhard ,2,12 Javier P Gisbert ,13,14 Hwoon-Yong Jung ,15 Peter H Katelaris,16 Jae Gyu Kim ,17 Hong Lu ,18 Lukas Macke,2,19 Varocha Mahachai,20 Steven F Moss,21 Jose Maria Remes Troche,22 Arnoldo Riquelme ,23,24 Marco Romano,25 Mashiko Setshedi ,26 Stella Smith ,27 Sebastian Suerbaum,2,28 Evariste Tshibangu-Kabamba, 29,30 Ratha-Korn Vilaichone,31 Abbas Yadegar ,32 Yoshio Yamaoka ,33,34 Francis Mégraud,35 Emad M El-Omar ,36 Kentaro Sugano ,37 Peter Malfertheiner 1 | L49: 1 | M49: 1Medical Department 2, LMU Munich, Munich, Germany chr.schulz@med.uni-muenchen.de. 2German Center for Infection Research (DZIF), partner site Munich, Munich, Germany. 3Internal Medicine, National Taiwan University Hospital, Taipei, Taiwan. 4Department of Internal Medicine, Al-Azhar University, Cairo, Egypt. 5Translational Immune Discovery Unit, Medical Research Council Weatherall Institute of Molecular Medicine (MRC WIMM), Radcliffe Department of Medicine, Oxford University, Oxford, England, UK. 6Translational Gastroenterology and Liver Unit, Nuffield Department of Medicine, John Radcliffe Hospital, Oxford University, Oxford, England, UK. 7Department of Gastroenterology and Digestive Endoscopy, Hospital Clínica Bíblica, San José, Costa Rica. 8Instituto Alfa de Gastroenterologia, Belo Horizonte - MG, Belo Horizonte - MG, Brazil. 9Department of Internal Medicine, University of Medicine and Pharmacy at Ho Chi Minh City, Ho Chi Minh City, Vietnam. 10Division of Gastroenterology, McGill University Heath Center, McGill University Faculty of Medicine, Montreal, Quebec, Canada. 11Institute of Epidemiology and Preventive Medicine, College of Public Health, National Taiwan University, Taipei City, Taipei City, Taiwan. 12Institut für Medizinische Mikrobiologie, Immunologie und Hygiene, Technische Universität München, Munich, Germany. 13Gastroenterology, Hospital Universitario de La Princesa, Instituto de Investigación Sanitaria Princesa (IP), Madrid, Spain. 14Centro de Investigación Biomédica en Red de Enfermedades Hepáticas y Digestivas (CIBEREHD), Madrid, Spain. 15Gastroenterology, University of Ulsan College of Medicine, Songpa-gu, Korea (the Republic of). 16Gastroenterology Department, Concord Hospital, Sydney, New South Wales, Australia. 17Division of Gastroenterology, Department of Internal Medicine, Chung-Ang University College of Medicine, Seoul, Korea (the Republic of). 18GI Division, Shanghai Jiao-Tong University School of Medicine Renji Hospital Shanghai Institution of Digestive Disease, Shanghai, China. 19Medical Department 2, Ludwig Maximilian University of Munich, Munich, BY, Germany. 20Center of Excellence in Digestive Diseases, Department of Medicine, Thammasat University, Bangkok, Bangkok, Thailand. 21Medicine, Rhode Island Hospital/Brown University, Providence, Rhode Island, USA. 22Digestive Physiology and Motility Lab, Medical Biological Research Institute, Universidad Veracruzana, Veracruz, Veracruz, Mexico. 23Department of Gastroenterology, Pontificia Universidad Catolica de Chile, Santiago, Región Metropolitana, Chile. 24Center for Prevention and Control of Cancer (CECAN), Pontificia Universidad Católica de Chile, Santiago, Región Metropolitana, Chile. 25Department of Precision Medicine, University of Campania Luigi Vanvitelli, Naples, Italy. 26University of Cape Town, Rondebosch, South Africa. 27Nigerian Institute of Medical Research, Lagos, Nigeria. 28Chair of Medical Microbiology and Hospital Epidemiology, Max von Pettenkofer Institute, Faculty of Medicine, LMU Munich, Munich, Germany. 29Department of Internal Medicine, Faculty of Medicine, University of Mbujimayi, Mbujimayi, Congo (the Democratic Republic of the). 30Research Center for Infectious Disease Sciences, Osaka Metropolitan University, Osaka, Osaka Prefecture, Japan. 31Thammasat University, Bangkok, Bangkok, Thailand. 32Foodborne and Waterborne Diseases Research Center, Research Institute for Gastroenterology and Liver Diseases, Shahid Beheshti University of Medical Sciences, Tehran, Tehran Province, Iran (the Islamic Republic of). 33Department of Environmental and Preventive Medicine, Oita University Faculty Of Medicine, Yufu, Oita Prefecture, Japan. 34Gastroenterology and Hepatology Section, Baylor College of Medicine, Houston, Texas, USA. 35INSERM U1312 BRIC, University of Bordeaux, Talence, Nouvelle-Aquitaine, France. 36UNSW Microbiome Research Centre, University of New South Wales, Sydney, New South Wales, Australia. 37Department of Medicine, Jichi Medical School, Tochigi, Japan. 38Medical Department 2, LMU Munich, Munich, Germany. | Q49: Publicado | U49: GUT | V49: 0 | W49: No | AD49: 45849 | AF49: https://doi.org/10.1136/gutjnl-2025-335523
B50: 43 | C50: 2025 | D50: 2 | E50: 2 | G50: Q2 | H50: 2.8 | J50: OncovigIA: Artificial Intelligence for Early Lung Cancer Detection and Referral in a Chilean Public Hospital | K50: Jose Peña, MD 1,2,3,4; SebastianSantana 5 ; Juan Cristobal Morales, MD 2,3 ; Natalie Pinto 2,6 ; Mariano Suarez5 ; Carola Sanchez3; Juan Carlos Opazo, MD 2,7 ; Rodrigo Villarroel, MD 2 ; Claudio Montenegro, MD 2 ; Bruno Nervi, MD 1,4 ; and Richard Weber, PhD 4,5,8 | L50: 0 | N50: 1 | O50: Departamento de Hematolog´ıa-Oncolog´ıa, Escuela de Medicina, Pontificia Universidad Cat´ olicade Chile, Santiago, Chile 2 Hospital Dr S´ oterodel R´ıo, Santiago, Chile 3 Servicio de Salud Metropolitano Sur Oriente, Santiago, Chile 4 Centro para la Prevenci´ ony el Control del C´ ancer(CECAN), Santiago, Chile 5 Departamento de Ingenier´ıa Industrial, Universidad de Chile, Santiago, Chile 6 Escuela de Enfermer´ıa, Pontificia Universidad Cat´olica de Chile, Santiago, Chile 7 Departamento de Medicina Interna, Escuela de Medicina, Pontificia Universidad Cat´ olicade Chile, Santiago, Chile 8 Instituto Sistemas Complejos de Ingenier´ıa (ISCI), Santiago, Chile | Q50: Publicado | U50: JCO Clinical Cancer Informatics | V50: 0 | W50: No | AD50: 45932 | AF50: https://doi.org/10.1200/CCI-25-00035
B51: 44 | C51: 2025 | D51: 3 | E51: 3 | G51: Q2 | H51: 3.3 | J51: Editorial: Head and neck squamous cell carcinoma: navigating the dawn of personalized medicine | K51: Luis Abel Quiñones1,2,3,4*, Ye Guo5 and Fujun Han6 | L51: 1 | M51: 1Laboratory of Chemical Carcinogenesis and Pharmacogenetics (CQF), Department of Basic and Clinical Oncology, Faculty of Medicine, University of Chile, Santiago, Chile, 2Department of Pharmaceutical Sciences and Technology, Faculty of Chemical and Pharmaceutical Sciences, University of Chile, Santiago, Chile, 3Latin American Network for Implementation and Validation of Clinical Pharmacogenomics Guidelines (RELIVAF), Santiago, Chile, 4Center for Cancer Prevention and Control (CECAN), Santiago, Chile, 5Department of Oncology, Shanghai East Hospital, School of Medicine, Tongji University, Shanghai, China, 6Cancer Centre, First Hospital of Jilin University, Changchun, China | N51: 1 | O51: 1Laboratory of Chemical Carcinogenesis and Pharmacogenetics (CQF), Department of Basic and Clinical Oncology, Faculty of Medicine, University of Chile, Santiago, Chile, 2Department of Pharmaceutical Sciences and Technology, Faculty of Chemical and Pharmaceutical Sciences, University of Chile, Santiago, Chile, 3Latin American Network for Implementation and Validation of Clinical Pharmacogenomics Guidelines (RELIVAF), Santiago, Chile, 4Center for Cancer Prevention and Control (CECAN), Santiago, Chile, 5Department of Oncology, Shanghai East Hospital, School of Medicine, Tongji University, Shanghai, China, 6Cancer Centre, First Hospital of Jilin University, Changchun, China | Q51: Publicado | U51: Frontiers in Oncology | V51: 0 | W51: No | X51: 0 | AD51: 45924 | AF51: https://doi.org/10.3389/fonc.2025.1684617
B52: 45 | C52: 2025 | D52: 2 | E52: 2 | G52: Q4 | H52: 0 | J52: Gastric remnant cancer: a comprehensive narrative review from carcinogenesis to treatment | K52: José Darío Portillo-Miño1,2* , Sandra Cifuentes1,2,3 , Javier Morales1,4 , Melissa Bastidas2 , William Otero2,5,6 , Paulo Pimentel de Assumpção7 , Gonzalo Latorre8 , Megan Neumann9 , Arnoldo Riquelme 8,10 | L52: 1 | M52: 1 Grupo de Investigacion en Enfermedades Infecciosas y Cancer (GINFYCA), Centro de Investigaciones Clínicas, Fundacion Hospital San Pedro. Pasto, Nariño. Colombia. 2 Grupo Colombiano de Investigacion en Helicobacter pylori, Bogotá, Colombia. 3 Gastroenterology and Digestive Endoscopy Unit, Fundación Hospital San Pedro, Pasto, Nariño. Colombia. 4 Oncological Surgery Service, Unidad Funcional del Cuidado Integral del Cáncer del Adulto (UFCA), Fundación Hospital San Pedro, Pasto, Nariño. Colombia. 5 Department of Gastroenterology, Faculty of Medicine, Universidad Nacional de Colombia, Bogotá. Colombia. 6 Department of Gastroenterology, Hospital Universitario Nacional de Colombia, Bogotá. Colombia 7 Oncology Research Center, Federal University of Pará, Pará. Brazil. 8 Department of Gastroenterology, Faculty of Medicine, Pontificia Universidad Católica de Chile, Santiago. Chile. 9 División of Surgery, Faculty of Medicine, Pontificia Universidad Católica de Chile, Santiago, Chile. 10 Centro para la Prevencion y el Control del Cancer (CECAN), Santiago. Chile | N52: 0 | Q52: Publicado | U52: Rev. Gastroenterología del Perú | V52: 0 | W52: No | X52: 0 | AD52: 45930 | AF52: https://doi.org/10.47892/rgp.2025.453.1943
B53: 46 | C53: 2025 | D53: 4 | E53: 4 | G53: Q2 | H53: 2.6 | J53: Inequities in breast cancer outcomes in Chile: An analysis of case fatality ratios and survival rates (2007–2018) | K53: Benjamín Madariaga1, Susana Mondschein 2,3,4∗, Soledad Torres5 | L53: 0 | N53: 1 | O53: 1 Department of Mathematical Engineering, University of Chile, Santiago, Chile, 2 Department of Industrial Engineering, University of Chile, Santiago, Chile, 3 Instituto Sistemas Complejos de Ingeniería (ISCI), Santiago, Chile, 4 Center for Cancer Prevention and Control (CECAN), Santiago, Chile, 5 Clínica Meds, Santiago, Chile | Q53: Publicado | U53: PLOS One | W53: No | AD53: 45929 | AF53: https://doi.org/10.1371/journal.pone.0325252
B54: 47 | C54: 2025 | D54: 3-1 | E54: 10 | F54: 1 | G54: Q4 | H54: 1.4 | J54: Chilean Biobanks: A Snapshot of the Current Landscape | K54: Iskra A. Signore,1,2 Diego I. Romero,2,3,* Gerardo Donoso,2,4,* Carolina Selman,5 Yolanda Espinosa-Parrilla,6–8 Macarena Fuentes-Guajardo,9 Claudia Bambs,2,10 Elisa Alcalde,11 Alejandra Calderón,12 Camila Corvalán,13 Sandro Casavilca-Zambrano,14–16 Juan Carlos Roa,2,17 and Alicia Colombo2,4,18,19 | L54: 1 | M54: 1Faculty of Medicine, Universidad de Atacama, Copiapó, Chile. 2Center for Cancer Prevention and Control (CECAN), Santiago, Chile. 3Tissues and Fluids Biobank of the School of Medicine, Pontificia Universidad Católica de Chile, Santiago, Chile. 4Service of Anatomic Pathology, Hospital Clínico de la Universidad de Chile, Santiago, Chile. 5Subdirection of Diagnostic Units and Biobank, Fundación Arturo López Pérez, Santiago, Chile. 6School of Medicine, Universidad de Magallanes, Punta Arenas, Chile. 7Evolutionary and Medical Genomics of Magallanes (GEMMa), Healthcare, Teaching, and Research Center (CADI-UMAG), Universidad de Magallanes, Punta Arenas, Chile. 8Chilean Group for Hereditary Cancer (GCCH), Punta Arenas, Chile. 9Department of Medical Technology, Faculty of Health Sciences, Universidad de Tarapacá, Arica, Chile. 10School of Public Health, Advanced Center for Chronic Diseases (ACCDiS), Faculty of Medicine, Pontificia Universidad Católica de Chile, Santiago, Chile. 11Hospital Luis Calvo Mackenna, Santiago, Chile. 12Precision Pathology Laboratory (LPP) and Biobank, Universidad de Valparaíso, Valparaíso, Chile. 13Research Center for Food Environments and Prevention of Chronic Diseases Associated with Nutrition (CIAPEC), Institute of Nutrition and Food Technology (INTA), Universidad de Chile, Santiago, Chile. 14National Tumor Bank, Instituto Nacional de Enfermedades Neoplásicas, Lima, Perú. 15International Joint Laboratory of Molecular Anthropological Oncology (LOAM), INEN, IRD, Lima, Perú. 16Faculty of Health Sciences, Universidad de Huánuco, Lima, Perú. 17Department of Pathology, Pontificia Universidad Católica de Chile, Santiago, Chile. 18Department of Basic Clinical Oncology, Faculty of Medicine, Universidad de Chile, Santiago, Chile. 19Department of Pathological Anatomy, Faculty of Medicine, Universidad de Chile, Santiago, Chile. *Both authors contributed equally to this work. | N54: 1 | O54: 1Faculty of Medicine, Universidad de Atacama, Copiapó, Chile. 2Center for Cancer Prevention and Control (CECAN), Santiago, Chile. 3Tissues and Fluids Biobank of the School of Medicine, Pontificia Universidad Católica de Chile, Santiago, Chile. 4Service of Anatomic Pathology, Hospital Clínico de la Universidad de Chile, Santiago, Chile. 5Subdirection of Diagnostic Units and Biobank, Fundación Arturo López Pérez, Santiago, Chile. 6School of Medicine, Universidad de Magallanes, Punta Arenas, Chile. 7Evolutionary and Medical Genomics of Magallanes (GEMMa), Healthcare, Teaching, and Research Center (CADI-UMAG), Universidad de Magallanes, Punta Arenas, Chile. 8Chilean Group for Hereditary Cancer (GCCH), Punta Arenas, Chile. 9Department of Medical Technology, Faculty of Health Sciences, Universidad de Tarapacá, Arica, Chile. 10School of Public Health, Advanced Center for Chronic Diseases (ACCDiS), Faculty of Medicine, Pontificia Universidad Católica de Chile, Santiago, Chile. 11Hospital Luis Calvo Mackenna, Santiago, Chile. 12Precision Pathology Laboratory (LPP) and Biobank, Universidad de Valparaíso, Valparaíso, Chile. 13Research Center for Food Environments and Prevention of Chronic Diseases Associated with Nutrition (CIAPEC), Institute of Nutrition and Food Technology (INTA), Universidad de Chile, Santiago, Chile. 14National Tumor Bank, Instituto Nacional de Enfermedades Neoplásicas, Lima, Perú. 15International Joint Laboratory of Molecular Anthropological Oncology (LOAM), INEN, IRD, Lima, Perú. 16Faculty of Health Sciences, Universidad de Huánuco, Lima, Perú. 17Department of Pathology, Pontificia Universidad Católica de Chile, Santiago, Chile. 18Department of Basic Clinical Oncology, Faculty of Medicine, Universidad de Chile, Santiago, Chile. 19Department of Pathological Anatomy, Faculty of Medicine, Universidad de Chile, Santiago, Chile. *Both authors contributed equally to this work. | Q54: Publicado | U54: Biopreserv Biobank | V54: 0 | W54: No | X54: 0 | AD54: 45929 | AF54: https://doi.org/10.1177/19475535251379990
B55: 48 | C55: 2025 | D55: 3-2 | E55: 10 | F55: 1 | G55: Q1 | H55: 8.9 | I55: 1 | J55: Extracellular matrix protein signaling promotes multi-step cancer vasculogenic mimicry formation | K55: Gabriel Mingo1, Andrés Valdivia1, Gema Nicolle Santander1,14, Nicole Babbitt1,14, Varina Aldana1, Javiera Pradenas1, Pamela González1,14, Cristóbal Canales1,14, Jorge A. Toledo6,7,15, Carolina Ibáñez2,8,9, Francisco Nualart10, Manuel Varas-Godoy5,11, Roger Gejman3, Juan Carlos Roa3,9,14, Andrea Ravasio4, Cristina Bertocchi1,12 and Gareth I. Owen1,2,9,13,14* | L55: 1 | M55: 1Department of Physiology, Faculty of Biological Sciences, Pontificia Universidad Católica de Chile, Santiago, Chile 2Department of Hematology and Oncology, Faculty of Medicine, Pontificia Universidad Católica de Chile, Santiago, Chile 3Department of Pathology, Faculty of Medicine, Pontificia Universidad Católica de Chile, Santiago, Chile 4Institute for Biological and Medical Engineering, Schools of Engineering, Medicine and Biological Sciences, Pontificia Universidad Católica de Chile, Santiago, Chile 5Centro de Biología Celular y Biomedicina (CEBICEM), Facultad de Ciencias, Universidad San Sebastián, Santiago, Chile 6Center for Advanced Clinical Research (CICA), Department of Neurology & Neurosurgery, Faculty of Medicine, Universidad de Chile, Santiago, Chile 7Advanced Scientific Equipment Network (REDECA), Faculty of Medicine, Universidad de Chile, Santiago, Chile 8Fundación Oncomujer, Santiago, Chile 9Center for Cancer prevention and Control (FONDAP-CECAN), Pontificia Universidad Católica de Chile, Santiago, Chile 10Faculty of Biological Sciences, NeuroCellT and Center For Advanced Microscopy (CMA), University of Concepcion, Concepcion, Chile 11Centro Ciencia & Vida, Fundación Ciencia & Vida, Santiago, Chile 12Graduate School of Engineering Science, University of Osaka, Osaka, Japan 13Advanced Center for Chronic Diseases (FONDAP-ACCDiS), Pontificia Universidad Católica de Chile, Santiago, Chile 14Millennium Institute on Immunology and Immunotherapy, Santiago 8331150, Chile 15Departamento de Ciencias de la Salud Universidad de Ayséén Coyhaique, Coyhaique, Chile | N55: 1 | O55: 1Department of Physiology, Faculty of Biological Sciences, Pontificia Universidad Católica de Chile, Santiago, Chile 2Department of Hematology and Oncology, Faculty of Medicine, Pontificia Universidad Católica de Chile, Santiago, Chile 3Department of Pathology, Faculty of Medicine, Pontificia Universidad Católica de Chile, Santiago, Chile 4Institute for Biological and Medical Engineering, Schools of Engineering, Medicine and Biological Sciences, Pontificia Universidad Católica de Chile, Santiago, Chile 5Centro de Biología Celular y Biomedicina (CEBICEM), Facultad de Ciencias, Universidad San Sebastián, Santiago, Chile 6Center for Advanced Clinical Research (CICA), Department of Neurology & Neurosurgery, Faculty of Medicine, Universidad de Chile, Santiago, Chile 7Advanced Scientific Equipment Network (REDECA), Faculty of Medicine, Universidad de Chile, Santiago, Chile 8Fundación Oncomujer, Santiago, Chile 9Center for Cancer prevention and Control (FONDAP-CECAN), Pontificia Universidad Católica de Chile, Santiago, Chile 10Faculty of Biological Sciences, NeuroCellT and Center For Advanced Microscopy (CMA), University of Concepcion, Concepcion, Chile 11Centro Ciencia & Vida, Fundación Ciencia & Vida, Santiago, Chile 12Graduate School of Engineering Science, University of Osaka, Osaka, Japan 13Advanced Center for Chronic Diseases (FONDAP-ACCDiS), Pontificia Universidad Católica de Chile, Santiago, Chile 14Millennium Institute on Immunology and Immunotherapy, Santiago 8331150, Chile 15Departamento de Ciencias de la Salud Universidad de Ayséén Coyhaique, Coyhaique, Chile | Q55: Publicado | S55: 1252982911 | T55: 45917 | U55: Cell Communication and Signaling | V55: 1 | W55: Gareth Owen | X55: 12-2025 | Y55: USD 2.787 | Z55: 2684132 | AD55: 45938 | AF55: https://doi.org/10.1186/s12964-025-02428-0
B56: 49 | C56: 2024 | D56: 3 | E56: 3 | G56: Q1 | H56: 10.1 | I56: 1 | J56: Advances in machine learning for tumour classification in cancer of unknown primary: A mini-review | K56: Karen Or´ostica a,**, Felipe Mardones a, Yanara A. Bernal b, Samuel Molina c, Marcos Orchard c, Ricardo A. Verdugo a,d, Daniel Carvajal-Hausdorf e, Katherine Marcelain d,f, Seba Contreras g,*, Ricardo Armisen | L56: 1 | M56: a Facultad de Medicina, Universidad de Talca, Talca, Chile b Centro de Gen´etica y Gen´omica, Instituto de Ciencias e Innovaci´on en Medicina, Facultad de Medicina Clínica Alemana Universidad del Desarrollo, Santiago, Chile c Department of Electrical Engineering, Faculty of Physical and Mathematical Sciences, University of Chile, Av. Tupper 2007, Casilla 412-3, Santiago, 8370451, Chile d Departamento de Oncología B´asico Clínica, Facultad de Medicina, Universidad de Chile, Santiago, Chile e Anatomia Patol´ogica, Clinica Alemana, Facultad de Medicina Universidad del Desarrollo, Santiago, Chile f Centro Para La Prevenci´on y el Control del C´ancer, Universidad de Chile, Santiago, Chile g Max Planck Institute for Dynamics and Self-Organization, G¨ottingen, Germany | N56: 1 | O56: a Facultad de Medicina, Universidad de Talca, Talca, Chile b Centro de Gen´etica y Gen´omica, Instituto de Ciencias e Innovaci´on en Medicina, Facultad de Medicina Clínica Alemana Universidad del Desarrollo, Santiago, Chile c Department of Electrical Engineering, Faculty of Physical and Mathematical Sciences, University of Chile, Av. Tupper 2007, Casilla 412-3, Santiago, 8370451, Chile d Departamento de Oncología B´asico Clínica, Facultad de Medicina, Universidad de Chile, Santiago, Chile e Anatomia Patol´ogica, Clinica Alemana, Facultad de Medicina Universidad del Desarrollo, Santiago, Chile f Centro Para La Prevenci´on y el Control del C´ancer, Universidad de Chile, Santiago, Chile g Max Planck Institute for Dynamics and Self-Organization, G¨ottingen, Germany | Q56: Publicado | U56: Cancer Letters | W56: No | AD56: 45624 | AF56: https://doi.org/10.1016/j.canlet.2024.217348
A57: NF | B57: 50 | C57: 2025 | D57: 3 | E57: 3 | G57: Q2 | H57: 3.9 | J57: Basic-Clinical Analysis of Parathyroid Cancer | K57: Lucas Fuenzalida 1,2,3,† , Sebastián Indo 3,4,†, Héctor R. Contreras 3,4,5 , Daniel Rappoport 2 and Patricio Cabané | L57: 0 | N57: 1 | O57: 1 Doctorate in Medical Sciences and Clinical Specialty Program, Postgraduate School, Faculty of Medicine, University of Chile, Santiago 8320328, Chile; lucas.fuenzalida@ug.uchile.cl 2 Department of Surgery, Clinical Hospital—University of Chile, Santiago 8320328, Chile; rappoport@uchile.cl 3 Laboratory of Cellular and Molecular Oncology, Department of Basic and Clinical Oncology, Faculty of Medicine, University of Chile, Santiago 8320328, Chile; srindo.cofre@gmail.com (S.I.); hcontrer@uchile.cl (H.R.C.) 4 Department of Medical Technology, Faculty of Medicine, University of Chile, Santiago 8320328, Chile 5 Center for Cancer Prevention and Control (CECAN), Santiago 8380453, Chile 6 Department of Surgery, Faculty of Medicine, Universidad Andres Bello, Santiago 7501015, Chile 7 Department of Head and Neck Surgery, Clinca INDISA, Santiago 7520440, Chile | Q57: Publicado | U57: Biomedicines | W57: No | AD57: 45727 | AF57: https://doi.org/10.3390/biomedicines13030687
B58: 51 | C58: 2025 | D58: 2 | E58: 2 | G58: Q3 | H58: 0.8 | J58: Retrospective study on disparities in time-totreatment by health insurance system in Chilean breast cancer patients | K58: Johanna Acevedo, Teresa Ip, Lea Maureira, Cesar Sanchez, Claudia Osorio, Claudia Carvajal, Rafael Araosa, Hernan Letelier, Francisco Acevedo, Tomas Merino | L58: 0 | N58: 1 | O58: aInstituto de Ciencias e Innovación en Medicina, ICIM, Facultad de Medicina Clínica Alemana Universidad del Desarrollo, Santiago, Chile; bCentro para la Prevención y Control del Cáncer (CECAN), Santiago, Chile; cServicio de Radioterapia, Hospital Regional de Talca, Talca, Chile; dFacultad de Medicina, Pontificia Universidad Católica de Chile, Santiago, Chile; eServicio de Radioterapia, Instituto Nacional del Cáncer, Santiago, Chile; fServicio de Radioterapia, Clínica Alemana de Santiago, Santiago, Chile; gThe GENomic Epidemiology in Emergent Diseases project (GENE2DIS), Santiago, Chile; hServicio de Radioterapia, Fundación Arturo López Pérez, Santiago, Chile | Q58: Publicado | U58: Medwave | W58: No | AD58: 45757 | AF58: https://DOI.org/10.5867/medwave.2025.03.3033
B59: 52 | C59: 2025 | D59: 2 | E59: 2 | G59: Q2 | H59: 2.2 | J59: Are we ready? assessing effectiveness and implementation of cancer control strategies in primary care: a comprehensive review of systematic reviews | K59: Javiera Martinez-Gutierrez , María Gabriela Soto, Andrea Rioseco, Catalina Bienzobas,Madeline Fowler, Gonzalo Ulloa, Mauricio Soto, Jon David Emery, Klaus Puschel | L59: 1 | M59: 1Department of Family and Community Medicine, School of Medicine, Pontificia Universidad Católica de Chile, Vicuña Mackenna 4860, Macul, Santiago, Región Metropolitana, 7820436, Chile 2Centre for Cancer Research and Department of General Practice, University of Melbourne, 780 Elizabeth St, Melbourne Victoria 3010, Australia 3Center for Cancer Prevention and Control (CECAN), ANID FONDAP ID 152220002, Avda. Libertador Bernando O'Higgins 340, Santiago, 3580000 Chile 4School of Public Health, Pontificia Universidad Católica de Chile, Avda. Libertador Bernando O’Higgins 340, Santiago, 3580000 Chile 5Department of Hematology and Oncology, School of Medicine, Pontificia Universidad Católica de Chile, Avda. Libertador Bernando O’Higgins 340, Santiago, 3580000 Chile 6The Primary Care Unit, University of Cambridge, Forvie Site, Robinson Way, Cambridge CB2 0SR, United Kingdom | N59: 0 | Q59: Publicado | U59: Family Practice | W59: No | AD59: 45695 | AF59: https://doi.org/10.1093/fampra/cmae078
A60: NF | B60: 53 | C60: 2025 | D60: 2 | E60: 2 | G60: Q1 | H60: 5.3 | J60: BTK inhibitors are a possible emerging therapeutic target for gastric cancer | K60: José Darío Portillo-Miño, Jhon Jairo Calderon, and Arnoldo Riquelme | L60: 1 | M60: 1Infectious Diseases and Cancer Research Group (GINFYCA), Clinical Research Center, Fundación Hospital San Pedro, Pasto, Nariño, Colombia; 2Colombian Research Group on Helicobacter pylori, Bogota, Colombia; 3Grupo de Inmunobiologia y Biologia Celular, Facultad de Ciencias, Pontificia Universidad Javeriana, Bogota, Colombia; 4Department of Gastroenterology, Faculty of Medicine, Pontifical Catholic University of Chile, Santiago, Chile; 5Centro para el Control y Prevencion del Cancer (CECAN), Santiago, Chile | N60: 0 | Q60: Publicado | U60: Molecular Therapy Oncology | W60: No | AD60: 45736 | AF60: https://doi.org/10.1016/j.omton.2025.200935
A61: CF | B61: 54 | C61: 2025 | D61: 2 | E61: 2 | G61: Q1 | H61: 8.1 | I61: 1 | J61: Gastric Cancer Screening in the United States: A Review of Current Evidence, Challenges, and Future Perspectives | K61: Dan Li, MD1, Douglas R. Morgan, MD, MPH, FACG, Juan E. Corral, MD, Elizabeth A. Montgomery, MD, Arnoldo Riquelme, MD and Shailja C. Shah, MD, MPH | L61: 1 | M61: 1Department of Gastroenterology, Kaiser Permanente Medical Center, Santa Clara, California, USA; 2Kaiser Permanente Northern California Division of Research, Oakland, California, USA; 3Division of Gastroenterology, The University of Alabama at Birmingham, Birmingham, Alabama, USA; 4Division of Gastroenterology, Prisma Health, Greenville, South Carolina, USA; 5Department of Pathology, University of Miami Miller School of Medicine, Miami, Florida, USA; 6Department of Gastroenterology, Faculty ofMedicine, Pontificia Universidad Cato´ lica de Chile, Center for Control and Prevention of Cancer (CECAN), Santiago, Chile; 7Division of Gastroenterology, University of California, San Diego, La Jolla, California, USA; 8Gastroenterology Section, Jennifer Moreno Department of Veterans Affairs Medical Center, La Jolla, California, USA. | N61: 0 | Q61: Publicado | U61: Amer J. of Gastroenterology | W61: No | AD61: 45728 | AF61: https://doi.org/10.14309/ajg.0000000000003301
A62: CF | B62: 55 | C62: 2025 | D62: 2 | E62: 2 | G62: Q1 | H62: 2.6 | J62: Global determinants of gynecologic cancer incidence and mortality: A cluster-based analysis with predictive insights | K62: Mauricio A. Cuello, Fernán Gomez-Valenzuela, | Ignacio Wichmann, Alexander B. Olawaiye | L62: 1 | M62: 1Department of Gynecology, School of Medicine, Pontificia Universidad Católica de Chile (PUC), Santiago, Chile 2Gynecologic Oncology Unit, Hospital Clínico Universidad Católica, UC-Christus Health Network, Santiago, Chile 3Center for Cancer Prevention and Control (CECAN), Santiago, Chile 4Precision Oncology Center, School of Medicine, Universidad Mayor, Santiago, Chile 5Department of Obstetrics, School of Medicine, Pontificia Universidad Católica de Chile, Santiago, Chile 6Division of Oncology, Department of Medicine, Stanford University School of Medicine, Stanford, California, USA 7Division of Gynecologic Oncology, Department of Obstetrics, Gynecology and Reproductive Sciences, University of Pittsburgh School of Medicine, Pittsburgh, Pennsylvania, USA | N62: 0 | Q62: Publicado | U62: Int J Gynecol Obstet | W62: No | AD62: 45904 | AF62: https://doi.org/10.1002/ijgo.70279.
A63: CF | B63: 56 | C63: 2025 | D63: 2 | E63: 2 | G63: Q1 | H63: 2.6 | J63: Re-evaluating prognostic indicators: The critical role of body composition and gene expression in endometrial cancer outcomes | K63: Mauricio A. Cuello, Fernán Gómez-Valenzuela, Enrique Ossandón, Ignacio Wichmann, Elisa Orlandini, Nicolás Sáez, Jorge Brañes, Sumie Kato, Carolina Ibañez | L63: 1 | M63: 1Department of Gynecology, School of Medicine, Pontificia Universidad Católica de Chile (PUC), Santiago, Chile 2Gynecologic Oncology Unit, Hospital Clínico Universidad Católica, UC-Christus Health Network, Santiago, Chile 3Center for Cancer Prevention and Control (CECAN), Santiago, Chile 4Advanced Center for Chronic Diseases (ACCDiS), Santiago, Chile 5Precision Oncology Center, School of Medicine, Universidad Mayor, Santiago, Chile 6Department of Obstetrics, School of Medicine, Pontificia Universidad Católica de Chile, Santiago, Chile 7Division of Oncology, Department of Medicine, Stanford University School of Medicine, Stanford, California, USA 8Department of Hematology and Oncology, School of Medicine, Pontificia Universidad Católica de Chile (PUC), Santiago, Chile | N63: 1 | O63: 1Department of Gynecology, School of Medicine, Pontificia Universidad Católica de Chile (PUC), Santiago, Chile 2Gynecologic Oncology Unit, Hospital Clínico Universidad Católica, UC-Christus Health Network, Santiago, Chile 3Center for Cancer Prevention and Control (CECAN), Santiago, Chile 4Advanced Center for Chronic Diseases (ACCDiS), Santiago, Chile 5Precision Oncology Center, School of Medicine, Universidad Mayor, Santiago, Chile 6Department of Obstetrics, School of Medicine, Pontificia Universidad Católica de Chile, Santiago, Chile 7Division of Oncology, Department of Medicine, Stanford University School of Medicine, Stanford, California, USA 8Department of Hematology and Oncology, School of Medicine, Pontificia Universidad Católica de Chile (PUC), Santiago, Chile | Q63: Publicado | U63: Int J Gynecol Obstet | W63: No | AD63: 45709 | AF63: https:/DOI.org/10.1002/ijgo.70016
B64: 57 | C64: 2025 | D64: 2 | E64: 2 | G64: Q1 | H64: 5.8 | J64: Convalescent plasma therapy and long-term SARS-COV-2 antiviral immune response in a prospective cohort of patients with COVID-19 | K64: Aldo Barrera, Constanza Martínez-Valdebenito, Bruno Nervi, Aracelly Gaete-Argel, Nicolas M.S. G´alvez, Catalina Osses, Cecilia Vizcaya,María E. Ceballos, Jaime Pereira, Mayling Chang, Luis Rojas, Sebastian Mondaca, Carolina Henríquez, Alexis M. Kalergis, Alessandro Sette, Alba Grifoni, Ricardo Soto-Rifo, Fernando Valiente-Echeverría, Marcela Ferres, María E. Balcells, Nicole Le Corre a | L64: 1 | M64: a Departamento de Enfermedades Infecciosas e Inmunología Pedi´atricas, Facultad de Medicina, Pontificia Universidad Cat´olica de Chile, Santiago, Chile b Red Salud UC-CHRISTUS, Laboratorio de Infectología y Virología Molecular, Santiago, Chile c Departamento de Hematología y Oncología, Facultad de Medicina, Pontificia Universidad Cat´olica de Chile, Santiago, Chile d Centro para la Prevenci´on y Control del C´ancer (CECAN), Santiago, Chile e Laboratorio de Virología Molecular y Celular, Programa de Virología, Instituto de Ciencias Biom´edicas, Facultad de Medicina, Universidad de Chile, Santiago, Chile f Millennium Institute on Immunology and Immunotherapy, Facultad de Ciencias Biol´ogicas, Facultad de Medicina, Pontificia Universidad Cat´olica de Chile, Santiago, Chile g Departamento de Enfermedades Infecciosas del Adulto, Facultad de Medicina, Pontificia Universidad Cat´olica de Chile, Santiago, Chile h Departamento de Medicina Interna, Programa de Farmacología y Toxicología, Facultad de Medicina, Pontificia Universidad Cat´olica de Chile, Santiago, Chile i Departamento de Endocrinología, Facultad de Medicina, Pontificia Universidad Cat´olica de Chile, Santiago, Chile j Center for Infectious Disease and Vaccine Research, La Jolla Institute for Immunology, La Jolla, CA 92037, USA A | N64: 1 | O64: a Departamento de Enfermedades Infecciosas e Inmunología Pedi´atricas, Facultad de Medicina, Pontificia Universidad Cat´olica de Chile, Santiago, Chile b Red Salud UC-CHRISTUS, Laboratorio de Infectología y Virología Molecular, Santiago, Chile c Departamento de Hematología y Oncología, Facultad de Medicina, Pontificia Universidad Cat´olica de Chile, Santiago, Chile d Centro para la Prevenci´on y Control del C´ancer (CECAN), Santiago, Chile e Laboratorio de Virología Molecular y Celular, Programa de Virología, Instituto de Ciencias Biom´edicas, Facultad de Medicina, Universidad de Chile, Santiago, Chile f Millennium Institute on Immunology and Immunotherapy, Facultad de Ciencias Biol´ogicas, Facultad de Medicina, Pontificia Universidad Cat´olica de Chile, Santiago, Chile g Departamento de Enfermedades Infecciosas del Adulto, Facultad de Medicina, Pontificia Universidad Cat´olica de Chile, Santiago, Chile h Departamento de Medicina Interna, Programa de Farmacología y Toxicología, Facultad de Medicina, Pontificia Universidad Cat´olica de Chile, Santiago, Chile i Departamento de Endocrinología, Facultad de Medicina, Pontificia Universidad Cat´olica de Chile, Santiago, Chile j Center for Infectious Disease and Vaccine Research, La Jolla Institute for Immunology, La Jolla, CA 92037, USA A | Q64: Publicado | U64: Current Research in Microbial Sciences | W64: No | AD64: 45847 | AF64: https://doi.org/10.1016/j.crmicr.2025.100440
A65: NF | B65: 58 | C65: 2025 | D65: 2 | E65: 2 | G65: Q2 | H65: 3.4 | J65: OLGA and OLGIM staging systems on the risk assessment of gastric cancer: a systematic review and meta‑analysis of prospective cohorts | K65: Harold Benites-Goñi , Dacio Cabrera-Hinojosa , Gonzalo Latorre, Adrian V. Hernandez, Hugo Uchima and Arnoldo Riquelme | L65: 1 | M65: Harold Benites-Goñi Unidad de Revisiones Sistemáticas y Metaanálisis, Universidad San Ignacio de Loyola, Avenida La Fontana 550, 15024, Lima, Peru Department of Gastroenterology, Hospital Nacional Edgardo Rebagliati Martins, Lima, Peru hbenites@usil.edu.pe Dacio Cabrera-Hinojosa Department of Gastroenterology, Hospital Nacional Dos de Mayo, Lima, Peru Gonzalo Latorre Department of Gastroenterology, Pontificia Universidad Católica de Chile, Santiago, Chile Adrian V. Hernandez Unidad de Revisiones Sistemáticas y Metaanálisis, Universidad San Ignacio de Loyola, Lima, Peru Health Outcomes, Policy and Evidence Synthesis Group, University of Connecticut School of Pharmacy, Storrs, CT, USA Hugo Uchima Endoscopy Unit, Teknon Medical Center, Barcelona, Spain Endoscopy Unit, Gastroenterology Department, Hospital Universitari Germans Trias i Pujol, Badalona, Spain Arnoldo Riquelme Department of Gastroenterology, Pontificia Universidad Católica de Chile, Santiago, Chile Centro para la Prevención y el Control del Cáncer, Santiago, Chile | N65: 0 | Q65: Publicado | U65: Therapeutic Advances in Gastroenterology | W65: No | AD65: 45706 | AF65: https://DOI.org/10.1177/17562848251325461
A66: NF | B66: 59 | C66: 2025 | D66: 2-3 | E66: 10 | F66: 1 | G66: Q2 | H66: 3.3 | J66: The mutational landscape and actionable targets of gallbladder cancer: an ancestry-informed and comparative analysis of a Chilean population | K66: Jose Ignacio Erices, Evelin Gonzalez, Marcela Salgado, Carol Barahona-Ponce, Matías Freire, Gonzalo Sepúlveda-Hermosilla, Diego Ampuero, Alejandro Blanco, Valentina Gárate-Calderón, Pablo Báez-Benavides, Camilo Tapia-Valladares, Jessica Toro, Iván Gallegos, Olga Barajas, Mónica Ahumada, Verónica Sanhueza, Loreto Spencer, Gonzalo De Toro, Erik Morales, Lorena Gutiérrez, Fernanda Morales, Arnaldo Marin, Nelson M. Varela, Justo Lorenzo Bermejo, Ricardo Armisen, and Katherine Marcelain* | L66: 0 | N66: 1 | O66: 1Departamento de Oncolog´ıa Ba´ sico Cl´ınico, Facultad de Medicina, Universidad de Chile, Santiago, Chile, 2Centro de Gene´ tica y Geno´ mica, Instituto de Ciencias e Innovacio´ n en Medicina, Facultad de Medicina Cl´ınica Alemana, Universidad del Desarrollo, Santiago, Chile, 3Departamento de Tecnolog´ıa Me´ dica, Facultad de Medicina, Universidad de Chile, Santiago, Chile, 4Statistical Genetics Research Group, Institute of Medical Biometry, Heidelberg University, Heidelberg, Germany, 5Corporación de Fomento de la Producción (CORFO) Center of Excellence in Precision Medicine, Pfizer Chile, Santiago, Chile, 6Centro de Informa´ tica Me´ dica y Telemedicina, Facultad de Medicina, Universidad de Chile, Santiago, Chile, 7Centro para la Prevencio´ n y el Control del Ca´ ncer, Centro para la Prevención y el Control del Cáncer (CECAN), Universidad de Chile, Santiago, Chile, 8Departamento de Anatom´ıa Patolo´ gica, Hospital Cl´ınico de la Universidad de Chile, Santiago, Chile, 9Departamento de Medicina Interna, Hospital Cl´ınico de la Universidad de Chile, Santiago, Chile, 10Department of Pathology, Hospital Padre Hurtado, Santiago, Chile, 11Department of Pathology, Hospital Cl´ınico Regional Guillermo Grant Benavente, Concepcio´ n, Chile, 12School of Medical Technology, Universidad Austral de Chile at Puerto Montt, Puerto Montt, Chile, 13Department of Pathology, Hospital Regional de Talca, Talca, Chile, 14Department of Preclinical Sciences, Faculty of Medicine, Universidad Cato´ lica del Maule, Talca, Chile, 15Department of Pathology, Hospital San Juan de Dios, Santiago, Chile | Q66: Publicado | U66: Frontiers in Oncology | V66: 0 | W66: No | X66: 0 | AD66: 45933 | AF66: https://DOI.org/10.3389/fonc.2025.1658528
A67: NF | B67: 60 | C67: 2025 | D67: 3 | E67: 3 | G67: Q4 | H67: 1.4 | J67: Advancing Cancer Research Capability in Peru Through the Integration of Registries With Biobanks | K67: Sandro Casavilca-Zambrano, Juan Contreras-Mancilla, Dany Córdova, Alicia Colombo, Jorge Honles, María Teresa García de Dávila, Milagros Abad-Licham, María López, Tatiana Vidaurre, Duniska Tarco, Gustavo Sarria, Francisco Berrospi, Elodie Caboux, Zisis Kozlakidis, and Stéphane Bertani | L67: 1 | M67: 1Banco Nacional de Tumores, Instituto Nacional de Enfermedades Neoplásicas, Lima, Peru. 2International Joint Laboratory of Molecular Anthropological Oncology (LOAM), INEN, IRD, Lima, Peru. 3Facultad de Ciencias de la Salud Universidad de Huánuco, Lima, Peru. 4Servicio de Anatomía Patológica, Hospital Clinico de la Universidad de Chile, Santiago, Chile. 5Departamento de Oncología Básico Clínico, Facultad de Medicina, Universidad de Chile, Santiago, Chile. 6Centro para la Prevención y el Control del Cáncer (CECAN), Santiago, Chile. 7UMR 152 PHARMADEV, Université de Toulouse, IRD, UPS, Toulouse, France. 8Fundación de Pediatría Garrahan, Buenos Aires, Argentina. 9Hospital Británico, Buenos Aires, Argentina. 10Escuela de Medicina Humana Universidad Privada Antenor Orrego, Trujillo, Peru. 11Departamento de Patología, Instituto Regional de Enfermedades Neoplásicas Norte “Dr. Luis Pinillos Ganoza,” Trujillo, Peru. 12Departamento de Patología, Instituto Regional de Enfermedades Neoplásicas del Centro, Concepción, Peru. 13Instituto Nacional de Enfermedades Neoplásicas, Lima, Peru. 14International Agency for Research on Cancer, Lyon, France. 1 | N67: 0 | Q67: Publicado | U67: Biopreservation and Biobanking | W67: No | AD67: 45700 | AF67: https://doi.org/10.1089/bio.2024.0158
A68: NF | B68: 61 | C68: 2025 | D68: 2 | E68: 2 | G68: Q1 | H68: 9.7 | I68: 1 | J68: Referral Criteria for Specialist Palliative Care for Patients With Dementia | K68: Yuchieh Kathryn Chang 1, Jennifer Philip 2 3 4, Jenny T van der Steen 5 6, Lieve Van den Block 7, Allyn Yin Mei Hum 8 9, Pedro E Pérez-Cruz 10 11, Carlos Paiva 12, Masanori Mori 13, Ping-Jen Chen 14 15 16, Meera R Agar 17, Laura Hanson 18, Catherine J Evans 19, David Hui 1 | L68: 1 | M68: 1Department of Palliative Care, Rehabilitation and Integrative Medicine, University of Texas MD Anderson Cancer Center, Houston. 2Department of Medicine, University of Melbourne, Fitzroy, Australia. 3Department of Palliative Care, St Vincent's Hospital Melbourne, Fitzroy, Australia. 4Department of Palliative Care, Peter MacCallum Cancer Centre, Melbourne, Australia. 5Department of Public Health and Primary Care, Leiden University Medical Center, Leiden, the Netherlands. 6Department of Primary and Community Care and Radboudumc Alzheimer Center, Nijmegen, the Netherlands. 7VUB-UGent End-of-Life Care Research Group, Department of Family Medicine and Chronic Care, Vrije Universiteit Brussel, Brussels, Belgium. 8Department of Palliative Medicine, Tan Tock Seng Hospital, Singapore. 9The Palliative Care Centre for Excellence in Research and Education, Dover Park Hospice, Singapore. 10Sección de Medicina Paliativa, Escuela de Medicina, Pontificia Universidad Católica de Chile, Santiago, Chile. 11Centro para el Control y la Prevención del Cáncer, Santiago, Chile. 12Department of Clinical Oncology, Barretos Cancer Hospital, Barretos, São Paulo, Brazil. 13Division of Palliative and Supportive Care, Seirei Mikatahara General Hospital, Hamamatsu, Shizuoka, Japan. 14Department of Family Medicine and Division of Geriatrics and Gerontology, Kaohsiung Medical University Hospital, Kaohsiung, Taiwan. 15National Center for Geriatrics and Welfare Research, National Health Research Institutes, Miaoli, Taiwan. 16School of Medicine, College of Medicine, National Sun Yat-sen University, Kaohsiung, Taiwan. 17IMPACCT, Faculty of Health, University of Technology Sydney, Sydney, Australia. 18Division of Geriatric Medicine and Palliative Care Program, University of North Carolina at Chapel Hill. 19Cicely Saunders Institute of Palliative Care, Policy and Rehabilitation, King's College London, London, United Kingdom. | N68: 0 | Q68: Publicado | U68: JAMA Network Open | W68: No | AD68: 45791 | AF68: https://doi.org/10.1001/jamanetworkopen.2025.10298
A69: NF | B69: 62 | C69: 2025 | D69: 2 | E69: 2 | G69: Q2 | H69: 3.5 | J69: Impact of a Curriculum Reform in Graduate Students Self-Reported Palliative Care Competencies | K69: Mónica Grez-Artigues MD, Alfredo Rodríguez-Nunez MD, Armando Maldonado-Morgado MD, Felipe Castro MD, Nicolás Orozco MD, Luciana Crispino MD, Francisca Villouta MD, Carolina Jaña MD, Ofelia Leiva-Vásquez MD, MSc, Pedro E. Pérez-Cruz MD, MPH | L69: 0 | N69: 0 | Q69: Publicado | U69: Journal of Pain and Symptom Management | W69: No | AD69: 45940 | AF69: https://doi.org/10.1016/j.jpainsymman.2025.10.003
A70: NF | B70: 63 | C70: 2025 | D70: 2 | E70: 2 | G70: Q2 | H70: 3.5 | J70: Beyond the Pandemic: End-of-Life Care Lessons from Latin America to Inform Future Health Emergencies | K70: Vilma A. Tripodoro, Pedro Pérez-Cruz, Marina Khoury, Martha Ximena León, José Mario López Saca, Verónica Veloso, Ángela Acero, Sebastián Soto-Guerrero, Marco Rodríguez, Michelle Uchida, Ida Korfage, Agnes van der Heide, CO-LIVE Latin America research group | L70: 1 | M70: 1 RED-InPal Pallium Latinoamérica, Buenos Aires, Argentina. 2 ATLANTES, Global Observatory of Palliative Care, Institute of Culture and Society, University of Navarra, Spain 3 Medicina Paliativa, Facultad de Medicina, Pontificia Universidad Católica de Chile, Santiago de Chile, Chile 4 Centro para la Prevención y el Control del Cáncer, CECAN, Santiago, Chile 5 Instituto de Investigaciones Médicas Alfredo Lanari, Universidad de Buenos Aires, Argentina 6 Universidad de La Sabana, Bogotá, Colombia 7 Hospice La Cima, El Salvador 8 Barretos Cancer Hospital, Brazil 9 Erasmus Medical Centre, Rotterdam, The Netherlands | N70: 0 | Q70: Publicado | U70: Journal of Pain and Symptom Management | W70: No | AD70: 45960 | AF70: https://doi.org/10.1016/j.jpainsymman.2025.10.016
A71: NF | B71: 64 | C71: 2025 | D71: 2 | E71: 2 | G71: Q1 | H71: 18 | I71: 1 | J71: The evolution of serious health-related suffering from 1990 to 2021: an update to The Lancet Commission on global access to palliative care and pain relief | K71: Felicia M Knaul, Héctor Arreola-Ornelas, Xiaoxiao J Kwete, Afsan Bhadelia, William E Rosa, Michael Touchton, Oscar Méndez-Carniado, Valentina Vargas Enciso, Tania Pastrana, Joseph R Friedman, Stephen R Connor, Julia Downing, Dean T Jamison, Eric L Krakauer, David Watkins, Renzo Calderon-Anyosa, Rodrigo Garcia-Santisteban, Renu S Nargund, Jim Cleary, Liliana De Lima, Nahla Gafer, Liz Grant, Christian Ntizimira, Pedro E Pérez-Cruz, M R Rajagopal, Dingle Spence, Paul Vila, Lukas Radbruch | L71: 1 | M71: 1Department of Medicine, David Geffen School of Medicine, University of California, Los Angeles, CA, USA; University of Miami Institute for Advanced Study of the Americas, University of Miami, Coral Gables, FL, USA; Tómatelo a Pecho, AC, Mexico City, Mexico; Faculty of Excellence, Tecnológico de Monterrey, Mexico City, Mexico. Electronic address: fknaul@mednet.ucla.edu. 2University of Miami Institute for Advanced Study of the Americas, University of Miami, Coral Gables, FL, USA; Tómatelo a Pecho, AC, Mexico City, Mexico; Institute for Obesity Research, Tecnológico de Monterrey, Monterrey, Mexico; School of Government and Public Transformation, Tecnológico de Monterrey, Monterrey, Mexico; Fundación Mexicana para la Salud, Mexico City, México. 3University of Miami Institute for Advanced Study of the Americas, University of Miami, Coral Gables, FL, USA; Yangzhou Philosophy and Social Science Research and Communication Center, Yangzhou, China. 4University of Miami Institute for Advanced Study of the Americas, University of Miami, Coral Gables, FL, USA; Department of Public Health, College of Health and Human Sciences, Purdue University, West Lafayette, IN, USA. 5University of Miami Institute for Advanced Study of the Americas, University of Miami, Coral Gables, FL, USA; Department of Psychiatry and Behavioral Sciences, Memorial Sloan Kettering Cancer Center, New York, NY, USA. 6University of Miami Institute for Advanced Study of the Americas, University of Miami, Coral Gables, FL, USA; Department of Political Science, University of Miami, Coral Gables, FL, USA. 7Fundación Mexicana para la Salud, Mexico City, México. 8University of Miami Institute for Advanced Study of the Americas, University of Miami, Coral Gables, FL, USA. 9Department for Palliative Medicine, Uniklinik RWTH Aachen, Aachen, Germany; International Association for Hospice and Palliative Care, Houston, TX, USA. 10Department of Psychiatry, University of California, San Diego, CA, USA. 11Worldwide Hospice Palliative Care Alliance, London, UK. 12International Children's Palliative Care Network, Bristol, UK; Cicely Saunders Institute of Palliative Care, Policy & Rehabilitation, within the Florence Nightingale Faculty of Nursing, Midwifery and Palliative Care, King's College, London, UK; Global Health Academy, College of Medicine and Veterinary Medicine, University of Edinburgh, Edinburgh, UK. 13Institute for Global Health Sciences, University of California, San Francisco, CA, USA. 14Department of Global Health & Social Medicine, Harvard Medical School, Boston, MA, USA; Division of Palliative Care & Geriatric Medicine, Massachusetts General Hospital, Boston, MA, USA; Department of Ethics, Social Medicine & Palliative Care, University of Medicine & Pharmacy at Ho Chi Minh City, Ho Chi Minh City, Vietnam. 15Department of Global Health, University of Washington, Seattle, WA, USA. 16Institute for Health Policy, Management and Evaluation, University of Toronto, Toronto, ON, Canada. 17Institute for Obesity Research, Tecnológico de Monterrey, Monterrey, Mexico; Department of Medicine, Charles E Schmidt College of Medicine, Florida Atlantic University, Boca Raton, FL, USA. 18University of Miami Institute for Advanced Study of the Americas, University of Miami, Coral Gables, FL, USA; MD Anderson Cancer Center, Houston, TX, USA. 19Indiana University School of Medicine, Indianapolis, IN, USA. 20International Association for Hospice and Palliative Care, Houston, TX, USA. 21Cicely Saunders Institute of Palliative Care, Policy & Rehabilitation, within the Florence Nightingale Faculty of Nursing, Midwifery and Palliative Care, King's College, London, UK; Khartoum Oncology Hospital, Khartoum, Sudan. 22Usher Institute, University of Edinburgh, Edinburgh, UK. 23African Center for Research on End of Life Care, Kigali, Rwanda. 24Sección Medicina Paliativa, Facultad de Medicina, Pontificia Universidad Católica de Chile, Santiago, Chile; Centro para la Prevención y el Control del Cáncer, Santiago, Chile. 25Pallium India Trust, Kerala, India. 26Department of Community Health and Psychiatry, University of the West Indies, Mona, Jamaica. 27International Association for Hospice and Palliative Care, Houston, TX, USA; Department of Palliative Medicine, University of Bonn, Bonn, Germany. PMID: 40021301 PMCID: PMC11868779 | N71: 0 | Q71: Publicado | U71: Lancet Global Health | W71: No | AD71: 45729 | AF71: https://doi.org/10.1016/S2214-109X(24)00476-5
B72: 65 | C72: 2025 | D72: 2 | E72: 2 | G72: Q4 | H72: 0.3 | J72: Challenges of Updating the Family Health Plan in Chile (2024) | K72: Dino Sepúlveda, María José Guzmán, Vania Zarzar, Maite González, Juan Pablo Rubio, Rafael Araos, Johanna Acevedo | L72: 0 | N72: 1 | O72: 1Instituto de Ciencias e Innovación en Medicina, Universidad del Desarrollo, Santiago, Chile. 2Ministerio de Salud, Santiago, Chile. | Q72: Publicado | U72: Revista Médica de Chile | W72: No | AD72: 45796 | AF72: https://DOI.org/10.4067/s0034-98872025000800576
F89: =SUM(F8:F88) -> 13 | H89: =AVERAGE(H8:H88) -> 4.8359375 | I89: =SUM(I8:I88) -> 13
L90: =SUM(L8:L89) -> 38 | N90: =SUM(N8:N89) -> 44 | W90: Carla Taramasco | X90: 14-2025 | Y90: USD 3255,52 | Z90: 3076890
J91: Actualizado por Carolina Cabrera: 16-10-2025 | W91: FINANCIADO CON FONDOS 2025 $ | Z91: =SUM(Z24:Z88)+Z90 -> 18553612
C94: EN REVISION
C96: 2025 | D96: 1 | J96: Impact of Life’s Essential Eight and Inflammatory Markers on Long-term Cardiovascular Disease Risk and All-cause Mortality: The Heart SCORE Study | K96: *Claudia E. Bambs1,2, *Ian Pollack3, Justin Swanson4, Jiaxuan Duan5, Christopher McKennan5, Kevin Kip6, Daniel Buysse7, Steven E. Reis^3,8 and Anum Saeed^3,8 | L96: 1 | M96: 1. School of Public Health, Faculty of Medicine, Pontificia Universidad Católica de Chile, Santiago, Chile 2. Advanced Center for Chronic Diseases and Center for Cancer Prevention and Control, Faculty of Medicine, Pontificia Universidad Católica de Chile. Santiago, Chile 3. School of Medicine, University of Pittsburgh, PA 4. University of South Florida, Tampa, FL 5. Department of Statistics, University of Pittsburgh, PA 6. Clinical Analytics, UPMC Health Services Division, Pittsburgh, PA 7. Department of Psychiatry, University of Pittsburgh, Pittsburgh, PA. 8. Heart and Vascular Institute, UPMC, Pittsburgh, PA | Q96: Publicado | V96: 0 | W96: No | AD96: 45812 | AF96: https://doi.org/10.1101/2025.06.02.25328831

Sheet  Publicaciones año 2
G1: REGISTRO DE PUBLICACIONES
G3: INFORMADO A ANID - INFORME DE AVANCE NR. 2
G4: 2024 | AH4: Los casilleros de este color deben ser llenados cuando la publicacion se haya relizado
C5: Completar para solicitud de financiamiento | AF5: Saldo UC | AG5: Saldo UCH | AH5: COMPLETAR CUANDO EL PAPER HA SIDO PUBLICADO
A6: Nr. | B6: Año Publicación | C6: WP | D6: WP consignado | E6: Nr pub con otros WP | F6: ISI Q1-Q4 | G6: Nombre publicación | H6: Autores | I6: Número Investigadores CECAN | J6: Nombre investigadores CECAN (Debe incluir 2 ó más) | K6: Nombre Investigadores Asociados CECAN participante | L6: Nombre Postdoc CECAN participante | M6: Nombre Tesistas CECAN participante | N6: Nombre investigadores externos | O6: Nro. Asociadas Internacionales | P6: Publicación con Institución Internacional | Q6: Nro. Asociadas Nacionales | R6: Publicación con Institución Nacional | S6: Objetivo Directo/ Asociado CECAN (Identifíquelo Ej: WP-1 proyecto 1) | T6: Funding % | U6: Estado de la Publicación | V6: Fecha estimada de publicación (En preparación/enviada) | W6: Invoice Nr. | X6: Fecha Invoice | Y6: Revista | Z6: Financiamiento CECAN | AA6: Solicitud de apoyo solicitado por | AB6: Nr. Solicitud de apoyo | AC6: Valor Publicación revista | AD6: Valor $ pagado por UC | AE6: Valor $ pagado por UCH | AF6: 36000000 | AG6: 10000000 | AH6: Fecha de publicación | AI6: Volúmen. Pág. Inicio y final | AJ6: DOI | AK6: ISSN | AL6: Nr. Productividad | AM6: Link paper | AN6: Informado en Informe de Avance
A7: 1 | B7: 2024 | C7: 2-4-5 | D7: 10 | E7: 1 | F7: Q3 | G7: Effects in Quality of Life of a Telemonitoring Platform Amongs Patients with Cancer (EQUALITE): A Randomized Trial Protocol | H7: Felipe Martínez, Carla Taramasco, Manuel Espinoza, Johanna Acevedo, Carolina Goic, and Bruno Nervi | O7: 0 | Q7: 1 | R7: Foro Nacional del Cáncer | U7: Publicado | W7: 2695061 | X7: 5-6 enero 2024 | Y7: MDPI: Methods and protocols | Z7: Si | AA7: Carla Taramasco | AB7: 1 | AC7: USD 1440 | AD7: 1543240 | AF7: Pagado con fondos 2023 | AH7: 2024 | AI7: 7, 24-33 | AJ7: 10.3390/mps7020024 | AK7: 2409-9279 | AM7: MPs | Free Full-Text | Effects on Quality of Life of a Telemonitoring Platform amongst Patients with Cancer (EQUALITE): A Randomized Trial Protocol (mdpi.com) | AN7: 2
A8: 2 | B8: 2023 | C8: 2-4-5 | D8: 10 | E8: 1 | F8: Q1 | G8: Differential Effects of a Telemonitoring Platform in the Development of Chemotherapy-Associated Toxicity: A Randomised Trial Protocol | H8: Felipe Martínez, Carla Taramasco, Manuel Espinoza, Johanna Acevedo, Carolina Goic, Bruno Nervi | O8: 0 | Q8: 1 | R8: Foro Nacional del Cáncer | U8: Publicado | W8: 2713462 | X8: 45295 | Y8: MDPI: Diagnostics | Z8: Si | AA8: Carla Taramasco | AB8: 2 | AC8: CHF 2.340 | AD8: 2507659 | AF8: Pagado con fondos 2023 | AH8: 2024 | AI8: 14, 619-630 | AJ8: 10.3390/diagnostics14060619 | AK8: 2075-4418 | AM8: Diagnostics | Free Full-Text | Differential Effects of a Telemonitoring Platform in the Development of Chemotherapy-Associated Toxicity: A Randomized Trial Protocol (mdpi.com) | AN8: 2
A9: 3 | B9: 2024 | C9: 4 | D9: 4 | F9: Q2 | G9: The legal path for priority setting in Chile: A critical analysis to impove health planning and stewardship | H9: Manuel A. Espinoza, Baltica Cabieses, Carolina Goic, Alejandro Andrade | O9: 0 | Q9: 1 | R9: Chilean Federation of Rare Diseases | U9: Publicado | W9: 2023-1025253-3 | X9: 45282 | Y9: Frontiers in Public Health | Z9: Si | AA9: Manuel Espinoza | AB9: 3 | AC9: USD 2.095 | AD9: 1925452 | AF9: Pagado con fondos 2023 | AH9: 2024 | AI9: 11,1-6 | AJ9: 10.3389/fpubh.2023.1302640 | AK9: 2296-2565 | AM9: Frontiers | The legal path for priority setting in Chile: a critical analysis to improve health planning and stewardship (frontiersin.org) | AN9: 2
A10: 4 | B10: 2024 | C10: 2-5 | D10: 10 | E10: 1 | F10: Q2 | G10: Desafíos en la vigilancia de todos los casos de cáncer: Registro Nacional de Cáncer Chileno | H10: Carla Taramasco, Carla Rimassa, Johanna Acevedo | O10: 0 | Q10: 1 | R10: Escuela de Fonoaudiología, Facultad de Medicina, Universidad de Valparaíso | U10: Publicado | W10: 370 | X10: 45321 | Y10: Medwave | Z10: Si | AA10: Carla Taramasco | AB10: 4 | AC10: 600000 | AD10: 600000 | AF10: Pagado con fondos 2023 | AH10: 27-02-2024 | AI10: 24, 2771-2776 | AJ10: DOI: 10.5867/medwave.2024.01.2771 | AK10: 0717-6384 | AM10: Desafíos en la vigilancia de todos los casos de cáncer en Chile: Registro Nacional de Cáncer - Medwave | AN10: 2
A11: 5 | B11: 2024 | C11: 5 | D11: 5 | F11: Q3 | G11: A Contemporary Review of Breast Cancer Risk Factors and the Role of Artificial Intelligence | H11: Orietta Nicolis, Denisse De Los Angeles and Carla Taramasco | O11: 0 | Q11: 0 | U11: Publicado | W11: 2023-1082281-4 | X11: 45436 | Y11: Frontiers in Oncology | Z11: Si | AA11: Carla Taramasco | AB11: 5 | AC11: 3295 | AD11: =AC11*910.79 -> 3001053 | AF11: =AF6-AD11 -> 32998947 | AH11: 2024 | AI11: 14, 1-18 | AJ11: 10.3389/fonc.2024.1356014 | AK11: 2234-943X | AM11: Frontiers | A contemporary review of breast cancer risk factors and the role of artificial intelligence (frontiersin.org) | AN11: 2
A12: 6 | B12: 2024 | C12: 3 | D12: 3 | F12: Q1 | G12: Distinct Driver Pathway Enrichments and a High Prevalence od TSC2 Mutstions in Right Colon Cancer in Chile: A comparative Analysis | H12: Camilo Tapia-Valladares, Guillermo Valenzuela, Evelin González, Ignacio Maureira, Jessica Toro, Matías Freire, Gonzalo Sepúlveda-Hermosilla, Diego Ampuero, Alejandro Blanco, Iván Gallegos, Fernanda Morales, José I. Erices, Olga Barajas, Mónica Ahumada, Héctor R. Contreras, Jaime González, Ricardo Armisén and Katherine Marcelain | O12: 0 | Q12: 1 | R12: Campus San Felipe, Universidad de Valparaíso, San Felipe, Chile | U12: Publicado | W12: 2890573 | X12: 45415 | Y12: MDPI: International Journal of Molecular Science | Z12: Si | AA12: Katherine Marcelain | AB12: 6 | AC12: 3174.19 | AD12: 2890847 | AF12: =AF11-AD12 -> 30108100 | AH12: 25-04-2024 | AI12: 25, 4695-4712 | AJ12: 10.3390/ijms25094695 | AK12: 1661-6596 | AM12: IJMS | Free Full-Text | Distinct Driver Pathway Enrichments and a High Prevalence of TSC2 Mutations in Right Colon Cancer in Chile: A Preliminary Comparative Analysis (mdpi.com) | AN12: 2
A13: 7 | B13: 2024 | C13: 4 | D13: 4 | F13: Q1 | G13: Barriers to the use of test for early detection of colorectal cancer in Chile | H13: Gabriela Alfaro, Zoltan Berger, Susana Mondschein, Felipe Subiabre, Natalia Yankovic | O13: 0 | Q13: 1 | R13: Business School, Universidad de los Andes | U13: Publicada | W13: 1452656405 | X13: 45398 | Y13: Scientific Reports (de Nature) | Z13: Si | AA13: Manuel Espinoza/Susana Mondschein | AB13: 7 | AC13: 2665 | AD13: =AC13*922.58 -> 2458675.7 | AF13: =AF12-AD13 -> 27649424 | AH13: 2024 | AI13: 14, 8817 | AJ13: https://doi.org/10.1038/s41598-024-58920-z | AK13: 2045-2322 | AM13: Barriers to the use of tests for early detection of colorectal cancer in Chile | Scientific Reports (nature.com) | AN13: 2
A14: 8 | B14: 2024 | C14: 2 | D14: 2 | F14: Q3 | G14: Cancer advocacy in residency education: From principles to competencies | H14: Klaus Puschel, Beti Thompson, Andrea Rioseco, Augusto Leon, Carolina Goic, Isabella Fuentes, Zdenka Vescovi | O14: 1 | P14: Public Health Division, Fred Hutchinson Cancer Research Center, Seattle, WA, United States | Q14: 0 | U14: Publicada | Y14: Journal of Cancer Policy | Z14: No | AF14: =AF13-AD14 -> 27649424 | AH14: 2024 | AI14: 4010047 | AJ14: https://doi.org/10.1016/j.jcpo.2024.100470 | AK14: 2213-5383 | AM14: Cancer advocacy in residency education: From principles to competencies - ScienceDirect | AN14: 2
A15: 9 | B15: 2024 | C15: 2-4 | D15: 10 | E15: 1 | F15: Q3 | G15: Estrategias para la prevención primaria y secundariadel cáncer gástrico: consenso chileno de panel deexpertos con técnica Delfi | H15: Óscar Corsi Sotelo, Margarita Pizarro Rojas, Antonio Rollán Rodríguez,Verónica Silva Figueroa, Raúl Araya Jofréd, María Ester Bufadel Godoy,Pablo Cortés González, Robinson González Donoso, Eduardo Fuentes López,Gonzalo Latorre Selvat, Patricio Medel-Jarah, Diego Reyes Placencia, Mauricio Pizarro Véliz, María Jesús Garchitorena Marqués, María Trinidad Zegers Vial, Francisca Crispi Galleguillos, Manuel A. Espinoza,y Arnoldo Riquelme Pérez | O15: 0 | Q15: 1 | R15: Instituto Chileno Japonés de Enfermedades Digestivas, Hospital Clínico San Borja-Arriarán, Unidad de Gastroenterología y Endoscopia, Hospital Militar de Santiago, Santiago, Chile, Centro de Enfermedades Digestivas, Clínica Universidad de Los Andes, Santiago, Chile, IntegraMédica, Clínica RedSalud Providencia, Santiago, Chile | U15: Publicada | Y15: Gastroenterología y Hepatología | Z15: No | AF15: =AF14-AD15 -> 27649424 | AH15: 2024 | AI15: 1,8 | AJ15: https://doi.org/10.1016/j.gastrohep.2024.01.008 | AK15: 1578-9519 | AM15: Estrategias para la prevención primaria y secundaria del cáncer gástrico: consenso chileno de panel de expertos con técnica Delfi - ScienceDirect | AN15: 2
A16: 10 | B16: 2024 | C16: 3 | D16: 3 | F16: Q2 | G16: Overexpression of REST Represses the Epithelial–Mesenchymal Transition Process and Decreases the Aggressiveness of Prostate Cancer Cells | H16: Sebastián Indo, Octavio Orellana-Serradell, María José Torres, Enrique A. Castellón and Héctor R. Contreras | O16: 0 | Q16: 1 | R16: Millennium Nucleus of Ion Channel-Associated Diseases (MiNICAD), Santiago | U16: Publicada | Z16: No | AF16: =AF15-AD16 -> 27649424 | AH16: 15-03-2024 | AI16: 25 | AJ16: 10.3390/ijms25063332 | AK16: 1661-6596 | AM16: IJMS | Free Full-Text | Overexpression of REST Represses the Epithelial&ndash;Mesenchymal Transition Process and Decreases the Aggressiveness of Prostate Cancer Cells (mdpi.com) | AN16: 2
A17: 11 | B17: 2023 | C17: 2-3 | D17: 10 | E17: 1 | F17: Q1 | G17: Comparison of OLGA and OLGIM as predictors of gastric cancer in a Latin American population: the ECHOS Study | H17: Gonzalo Latorre, Felipe Silva, Isabella Montero, Miguel Bustamante, Eitan Dukes, Javier Uribe, Oscar Corsi Sotelo, Diego Reyes, Eduardo Fuentes-López, Margarita Pizarro, Patricio Medel, Javiera Torres, Juan Carlos Roa, Sebastián Pizarro, Pablo Achurra, Andrés Donoso, Ignacio Wichmann, Alejandro H Corvalán, Javier Chahuan, Roberto Candia, Carlos Agüero, Robinson Gonzalez, Jose Ignacio Vargas, Alberto Espino, M Constanza Camargo, Shailja Shah, Arnoldo Riquelme | O17: 1 | P17: Division of Oncology, Department of Medicine, Stanford University School of Medicine, Stanford, California, USA; Division of Cancer Epidemiology and Genetics, National Cancer Institute, Bethesda, Maryland, USA, Department of Gastroenterology, Veterans Affairs, VA San Diego Healthcare System, San Diego, California, USA, Department of Gastroenterology, University of California San Diego, La Jolla, California, USA | Q17: 0 | U17: Publicada | Y17: GUT | Z17: No | AF17: =AF16-AD17 -> 27649424 | AH17: 2023 | AI17: 0, 1-3 | AJ17: 10.1136/gutjnl-2023-331059 | AK17: 1468-3288 | AM17: https://gut.bmj.com/content/early/2023/12/26/gutjnl-2023-331059.long | AN17: 2
A18: 12 | B18: 2024 | C18: 2-3 | D18: 10 | E18: 1 | F18: Q1 | G18: Quadruple therapies show a higher eradication rate compared to standard triple therapy for Helicobacter pylori infection within the LEGACy consortium. A multicenter observational study in European and Latin American countries | H18: Patricio Medel-Jara, MPH, PhD; Diego Reyes Placencia, MD; Eduardo Fuentes-López, PhD; Oscar Corsi MD, MPH; Gonzalo Latorre, MD; Rosario Antón, MD; Elena Jiménez, PhD; Ana Miralles-Marco,PhD; Carmelo Caballero, MD, PhD; Hugo Boggino, MD; Daniel Cantero, MD; Rita Barros, BSc, PhD; João Santos- Antunes, MD, PhD; Marc Díez, MD; Luis A. Quiñones, Ph ; Erick Riquelme, PhD; Antonio Rollán, MD; Leslie C. Cerpa, PhD; Ivania Valdés PhD; Olga P. Nyssen, BSc, PhD; Leticia Moreira, MD, PhD; Javier P. Gisbert MD, PhD; M. Constanza Camargo, PhD; Nayeli Ortiz-Olvera; Alberto M. Leon-Takahashi, MD, MHA; Erika Ruiz-Garcia, Edith A. Fernández-Figueroa; Marcelo Garrido, MD; Gareth I. Owen, PhD, Andrés Cervantes, MD, PhD; Tania Fleitas, MD, PhD; Arnoldo Riquelme, MD | O18: 1 | P18: 6Digestive Medicine Department, Hospital Clínico Universitario de Valencia, Valencia, Spain/ 7Biochemistry Department and Molecular Biology, Universidad de Valencia, Valencia, Spain,/ 8INCLIVA Biomedical Research Institute, Valencia, Spain/ 24Servicio de Aparato Digestivo. Hospital Universitario de La Princesa, Instituto de Investigación Sanitaria Princesa (IIS‐Princesa), Universidad Autónoma de Madrid (UAM), Madrid, Spain,/ 25Centro de Investigación Biomédica en Red de Enfermedades Hepáticas y Digestivas (CIBERehd), Madrid, Spain/ 26Hospital Clínic de Barcelona, Centro de Investigación Biomédica en Red en Enfermedades Hepáticas y Digestivas (CIBERehd),/ IDIBAPS (Institut d’Investigacions Biomèdiques August Pi i Sunyer), University of Barcelona, Barcelona, Spain/ 27Division of Cancer Epidemiology and Genetics, National Cancer Institute, Rockville, Maryland, USA/ 28Departamento de Gastroenterología, UMAE, Hospital de Especialidades “Dr.Bernardo Sepúlveda”, Centro Médico Nacional Siglo XXI, IMSS, Ciudad de México, México/29Departamento de Gastroenterología, Instituto Nacional de Cancerología,Ciudad de México, México/ 30Laboratorio de Medicina Traslacional, Instituto Nacional de Cancerología, Ciudad de México, México 31Núcleo B de Innovación en Medicina de Precisión. Instituto Nacional de Medicina Genómica, Ciudad de México, México/ 9GenPat Laboratory, Asunción, Paraguay/ 10Endoscopy Department, Instituto de Previsión Social, Asunción, Paraguay/ 11IPATIMUP ‐ Institute of Pathology and Molecular Immunology of the University of Porto, Porto, Portugal/ 12Department of Pathology, Medical Faculty of the University of Porto, Porto, Portugal/ 13Department of Gastroenterology, Centro Hospitalar Universitário de S. João, Porto, Portugal/ 14Department of Gastroenterology, Medical Faculty of the University of Porto, Porto, Portugal/ 15Vall d'Hebron University, Barcelona, Spain/ 16Hospital‐Vall d’Hebron Institute of Oncology (VHIO), Barcelona, Spain/36Medical Oncology Department, Hospital Clínico Universitario de Valencia, Valencia, Spain | Q18: 1 | R18: 19Latin American Network for Implementation and Validation of Clinical Pharmacogenomics Guidelines (RELIVAF),3Doctorate Program, Integrative Genomics, Universidad Mayor, Santiago, Chile32Centro de Oncología de Precisión, Escuela de Medicina, Universidad Mayor, Santiago, Chile34Millennium Institute on Immunology and Immunotherapy, Santiago, Chile 35Advanced Center for Chronic Diseases, | U18: Publicada | Y18: United European Gastroenterology Journal | Z18: Si (50%) | AA18: Arnoldo Riquelme | AB18: 8 | AC18: USD 1465 | AD18: =1465*910.79 -> 1334307.3 | AF18: =AF17-AD18 -> 26315117 | AH18: 2024 | AI18: 1,10 | AJ18: https://doi.org/10.1002/ueg2.12605 | AK18: 2050-6414 | AM18: Quadruple therapies show a higher eradication rate compared to standard triple therapy for Helicobacter pylori infection within the LEGACy consortium. A multicenter observational study in European and Latin American countries - Medel‐Jara - United European Gastroenterology Journal - Wiley Online Library | AN18: 2
A19: 13 | B19: 2024 | C19: 3 | D19: 3 | F19: Q1 | G19: LINC00662 promotes aggressive traits by modulating OCT4 ex-pression through miR-335-5p in gallbladder cancer cells | H19: Pablo Pérez-Moreno, Ismael Riquelme, Carolina Bizama, Luis Vergara-Gómez, Julio C. Tapia, Priscilla Brebi, Patricia García and Juan C. Roa | Q19: 1 | R19: Institute of Biomedical Sciences, Faculty of Health Sciences, Universidad Autónoma de Chile, Temuco 4810101 | U19: Publicada | Y19: MDPI: International Journal Molecular Sciences | Z19: Si (50%) | AA19: Enrique Castellón | AB19: 9 | AC19: USD 1460,18 | AD19: =1460.18*910.79 -> 1329917.3 | AF19: =AF18-AD19 -> 24985200 | AH19: 2024 | AI19: 25, 6740-6752 | AJ19: 10.3390/ijms25126740 | AK19: 1422-0067 | AM19: IJMS | Free Full-Text | LINC00662 Promotes Aggressive Traits by Modulating OCT4 Expression through miR-335-5p in Gallbladder Cancer Cells (mdpi.com) | AN19: 2
A20: 14 | B20: 2024 | C20: 4 | D20: 4 | F20: Q2 | G20: Challenges for gene therapy in teh financial sustainability of the health systems: A scoping review | H20: Hugo Ossandón (HO), Nicolas Armijo (NA), Constanza Vargas (CV), Gabriela Repetto (GR), Manuel A. Espinoza (ME) | O20: 1 | P20: 3Centre for Health Economics Research and Evaluation (CHERE), University of Technology Sydney, Sydney, Australia | Q20: 1 | R20: 1Departamento de Coordinación de Garantías y Prestaciones de Salud, División de Planificación Sanitaria, Ministerio de Salud de Chile, Santiago, Chile, 2Centro de Investigación Clínica, Unidad de Evaluación de Tecnologías en Salud (ETESA UC), Pontificia Universidad Católica de Chile, Santiago, | U20: Publicada | Y20: Orphanet Journal of Rare Diseases | Z20: Si | AA20: Manuel Espinoza | AB20: 10 | AC20: USD 2387 | AD20: =2387*910.79 -> 2174055.7 | AF20: =AF19-AD20 -> 22811144 | AH20: 2024 | AI20: 19243 | AJ20: https://doi.org/10.1186/s13023-024-03249-z | AK20: 1750-1172 | AM20: Challenges for gene therapy in the financial sustainability of health systems: a scoping review | Orphanet Journal of Rare Diseases | Full Text (biomedcentral.com) | AN20: 2
A21: 15 | B21: 2024 | C21: 4 | D21: 4 | F21: Q3 | G21: Harnessing Health Technology Assessment in Latin America and the Caribbean: Keeping the Region on Course | H21: Ursula Giediona, Manuel Antonio Espinoza, Pamela Góngora-Salazar, Abha Mehndiratta, and Dan Ollendorffa | O21: 1 | P21: Center for Global Development, Washington, DC, USA; Social Protection and Health Division, Inter-American Development Bank, Washington, DC, USA; Nuffield Department of Population Health, University of Oxford, Oxford, UK; Center for Global Development, London, UK; Center for the Evaluation of Value and Risk in Health, Tufts Medical Center, Boston, MA, USA | U21: Publicada | Y21: Health Systems and Reform | Z21: No | AF21: =AF20-AD21 -> 22811144 | AH21: 2023 | AI21: 9, 2314482 | AJ21: 10.1080/23288604.2024.2314482 | AK21: 2328-8604 | AM21: Full article: Harnessing Health Technology Assessment in Latin America and the Caribbean: Keeping the Region on Course (tandfonline.com) | AN21: 2
A22: 16 | B22: 2024 | C22: 3 | D22: 3 | F22: Q1 | G22: A Comprehensive Analysis of the Effect of A>I(G) RNA-Editing Sites on Genotoxic Drug Response and Progression in Breast Cancer | H22: Yanara A. Bernal, Alejandro Blanco, Eduardo A. Sagredo, Karen Oróstica, Ivan Alfaro, Katherine Marcelain and Ricardo Armisén | O22: 1 | P22: Department of Molecular Biosciences, The Wenner-Gren Institute, Stockholm University, Svante Arrhenius, vag 20C, SE-106 91 Stockholm, Sweden | Q22: 1 | R22: Instituto de Investigación Interdisciplinaria, Vicerrectoría Académica, Universidad de Talca, | U22: Publicada | Y22: MDPI: Biomedicines | Z22: No | AF22: =AF21-AD22 -> 22811144 | AH22: 25-03-2024 | AI22: 12, 728 | AJ22: 10.3390/biomedicines12040728 | AK22: 2227-9059 | AM22: Biomedicines | Free Full-Text | A Comprehensive Analysis of the Effect of A>I(G) RNA-Editing Sites on Genotoxic Drug Response and Progression in Breast Cancer (mdpi.com) | AN22: 2
A23: 17 | B23: 2024 | C23: 3 | D23: 3 | F23: Q1 | G23: Exploring the impact of MiR-92a-3p on FOLFOX chemoresistance biomarker genes in colon cancer cell lines | H23: Paula I. Escalante, Luis A. Quiñones and Héctor R. Contreras | O23: 0 | Q23: 1 | R23: Latin American Network for the Implementation and Validation of Pharmacogenomic Clinical Guidelines (RELIVAF), Santiago, Chile, | U23: Publicada | Y23: Frontiers in Pharmacology | Z23: No | AF23: =AF22-AD23 -> 22811144 | AH23: 45569 | AI23: 15, 1376638 | AJ23: 10.3389/fphar.2024.1376638 | AK23: 1663-9812 | AM23: Frontiers | Exploring the impact of MiR-92a-3p on FOLFOX chemoresistance biomarker genes in colon cancer cell lines (frontiersin.org) | AN23: 2
A24: 18 | B24: 2024 | C24: 3 | D24: 3 | F24: Q1 | G24: Assessing the Occurrence and Influence of Cancer Chemotherapy-Related Pharmacogenetic Alleles in the Chilean Population | H24: Gareth I. Owen, Miguel Cordova-Delgado, Bernabé I. Bustos, Leslie C. Cerpa, Pamela Gonzalez, Sebastián Morales-Pison, Benjamín Garcia-Bloj, Marcelo Garrido, Juan Francisco Miquel and Luis A. Quiñones | O24: 1 | P24: Ken and Ruth Davee Department of Neurology, Simpson Querrey Center for Neurogenetics, Feinberg School of Medicine, Northwestern University, Chicago, IL 60611, USA | Q24: 1 | R24: Advanced Center for Chronic Diseases (ACCDiS), Santiago 8330034, Chile, Millennium Institute on Immunology and Immunotherapy, Santiago 8331150, Chile, Latin American Network for Implementation and Validation of Clinical Pharmacogenomics Guidelines (RELIVAF-CYTED), Santiago, Centro de Oncología de Precisión (COP), Facultad de Medicina y Ciencias de la Salud, Universidad Mayor,Santiago 7560908, ChileSAGA, Centro de Estudios Clínicos, Santiago 7610315, Chile Department of Oncología, Clínica Indisa, Santiago 7520440, Chile,, | U24: Publicada | Y24: MDPI: Pharmaceutics | Z24: No | AF24: =AF23-AD24 -> 22811144 | AH24: 45539 | AI24: 16, 561 | AJ24: 10.3390/pharmaceutics16040561 | AK24: 1999-4923 | AM24: https://doi.org/10.3390/pharmaceutics16040561 | AN24: 2
A25: 19 | B25: 2024 | C25: 2-3 | D25: 10 | E25: 1 | F25: Q2 | G25: Clinical and Genomic Characterization of ERBB2-altered Gallbladder Cancer: exploring differences between an American and a Chilean cohort | H25: Sebastián Mondaca, Henry Walch, Santiago Sepúlveda, Nikolaus Schultz, Gonzalo Muñoz, Amin Yaqubie, Patricia Macanas, Claudia Pareja, Patricia Garcia, Walid Chatila, Bruno Nervi, Bob Li, James J. Harding, Paola Viviani, Juan Carlos Roa, Ghassan K. Abou-Alfa | O25: 1 | P25: 2Marie-Josée and Henry R. Kravis Center for Molecular Oncology, Memorial Sloan Kettering Cancer Center, New York, NY/ 4Department of Medicine, Memorial Sloan Kettering Cancer Center, New York, NY, USA/ 6Weill Medical College at Cornell University, Cancer Center, New York, NY, USA/ 8Trinity College, Dublin Medical School, Dublin, Ireland | Q25: 0 | U25: Publicada | W25: APC600553511 | X25: 45485 | Y25: JCO Global Oncology | Z25: SI | AA25: Bruno Nervi | AB25: 11 | AC25: USD 2200 solo 50% US 1100 | AD25: 1042129 | AF25: =AF24-AD25 -> 21769015 | AH25: 45575 | AI25: 10, e2400090 | AJ25: https://doi.org/10.1200/GO.24.00090 | AK25: 2687-8941 | AM25: Clinical and Genomic Characterization of ERBB2-Altered Gallbladder Cancer: Exploring Differences Between an American and a Chilean Cohort | JCO Global Oncology | AN25: 2
A26: 20 | B26: 2024 | C26: 2 | D26: 2 | F26: Q1 | G26: Gene content, phage cycle regulation model and prophage inactivation disclosed by prophage genomics in the Helicobacter pylori Genome Project | H26: Filipa F. Vale, HpGP Research Network, Richard J. Robertsc, Ichizo Kobayashid, M. Constanza Camargo, and Charles S. Rabkinh | O26: 1 | P26: aBioISI – Instituto de Biossistemas e Ciências Integrativas, Faculdade de Ciências, Universidade de Lisboa, Lisbon, Portugal; bResearch Institute for Medicines (iMed-ULisboa), Faculty of Pharmacy, Universidade de Lisboa, Lisbon, Portugal; cNew England Biolabs, Ipswich, MA, USA; dResearch Center for Micro-Nano Technology, Hosei University, Tokyo, Japan; eDepartment of Computational Biology and Medical Sciences, Graduate School of Frontier Sciences, University of Tokyo, Tokyo, Japan; fInstitute of Medical Science, University of Tokyo, Tokyo, Japan; gLaboratory of Genome Informatics, National Institute for Basic Biology, Okazaki, Aichi, Japan; hDivision of Cancer Epidemiology and Genetics, National Cancer Institute, Rockville, MD, US | Q26: 0 | U26: Publicada | Y26: GUT MICROBES | Z26: no | AF26: =AF25-AD26 -> 21769015 | AH26: 45634 | AI26: 16, 2379440 | AJ26: https://doi.org/10.1080/19490976.2024.2379440 | AK26: 1949-0984 | AM26: Full article: Gene content, phage cycle regulation model and prophage inactivation disclosed by prophage genomics in the Helicobacter pylori Genome Project (tandfonline.com) | AN26: 2
A27: 21 | B27: 2024 | C27: 4 | D27: 4 | F27: Q4 | G27: Diagnóstico y etapificación de cáncer de mama en Chile: estudio por encuesta no probabilística de frecuencia y tiempos | H27: Carla Campañaa, Marcela Oyarte, Báltica Cabieses,Alexandra Obach | O27: 0 | Q27: 0 | U27: Publicada | Y27: Medwave | Z27: SI | AA27: Manuel Espinoza | AB27: 12 | AC27: 800000 | AD27: 800000 | AF27: =AF26-AD27 -> 20969015 | AH27: 14-10-2024 | AI27: 24, e2801 | AJ27: 10.5867/medwave.2024.09.2801 | AK27: 0717-6384 | AM27: Diagnóstico y etapificación de cáncer de mama en Chile: estudio por encuesta no probabilística de III a IV frecuencia y tiempos - Medwave | AN27: 2
A28: 22 | B28: 2024 | C28: 2 | D28: 2 | F28: Q1 | G28: Implementation of Cancer Prevention Practices in Primary Care: Reesults of a Cohort Study in Chile 2018-2022 | H28: Klaus Puschel, Andrea Rioseco, Mauricio Soto, Gabriela Soto, Sarah Paz, Javiera Martinez, Eduardo Arenas, Marcela Faundez, Augusto Leon, Jon Emery, Beti Thompson | O28: 1 | P28: c Department of General Practice and Centre for Cancer Research, University of Melbourne, Victoria, Australia d Public Health Division, Fred Hutchinson Cancer Research Center, Seattle, WA, USA | Q28: 0 | T28: 40 | U28: Publicada | W28: OAD0000464806 | X28: 45518 | Y28: Public Health | Z28: SI | AA28: Klaus Puschel | AB28: 13 | AC28: USD 2950 | AD28: =2950*922.58 -> 2721611 | AF28: =AF27-AD28 -> 18247404 | AH28: Septiembre 2024 | AI28: 236, 168-174 | AJ28: https://doi.org/10.1016/j.puhe.2024.08.006 | AK28: 2666-5352 | AM28: Implementation of cancer prevention practices in primary care: results of a cohort study in Chile 2018–2022 - ScienceDirect | AN28: 2
A29: 23 | B29: 2023 | C29: 2 | D29: 2 | F29: Q1 | G29: Cyclooxygenase-2 Blockade Is Crucial to Restore Natural Killer Cell Activity before Anti-CTLA-4 Therapy against High-Grade Serous Ovarian Cancer | H29: Fernán Gómez-Valenzuela, Ignacio Wichmann, Felipe Suárez, Sumie Kato, Enrique Ossandón, Marcela Hermoso, Elmer A. Fernández and Mauricio A. Cuello | O29: 1 | P29: 4 4Division of Oncology, Department of Medicine, School of Medicine, Stanford University, Stanford, CA 94305, USA/ 6- Fundación para el Progreso de la Medicina (CONICET), Córdoba X5000, Argentina/7 Facultad de Ciencias Exactas, Físicas y Naturales, Universidad Nacional de Córdoba, Córdoba X5000, Argentina | Q29: 0 | U29: Publicada | Y29: MDPI: CANCERS | Z29: NO | AF29: =AF28-AD29 -> 18247404 | AH29: 45282 | AI29: 16, 80 | AJ29: https://doi.org/ 10.3390/cancers16010080 | AK29: 2072-6694 | AM29: Cyclooxygenase-2 Blockade Is Crucial to Restore Natural Killer Cell Activity before Anti-CTLA-4 Therapy against High-Grade Serous Ovarian Cancer (mdpi.com) | AN29: 2
A30: 24 | B30: 2024 | C30: 2 | D30: 2 | F30: Q2 | G30: Statin use is not associated with inflammation among Chilean women of Mapuche and non-Mapuche ancestry with gallstones | H30: Sarah S Jackson, Marina Lex, Vanessa Van De Wyngard, Paz Cook, Allan Hildesheim, Ligia A Pinto, Sharon H Jackson, Kelvin Choi, Tsion Zewdu Minas, Héctor Fabio Losada Morales, Juan Carlos Araya, Catterina Ferreccio, Jill Koshiol & Ruth M Pfeiffer | O30: 1 | P30: 1Division of Cancer Epidemiology & Genetics, National Cancer Institute, Rockville, MD, USA 2Department of Mathematics, The Technical University of Munich, Munich, Germany/ 5Frederick National Laboratory for Cancer Research, National Cancer Institute, Frederick, MD, USA 6Division of Intramural Research, National Institute on Minority Health & Health Disparities, Bethesda, MD, USA 7Laboratory of Human Carcinogenesis, Center for Cancer Research, National Cancer Institute, National Institutes of Health, Bethesda, MD, USA | Q30: 1 | R30: 4Advanced Center for Chronic Diseases (ACCDiS), FONDAP, Santiago, Chile/ 9Hepato-pancreatic & biliary surgery team, Hospital Dr. Herna´n Henriquez Aravena, Temuco, Chile/ 10Laboratorio de Inmunopatolog´ıa Traslacional, Facultad de Ciencias, Universidad Mayor, Chile | U30: Publicada | Y30: Future Sci. OA | Z30: NO | AF30: =AF29-AD30 -> 18247404 | AH30: 45454 | AI30: 10, 2340327 | AJ30: https://doi.org/10.2144/fsoa-2023-0032 | AK30: 2056-5623 | AM30: Full article: Statin use is not associated with inflammation among Chilean women of Mapuche and non-Mapuche ancestry with gallstones (tandfonline.com) | AN30: 2
A31: 25 | B31: 2024 | C31: 2 | D31: 2 | F31: Q1 | G31: Cholecystectomy and digestive cancer in Chile: Complementary results from interrupted time series and aggregated data analyses | H31: Constanza Gonzalez, Alfonso García-Pérez, Bruno Nervi, César Munoz, Erik Morales, Hector Losada, Gina Merino-Pereira, Francisco Rothhammer, Justo Lorenzo Bermejo | O31: 1 | P31: 1Statistical Genetics Research Group, Institute of Medical Biometry, Heidelberg University, Heidelberg, Germany/3Departamento de Estadística, Universidad Nacional de Educación a Distancia (UNED), Madrid, Spain | Q31: 1 | R31: 5Hospital Regional de Talca, Talca, Chile/8Departamento Manejo Integral del Cáncer y Otros Tumores, Subsecretaria de Salud Pública, Ministerio de Salud de Chile, Santiago, Chile / 9Instituto de Alta Investigación, Tarapacá University, Arica, Chile | U31: Aceptada | Y31: Int. J. Cancer | Z31: NO | AF31: =AF30-AD31 -> 18247404 | AH31: 16-ago-24 | AI31: na:1-13 | AJ31: https://doi.org/10.1002/ijc.35138 | AK31: 1097-0215 | AM31: Cholecystectomy and digestive cancer in Chile: Complementary results from interrupted time series and aggregated data analyses - Gonzalez - International Journal of Cancer - Wiley Online Library
A32: 26 | B32: 2024 | C32: 1 | D32: 1 | F32: Q1 | G32: National health examination surveys; a source of critical data | H32: Paula Margozzini,a Hanna Tolonen,b Antonio Bernabe-Ortiz,c Sarah Cuschieri,d Chiara Donfrancesco,e Luigi Palmieri,e Luz Maria Sanchez-Romero,f Jennifer S Mindellg & Oyinlola Oyebodeh | O32: 1 | P32: b Finnish Institute for Health and Welfare, Helsinki, Finland. c Universidad Científica del Sur, Lima, Peru. d Faculty of Medicine and Surgery, University of Malta, Msida, Malta. e Istituto Superiore di Sanità, Rome, Italy. f Department of Oncology, Georgetown University Medical Centre, Washington DC., United States of America. g Department of Epidemiology and Public Health, University College London, 1–19 Torrington Place, London, WC1E 6BT, England. h Wolfson Institute of Population Health, Queen Mary University of London, London, England. | R32: a Department of Public Health, Pontificia Universidad Católica de Chile, Santiago, Chile. | T32: 0.5 | Y32: Bull World Health Organ | Z32: NO | AF32: =AF31-AD32 -> 18247404 | AH32: 45447 | AI32: 102:588-599 | AJ32: http://dx.doi.org/10.2471/BLT.24.291783 | AK32: 0042-9686 | AM32: Bulletin of the World Health Organization (nih.gov) | AN32: 2
A33: 27 | B33: 2024 | C33: 1 | D33: 1 | F33: Q4 | G33: Comorbilidad entre obesidad y tabaquismo, y su asociación con factores de riesgo cardiometabólicos: Resultados de la Encuesta Nacional de Salud 2016-2017 | H33: Rodrigo Santis 1, Francisco Del Río 1, Claudia Bambs 2, Paula Margozzini 2, Marcela Babul 1, Florencia Santis a, Sofía Herrera 1 | O33: 0 | R33: 1Departamento de Psiquiatría, Facultad de Medicina, Pontificia Universidad Católica de Chile. Diagonal Paraguay 362, 5to piso, Santiago, Chile. 2Departamento de Salud Pública, Facultad de Medicina, Pontificia Universidad Católica de Chile. Diagonal, Paraguay 362, Segundo piso, Santiago, Chile. 3Centro Avanzado de Enfermedades Crónicas ACCDiS (FONDAP 1513001). Sergio Livingstone 1007, Independencia, Santiago, Chile. 4Centro para la Prevención y el Control del Cáncer CECAN. Santiago, Chile. aEstudiante de Medicina, Escuela de Medicina, Pontificia Universidad Católica de Chile. | T33: 0.5 | U33: Publicada | Y33: Revista Médica de Chile | Z33: NO | AF33: =AF32-AD33 -> 18247404 | AH33: ene-24 | AI33: 152-8-18 | AJ33: http://dx.doi.org/10.4067/s0034-98872024000100007 | AK33: 0034-9887 | AM33: Comorbilidad entre obesidad y tabaquismo, y su asociación con factores de riesgo cardiometabólicos: Resultados de la Encuesta Nacional de Salud 2016-2017 (scielo.cl) | AN33: 2
A34: 28 | B34: 2024 | C34: 2 | D34: 2 | F34: Q1 | G34: Community preparedness for natural hazards in two Chilean coastal cities | H34: Castañeda, J. V., Repetto, P. B., Bronfman, N. C., & Cisternas, P. C. | O34: 0 | Q34: 1 | R34: a Department of Psychology, Pontificia Universidad Católica de Chile, Santiago, Chile; b Research Center for Integrated Disaster Risk Management (CIGIDEN), ANID/FONDAP/1523A0009 Santiago, Chile; d Engineering Sciences Department, Universidad Andres Bello, Santiago, Chile; e Industrial and Systems Engineering Department, Pontificia Universidad Católica de Chile, Santiago, Chile, | T34: 0 | Y34: Journal of Risk Research | Z34: NO | AF34: =AF33-AD34 -> 18247404 | AH34: 45573 | AI34: 2024,1-21 | AJ34: https://doi.org/10.1080/13669877.2024.2387355 | AK34: 1466-4461 | AM34: Full article: Community preparedness for natural hazards in two Chilean coastal cities | AN34: 2
A35: 29 | B35: 2024 | C35: 4-5 | D35: 10 | E35: 1 | F35: Q1 | G35: Improving efficiency in healtcare: lessons from succesful health policies in Chile | H35: Espinoza, MA., Zamorano, P., Zuñiga-San Martin, C., Taramasco, C., Martinez, F., Becerra, S., Letelier, MJ., Armijo, N. | O35: 0 | Q35: 1 | R35: a Center for Cancer Prevention and Control, Santiago, Chile/ b Escuela de Salud Pública, Pontificia Universidad Católica de Chile, Santiago, Chile/ c Centro de Innovación Ancora UC, Pontificia Universidad Católica de Chile, Santiago, Chile/d Universidad Católica de la Santísima Concepción, Concepción, Chile/ e Instituto de Tecnología para la Innovación en Salud y Bienestar, Facultad de Ingeniería, Universidad Andrés Bello, Santiago, Chile/ f Departamento de Salud Digital, Ministerio de Salud, Santiago, Chile g Escuela de Medicina, Facultad de Medicina, Universidad Andrés Bello, Viña del Mar, Chile | W35: OAD0000486594 | X35: 45572 | Y35: Archives of Medical Research | Z35: SI | AB35: 14 | AC35: USD 2.740 | AD35: =2750*949.34 -> 2610685 | AF35: =AF34-AD35 -> 15636719 | AH35: ene-25 | AI35: 56, 103105 | AJ35: https://doi.org/10.1016/j.arcmed.2024.103105 | AK35: 1873-5487 | AM35: Improving Efficiency in Healthcare: Lessons from Successful Health Policies in Chile - ScienceDirect | AN35: 2
A36: 30 | B36: 2024 | C36: 2 | D36: 2 | F36: Q1 | G36: Global Assessment of Palliative Care Need: Serious Health-Related Suffering Measurement Methodology | H36: Xiaoxiao J. Kwete, MBBS,MSc, Afsan Bhadelia,PhD y, Héctor Arreola-Ornelas, MSc, Oscar Mendez, William E. Rosa, PhD, MBE, APRN, Stephen Connor, PhD, Julia Downing, PhD,MMedSci,RGN, Dean Jamison, PhD, David Watkins, MD, MPH, Renzo Calderon, PhD, Jim Cleary, MD, Joseph R. Friedman, PhD, MPH, Liliana De Lima, MSc, Christian Ntizimira, MD, MSc, Tania Pastrana, PD, Dr.med.Dipl.,Pedro E. Pérez-Cruz, MD,MPH, Dingle Spence, BSc, ,DMRT,DipPall.Med,FRCR, M.R.Rajagopal, MD, Valentina Vargas Enciso, MSc, Eric L. Krakauer, PhD, Lukas Radbruch, MD,and Felicia Marie Knaul, PhD | O36: 1 | P36: 1 University of Miami Institute for Advanced Study of the Americas, University of Miami (X.J.K., A.B., H.A.-O., W.E.R., R.C., V.V.E., F.M.K.), Miami, Florida, USA 2 Department of Public Health, College of Health and Human Sciences (A.B.), Purdue University, West Lafayette, Indiana, USA 3 Institute for Obesity Research, Tecnologico de Monterrey (H.A.-O.), Monterrey, Mexico 4 School of Government and Public Transformation, Tecnologico de Monterrey, Mexico City, Mexico 5 Tómatelo a Pecho, A.C. (H.A-O., O.M., F.M.K.), Mexico City, Mexico 6 Fundación Mexicana para la Salud (FUNSALUD) (H.A.-O.), Mexico City, México 7 Department of Psychiatry and Behavioral Sciences (W.E.R.), Memorial Sloan Kettering Cancer Center, New York, New York, USA 8 Worldwide Hospice Palliative Care Alliance (S.C.), London, UK 9 International Children's Palliative Care Network (J.D.), Bristol, UK 10 University of California (D.J.), San Francisco, California, USA 11 Department of Global Health, University of Washington (D.W.), Seattle, Washington, USA 12 Indiana University School of Medicine (J.C.), Indianapolis, Indiana, USA 13 Center for Social Medicine and Humanities, University of California, Los Angeles, California, USA 14 International Association of Hospice and Palliative Care (L.D.L.), Houston, Texas, USA 15 African Center for Research on End of Life Care (C.N.), Kigali, Rwanda 16 Department of Palliative Medicine, Medical Faculty, RWTH Aachen University, Aachen, Germany 17 Sección Medicina Paliativa, Facultad de Medicina, Pontificia Universidad Católica de Chile, Santiago, Chile 18 Centro para la Prevención y el Control del Cáncer (CECAN), Pontificia Universidad Católica de Chile, Santiago, Chile 19 University of the West Indies (D.S.), Mona, Jamaica 20 Pallium India Trust (M.R.R.), Kerala, India 21 Department of Global Health & Social Medicine, Harvard Medical School (E.L.K.), Boston, Massachusetts, USA 22 Sylvester Comprehensive Cancer Center, Miller School of Medicine (F.M.K.), University of Miami, Miami, Florida, USA 23 Leonard M. Miller School of Medicine (F.M.K.), University of Miami, Miami, Florida, USA | Y36: Journal of Pain and Symptom Management | AF36: =AF35-AD36 -> 15636719 | AH36: ago-24 | AI36: 68, e116- e137 | AJ36: https://doi.org/10.1016/j.jpainsymman.2024.03.027 | AK36: 1873-6513 | AM36: Global Assessment of Palliative Care Need: Serious Health-Related Suffering Measurement Methodology - ScienceDirect | AN36: 2
A37: 31 | B37: 2024 | C37: 3 | D37: 3 | F37: Q2 | G37: Beyond tobacco: genomic disparities in lung cancer between smokers and never-smokers. | H37: Javiera Garrido, Yanara Bernal, Evelin González, Alejandro Blanco, Gonzalo Sepúlveda‑Hermosilla, Matías Freire, Karen Oróstica, Solange Rivas, Katherine Marcelain, Gareth Owen, Carolina Ibañez,Alejandro Corvalan, Marcelo Garrido, Rodrigo Assar, Rodrigo Lizana, Javier Cáceres‑Molina,Diego Ampuero, Liliana Ramos, Paola Pérez, Osvaldo Aren, Sara Chernilo, Cristina Fernández,María Loreto Spencer, Jacqueline Flores Aguila, Giuliano Bernal Dossetto, Mónica Ahumada Olea, Germán Rasse, Carolina Sánchez, Maria Galli de Amorim, Thais F. Bartelli, Diana Noronha Nunes, Emmanuel Dias‑Neto, Helano C. Freitas and Ricardo Armisén | O37: 1 | P37: 8 NIDCR, National Institute of Health, Bethesda, USA. /17 Laboratory of Medical Genomics, A. C. Camargo Cancer Center, Sao Paulo, Brazil./18 Department of Clinical Oncology, A.C. Camargo Cancer Center, Sao Paulo, Brazil/ 20 Department of Radiation Oncology, Cancer Institute of New Jersey, Rutgers University, Newark, NJ, USA. | Q37: 1 | R37: 1 Centro Genética y Genómica, Instituto de Ciencias E Innovación en Medicina, Facultad de Medicina Clínica Alemana, Universidad del Desarrollo, Santiago, Chile. 2 Departamento de Oncología Básico Clínica, Facultad de Medicina, Universidad de Chile, Santiago, Chile. 3 Centro Para La Prevención y el Control del Cáncer, Universidad de Chile, Santiago, Chile. 4 Departamento de Hematología y Oncología and Advanced Center for Chronic Diseases, Pontificia Universidad Católica de Chile, Santiago, Chile. 5 Centro de Oncología de Precisión, Universidad Mayor, Santiago, Chile /6 CORFO Center of Excellence in Precision Medicine Pfizer, Santiago, Chile. 7 Instituto de Ciencias Biomédicas, Facultad de Medicina, Universidad de Chile, Santiago, Chile. 9 Centro de Investigación Clínica Bradford Hill, Santiago, Chile/ 10 Instituto Nacional del Tórax, Santiago, Chile/11 Departamento de Patología, Hospital Clínico Regional de Concepción Dr. Guillermo Grant Benavente Chile, Concepcion, Chile/12 Departamento de Salud Pública, Facultad de Medicina, Universidad Católica del Norte, La Serena, Chile. 13 Departamento de Ciencias Biomédicas, Facultad de Medicina, Universidad Católica Del Norte, La Serena, Chile/ 14 Departamento de Medicina Interna, Servicio de Oncología, Hospital Clínico de La Universidad de Chile, Santiago, Chile./15 Hospital de Puerto Montt, Puerto Montt, Chile. /16 Centro de Genómica y Bioinformática, Universidad Mayor, Santiago, Chile./19 Instituto de Investigación Interdisciplinario, Vicerrectoría Académica, Universidad de Talca, Talca, Chile/ 21 Millennium Institute for Immunology and Immunotherapy, Santiago, Chile. | Y37: BMC Cancer | AF37: =AF36-AD37 -> 15636719 | AJ37: https://doi.org/10.1186/s12885-024-12737-1
E38: =SUM(E7:E37) -> 8 | O38: =SUM(O7:O37) -> 16 | Q38: =SUM(Q7:Q37) -> 19 | Y38: TOTAL | AA38: TOTAL Inf de Avance 2024-Ppto 2024 | AD38: =SUM(AD11:AD37) -> 20363281
Y39: 8 publicaciones del Informe de Avance 2025 fueron financiadas con fondos 2024 | AD39: 20022541
G40: Actualizado por Carolina Cabrera: 14-05-2025 | AB40: Total gastado ppto 2024 | AD40: =SUM(AD38:AD39) -> 40385822

Sheet  Publicaciones año 1
I2: REGISTRO DE PUBLICACIONES | AJ2: ENVIAR PDF DE LA PUBLICACION A ccabrerav@uc.cl con copia a cgoicb@uc.cl y a cecan@uc.cl
I4: INFORMADO A ANID - INFORME DE AVANCE NR. 1
I5: 2023 | AJ5: Los casilleros de este color deben ser llenados cuando la publicacion se haya relizado
C6: Completar para solicitud de financiamiento | AH6: Saldo UC | AI6: Saldo UCH | AJ6: COMPLETAR CUANDO EL PAPER HA SIDO PUBLICADO
A7: Nr. | B7: Año Publicacion | C7: WP | D7: WP consignado | E7: Nr pub con otros WP | F7: ISI Q1-Q4 | I7: Nombre publicación | J7: Autores | K7: Número Investigadores CECAN | L7: Nombre investigadores CECAN (Debe incluir 2 ó más) | M7: Nombre Investigadores Asociados CECAN participante | N7: Nombre Postdoc CECAN participante | O7: Nombre Tesistas CECAN participante | P7: Nombre investigadores externos | R7: Publicación con Institución Internacional | T7: Publicación con Institución Nacional | U7: Objetivo Directo/ Asociado CECAN (Identifíquelo Ej: WP-1 proyecto 1) | V7: Funding % | W7: Estado de la Publicación | X7: Fecha estimada de publicación (En preparación/enviada) | Y7: Invoice Nr. | Z7: Fecha Invoice | AA7: Revista | AB7: Financiamiento CECAN | AC7: Solicitud de apoyo solicitado por | AD7: Nr. Solicitud de apoyo | AE7: Valor Publicación revista | AF7: Valor $ pagado por UC | AG7: Valor $ pagado por UCH | AJ7: Fecha de publicación | AK7: Volúmen. Pág. Inicio y final | AL7: DOI | AM7: ISSN | AN7: Nr. Productividad | AO7: Link paper | AP7: Informado en Informe de Avance
A8: 1 | B8: 2023 | C8: 1-2 | D8: 10 | E8: 1 | F8: Q3 | I8: “Appagalo” a Customized Mobile Health Intervention (mHealth) for Smoking Cessation in Women: A Randomized Controlled Trial | J8: Javiera Martinez-Gutierrez; Angélica Domínguez; Carolina López; Juan Alcántara; Carolina Althausen; Mildred Rojas; Leonardo Véjar; Claudia Bambs | Q8: 1 | R8: 2Department of General Practice, School of Medicine, Dentistry, and Health Services, University of Melbourne, Melbourne, VIC, Australia | S8: 1 | T8: 5Smoking Cessation Program, Christus UC Medical Network, Santiago, Chile. 6Smoking Cessation Program, Servicio de Salud Metropolitano Sur Oriente, Santiago | AA8: Tobacco Use Insights | AB8: No | AJ8: 44978 | AK8: 16. 1-14 | AL8: DOI: 10.1177/1179173X231152316 | AM8: 1179-173X | AO8: https://pubmed.ncbi.nlm.nih.gov/36844174/ | AP8: 1
A9: 2 | B9: 2023 | C9: 2 | D9: 2 | F9: Q3 | I9: The Clinical Impact and Cost-Effectiveness of Surveillance of Incidentally-Detected Gastric Intestinal Metaplasia: A Microsimulation Analyses | J9: Nikhil R Thiruvengadam, Shashank Gupta, Seth Buller, Imad Awad, Devika Gandhi, Allison Ibarra, Gonzalo Latorre, Arnoldo Riquelme, Michael L Kochman, Gregory Cote, Shailja C Shah, Monica Saumoy | Q9: 1 | R9: 1Division of Gastroenterology and Hepatology, Loma Linda University Health, Loma Linda, California; 2Department of Medicine, Loma Linda University Health, Loma Linda, California; 3Loma Linda University School of Medicine, Loma Linda, California; 4Division of Gastroenterology, University of California San Diego, San Diego, California7Division of Gastroenterology and Hepatology, Perelman School of Medicine, Philadelphia, Pennsylvania; 8Division of Gastroenterology and Hepatology, Oregon Health & Science University, Portland, Oregon; 9Gastroenterology Section, Veterans Affairs San Diego Healthcare System, San Diego, California; and 10Center for Digestive Health, Penn Medicine Princeton Medical Center, Plainsboro, New Jersey; | S9: 0 | AA9: Gastroenterología y Hepatología | AB9: No | AJ9: 45086 | AK9: 451-452 | AL9: doi: 10.1016/j.cgh.2023.05.028 | AM9: 1542-3565 | AO9: https://pubmed.ncbi.nlm.nih.gov/37302442/ | AP9: 1
A10: 3 | B10: 2023 | C10: 2-3 | D10: 10 | E10: 1 | F10: Q3 | I10: Implementation of the Updated Sydney System biopsy protocol improves the diagnostic yield of gastric preneoplastic conditions: results from a real-world study | J10: Gonzalo Latorre 1, José Ignacio Vargas 1, Shailja C Shah 2, Danisa Ivanovic-Zuvic 3, Pablo Achurra 4, Martín Fritzsche 5, Jai-Sen Leung 5, Bernardita Ramos 5, Elisa Jensen 5, Javier Uribe 1, Isabella Montero 5, Vicente Gandara 5, Camila Robles 5, Miguel Bustamante 5, Felipe Silva 5, Eitan Dukes 5, Oscar Corsi 1, Francisca Martínez 5, Victoria Binder 5, Roberto Candia 1, Robinson González 1, Alberto Espino 1, Carlos Agüero 1, Allan Sharp 4, Javiera Torres 6, Juan Carlos Roa 7, Margarita Pizarro 1, Alejandro H Corvalan 8, Charles S Rabkin 9, M Constanza Camargo 9, Arnoldo Riquelme 10 | Q10: 1 | R10: b Gastroenterology Section, Veterans Affairs, San Diego Healthcare System, San Diego, CA, USA c Division of Gastroenterology, University of California, San Diego, San Diego, CA, USA/ Division of Cancer Epidemiology and Genetics, National Cancer Institute, Rockville, MD, USA | S10: 1 | T10: Advanced Center for Chronic Diseases (ACCDIS), Santiago, Chile | AA10: Gastroenterología y Hepatología | AB10: No | AJ10: 45147 | AK10: 391-396 | AL10: doi: 10.1016/j.gastrohep.2023.08.005 | AM10: 1578-9519 | AO10: https://pubmed.ncbi.nlm.nih.gov/37598725/ | AP10: 1
